Workbook
Name Slicer_Application_Status: #N/A
Name Slicer_Month: #N/A
Name Slicer_Year1: #N/A

Sheet Overview
I3: Total Financing | K3: Total Amount Paid | M3: Outstanding Balance | O3: Interest Income
I4: ='Analysis - financing'!I10 -> 117619700
I5: ='Analysis - financing'!$O$7 -> 979710200 | J5: ='Analysis - financing'!$AE$7 -> 117619700
I6: =IF('Analysis - financing'!$Z$8>0,"▲ "&TEXT('Analysis - financing'!$Z$8,"0.0%"),IF('Analysis - financing'!Z8<0,"▼ "&TEXT(ABS('Analysis - financing'!$Z$8),"0.0%"),"— 0.0%")) -> ▼ 16.9%
D14: Line Chart

Sheet Application
I3: Total Applications | K3: Approved Application | M3: Approval Rate | O3: Rejection Rate
D14: Line Chart

Sheet Insight

Sheet Analysis - financing
C2: =TODAY() -> 46270
C4: ="DATA AS OF "&TEXT(MAX(tbl_LoanData[Application Date]),"mmm d, yyyy") -> DATA AS OF Aug 25, 2026 | J4: ='Analysis - financing'!CD15 -> 0.76047904
AD5: Total Financing
O6: Look Up for last YTD | T6: Total Financing Look Up for last MTD | Y6: Total Financing | Z6: Table Helper | AD6: Look Up for last MTD
O7: =LOOKUP(9.99999999999999E+307,Q17:Q1000) -> 979710200 | T7: =LOOKUP(9.99999999999999E+307,U17:U1000) -> 83659000 | Y7: Previous MoM% | AD7: =LOOKUP(9.99999999999999E+307,AD17:AD1000) -> 46204 | AE7: =LOOKUP(9.99999999999999E+307,AE17:AE1000) -> 117619700 | BU7: Total Applications | BV7: =SUM(BV14:BV500) -> 1364 | BY7: Total Approved Application | BZ7: =SUM(BZ14:BZ500) -> 127
Y8: =AD7 -> 46204 | Z8: =INDEX(AA16:AA72,MATCH($AD$7,Y16:Y72,0)) -> -0.16852151 | BY8: Approval Rate | BZ8: =BZ7/BV7 -> 0.093108504
I9: Total Financing | J9: Total Amount Paid | K9: Outstanding Balance | L9: Intrest Income | BY9: Rejection Rate
I10: =SUM(I17:I25) -> 117619700 | J10: =SUM(J17:J25) -> 966456.05 | K10: =SUM(K17:K25) -> 1.5346928e+08 | L10: =SUM(L17:L25) -> 36816037
BU12: Application Count | BY12: Application Status | BZ12: Approved
O13: Application Status | P13: Approved
C14: Application Status | D14: Approved | H14: Application Status | I14: Approved | O14: Year | P14: 2026 | T14: Application Status | U14: Approved | Y14: Application Status | Z14: Approved | AD14: Application Status | AE14: Approved | AM14: Application Status | AN14: Approved | AR14: Application Status | AS14: Approved | AW14: Application Status | AX14: Approved | BB14: Application Status | BC14: Approved | BG14: Application Status | BH14: Approved | BL14: Application Status | BM14: Approved | BP14: Application Status | BQ14: Approved | BU14: Date | BV14: Count of Application Status | BW14: Sum of Approved Helper | BY14: Date | BZ14: Approved Application | CC14: Status | CD14: Status Percentage | CG14: Status | CH14: Count of Age Bracket
BU15: 46023 | BV15: 194 | BW15: 149 | BY15: 46204 | BZ15: 127 | CC15: Approved | CD15: 0.76047904 | CG15: 18-24 | CH15: 11
C16: Sum of Loan Amount | D16: Approved Customers | E16: Average of Loan amount | H16: Row Labels | I16: Sum of Loan Amount | J16: Sum of Amount Paid | K16: Sum of Outstanding Balance | L16: Sum of Interest Income | O16: Date | P16: Sum of Loan Amount | Q16: Running Total In | T16: Date | U16: Total Loans | Y16: Date | Z16: Total Loans | AA16: MoM% | AD16: Date | AE16: Total Loans | AI16: Status | AJ16: Customers | AM16: Status | AN16: Customers | AR16: Brand | AS16: Total Approved Amount | AW16: Branch | AX16: Total Approved Amount | BB16: Vehicle Type | BC16: Total Approved Amount | BG16: Vehicle Type | BH16: Count of Vehicle Type | BL16: Gender | BM16: Count of Gender | BP16: Loan Status | BQ16: Count of Loan Status | BU16: 46054 | BV16: 147 | BW16: 115 | CC16: Pending | CD16: 0.10778443 | CG16: 25-34 | CH16: 34
C17: 117619700 | D17: 127 | E17: 926139.37 | H17: 2026 | I17: 117619700 | J17: 966456.05 | K17: 1.5346928e+08 | L17: 36816037 | O17: January | P17: 151982000 | Q17: 151982000 | T17: 46023 | U17: 151982000 | Y17: 44927 | Z17: 135232300 | AD17: 46204 | AE17: 117619700 | AI17: Low Risk | AJ17: 125 | AM17: Medium RIsk | AN17: 0.015748031 | AR17: Toyota | AS17: 23155300 | AW17: Davao | AX17: 12114300 | BB17: Motorcycle | BC17: 2316700 | BG17: Truck | BH17: 2 | BL17: Female | BM17: 0.43307087 | BP17: Active | BQ17: 1 | BU17: 46082 | BV17: 174 | BW17: 129 | CC17: Rejected | CD17: 0.13173653 | CG17: 35-44 | CH17: 31
O18: February | P18: 108741100 | Q18: 260723100 | T18: 46054 | U18: 108741100 | Y18: 44958 | Z18: 133372100 | AA18: -0.013755589 | AI18: Not Applicable | AJ18: 40 | AM18: Low Risk | AN18: 0.98425197 | AR18: Honda | AS18: 22997400 | AW18: Makati | AX18: 12371500 | BB18: Truck | BC18: 5306700 | BG18: Pickup | BH18: 14 | BL18: Male | BM18: 0.56692913 | BU18: 46113 | BV18: 167 | BW18: 132 | CG18: 45-54 | CH18: 43
O19: March | P19: 113040900 | Q19: 373764000 | T19: 46082 | U19: 113040900 | Y19: 44986 | Z19: 145709500 | AA19: 0.092503605 | AI19: Medium RIsk | AJ19: 2 | AR19: Ford | AS19: 14031400 | AW19: Cavite | AX19: 12663300 | BB19: Pickup | BC19: 16518800 | BG19: Motorcycle | BH19: 22 | BU19: 46143 | BV19: 163 | BW19: 124 | CG19: 55-64 | CH19: 43
O20: April | P20: 135152900 | Q20: 508916900 | T20: 46113 | U20: 135152900 | Y20: 45017 | Z20: 133028600 | AA20: -0.087028643 | AR20: Mitsubishi | AS20: 13951500 | AW20: Quezon City | AX20: 15846700 | BB20: Sedan | BC20: 26779300 | BG20: SUV | BH20: 28 | BU20: 46174 | BV20: 187 | BW20: 145 | CG20: 65+ | CH20: 5
O21: May | P21: 128056100 | Q21: 636973000 | T21: 46143 | U21: 128056100 | Y21: 45047 | Z21: 132813100 | AA21: -0.0016199524 | AI21: Total | AJ21: =SUM(AJ17:AJ20) -> 167 | AR21: Hyundai | AS21: 11061700 | AW21: CDO | AX21: 17831100 | BB21: MPV/Van | BC21: 29972500 | BG21: MPV/Van | BH21: 29 | BU21: 46204 | BV21: 167 | BW21: 127
O22: June | P22: 141458500 | Q22: 778431500 | T22: 46174 | U22: 141458500 | Y22: 45078 | Z22: 120023500 | AA22: -0.09629773 | AR22: Nissan | AS22: 10178100 | BB22: SUV | BC22: 36725700 | BG22: Sedan | BH22: 32 | BU22: 46235 | BV22: 165 | BW22: 125
O23: July | P23: 117619700 | Q23: 896051200 | T23: 46204 | U23: 117619700 | Y23: 45108 | Z23: 136643400 | AA23: 0.13847205 | AR23: Isuzu | AS23: 8442900
O24: August | P24: 83659000 | Q24: 979710200 | T24: 46235 | U24: 83659000 | Y24: 45139 | Z24: 147659900 | AA24: 0.080622262 | AR24: Suzuki | AS24: 6877900
Y25: 45170 | Z25: 141300400 | AA25: -0.043068565 | AR25: Kia | AS25: 3822100
Y26: 45200 | Z26: 160190700 | AA26: 0.13368894 | AR26: Hino | AS26: 1788200
Y27: 45231 | Z27: 120250500 | AA27: -0.24932908 | AR27: Yamaha | AS27: 936600
Y28: 45261 | Z28: 171109600 | AA28: 0.42294294 | AR28: Kawasaki | AS28: 376600
Y29: 45292 | Z29: 113893500 | AA29: -0.33438276
Y30: 45323 | Z30: 119264800 | AA30: 0.047160725
Y31: 45352 | Z31: 139185400 | AA31: 0.16702833
Y32: 45383 | Z32: 138592100 | AA32: -0.0042626597
Y33: 45413 | Z33: 134241000 | AA33: -0.031395007
Y34: 45444 | Z34: 157307100 | AA34: 0.17182604
Y35: 45474 | Z35: 141233900 | AA35: -0.10217721
Y36: 45505 | Z36: 129620300 | AA36: -0.08222955
Y37: 45536 | Z37: 117633200 | AA37: -0.09247857
Y38: 45566 | Z38: 128555300 | AA38: 0.092848788
Y39: 45597 | Z39: 140079300 | AA39: 0.089642356
Y40: 45627 | Z40: 119047700 | AA40: -0.15014067
... Y60: 46235 | Z60: 83659000 | AA60: -0.28873309

Sheet Loan Data
A1: Loan ID | B1: Customer ID | C1: First Name | D1: Middle Name | E1: Last Name | F1: Age | G1: Gender | H1: City | I1: Region | J1: Application Date | K1: Approval Date | L1: Vehicle Type | M1: Vehicle Brand | N1: Vehicle Model | O1: Vehicle Price | P1: Down Payment | Q1: Loan Amount | R1: Loan Term (Months) | S1: Interest Rate (%) | T1: Monthly Amortization | U1: Application Status | V1: Loan Status | W1: Amount Paid | X1: Outstanding Balance | Y1: Target Amount | Z1: Days Past Due | AA1: Delinquency Status | AB1: Branch | AC1: Loan Officer / Collector | AD1: Payment Frequency | AE1: Loan-to-Value (%) | AF1: Missed Payments (Count) | AG1: Risk Category | AH1: Approval Turnaround (Days) | AI1: Age Bracket | AJ1: Year | AK1: Month | AL1: First Day of the Month | AM1: MTD Amount | AN1: Interest Income | AO1: Approved Helper | AP1: MTD Period | AQ1: MTD Date Range
A2: LN-100006 | B2: CUS-200006 | C2: Angela | D2: Villanueva | E2: Manalo | F2: 25 | G2: Female | H2: Vigan | I2: Region I (Ilocos Region) | J2: 44928 | K2: 44935 | L2: Pickup | M2: Ford | N2: Ranger | O2: 1477000 | P2: 172700 | Q2: 1304300 | R2: 48 | S2: 5.75 | T2: 33422.69 | U2: Approved | V2: Active | W2: 1270062.2 | X2: 334226.78 | Y2: 1604289 | Z2: 145 | AA2: Over 90 Days | AB2: Makati | AC2: J. Espino | AD2: Monthly | AE2: 88.31 | AF2: 5 | AG2: High Risk | AH2: 7 | AI2: =IF(F2<25,"18-24",IF(F2<35,"25-34",IF(F2<45,"35-44",IF(F2<55,"45-54",IF(F2<65,"55-64","65+"))))) -> 25-34 | AJ2: =YEAR(tbl_LoanData[[#This Row],[Application Date]]) -> 2023 | AK2: =TEXT(tbl_LoanData[[#This Row],[Application Date]],"MMMM") -> January | AL2: =DATE(YEAR(tbl_LoanData[[#This Row],[Application Date]]),MONTH(tbl_LoanData[[#This Row],[Application Date]]),1) -> 44927 | AM2: =IF(AND(tbl_LoanData[[#This Row],[Application Date]]>=EOMONTH(TODAY(),-1)+1,tbl_LoanData[[#This Row],[Application Date]]<=TODAY()),tbl_LoanData[[#This Row],[Loan Amount]],0) -> 0 | AN2: =tbl_LoanData[[#This Row],[Amount Paid]]-(Q2-X2) -> 299989 | AO2: =IF(tbl_LoanData[[#This Row],[Application Status]]="Approved",1,0) -> 1 | AP2: =IF(AND(J2>=DATE(YEAR(TODAY()),MONTH(TODAY()),1),J2<=TODAY()),"Current MTD",IF(AND(J2>=EOMONTH(TODAY(),-2)+1,J2<=EOMONTH(TODAY(),-1)),"Previous MTD","")) | AQ2: =IF(AND(J2>=DATE(YEAR(TODAY()),MONTH(TODAY()),1),J2<=TODAY()),TEXT(DATE(YEAR(TODAY()),MONTH(TODAY()),1),"mmm d")&"–"&DAY(TODAY()),IF(AND(J2>=EOMONTH(TODAY(),-2)+1,J2<=EOMONTH(TODAY(),-1)),""&TEXT(EOMONTH(TODAY(),-2)+1,"mmm d")&"–"&DAY(TODAY()),""))
A3: LN-100117 | B3: CUS-200117 | C3: Camille | D3: Santos | E3: Umali | F3: 58 | G3: Female | H3: Lucena | I3: Region IV-A (CALABARZON) | J3: 44928 | K3: 44937 | L3: SUV | M3: Mitsubishi | N3: Xpander Cross | O3: 2055000 | P3: 637500 | Q3: 1417500 | R3: 60 | S3: 6 | T3: 30712.5 | U3: Approved | V3: Active | W3: 1320637.5 | X3: 522112.5 | Y3: 1842750 | Z3: 0 | AA3: Current | AB3: Manila | AC3: D. Morales | AD3: Monthly | AE3: 68.98 | AF3: 0 | AG3: Low Risk | AH3: 9 | AI3: =IF(F3<25,"18-24",IF(F3<35,"25-34",IF(F3<45,"35-44",IF(F3<55,"45-54",IF(F3<65,"55-64","65+"))))) -> 55-64 | AJ3: =YEAR(tbl_LoanData[[#This Row],[Application Date]]) -> 2023 | AK3: =TEXT(tbl_LoanData[[#This Row],[Application Date]],"MMMM") -> January | AL3: =DATE(YEAR(tbl_LoanData[[#This Row],[Application Date]]),MONTH(tbl_LoanData[[#This Row],[Application Date]]),1) -> 44927 | AM3: =IF(AND(tbl_LoanData[[#This Row],[Application Date]]>=EOMONTH(TODAY(),-1)+1,tbl_LoanData[[#This Row],[Application Date]]<=TODAY()),tbl_LoanData[[#This Row],[Loan Amount]],0) -> 0 | AN3: =tbl_LoanData[[#This Row],[Amount Paid]]-(Q3-X3) -> 425250 | AO3: =IF(tbl_LoanData[[#This Row],[Application Status]]="Approved",1,0) -> 1 | AP3: =IF(AND(J3>=DATE(YEAR(TODAY()),MONTH(TODAY()),1),J3<=TODAY()),"Current MTD",IF(AND(J3>=EOMONTH(TODAY(),-2)+1,J3<=EOMONTH(TODAY(),-1)),"Previous MTD","")) | AQ3: =IF(AND(J3>=DATE(YEAR(TODAY()),MONTH(TODAY()),1),J3<=TODAY()),TEXT(DATE(YEAR(TODAY()),MONTH(TODAY()),1),"mmm d")&"–"&DAY(TODAY()),IF(AND(J3>=EOMONTH(TODAY(),-2)+1,J3<=EOMONTH(TODAY(),-1)),""&TEXT(EOMONTH(TODAY(),-2)+1,"mmm d")&"–"&DAY(TODAY()),""))
A4: LN-100160 | B4: CUS-200160 | C4: Ricardo | D4: Salazar | E4: Quiambao | F4: 57 | G4: Male | H4: Batangas City | I4: Region IV-A (CALABARZON) | J4: 44940 | K4: 44951 | L4: SUV | M4: Honda | N4: BR-V | O4: 1996000 | P4: 266400 | Q4: 1729600 | R4: 12 | S4: 6.05 | T4: 152853.4 | U4: Approved | V4: Defaulted | W4: 1681387.4 | X4: 152853.4 | Y4: 1834240.8 | Z4: 30 | AA4: 1-30 Days | AB4: CDO | AC4: I. Cabrera | AD4: Monthly | AE4: 86.65 | AF4: 1 | AG4: Low Risk | AH4: 11 | AI4: =IF(F4<25,"18-24",IF(F4<35,"25-34",IF(F4<45,"35-44",IF(F4<55,"45-54",IF(F4<65,"55-64","65+"))))) -> 55-64 | AJ4: =YEAR(tbl_LoanData[[#This Row],[Application Date]]) -> 2023 | AK4: =TEXT(tbl_LoanData[[#This Row],[Application Date]],"MMMM") -> January | AL4: =DATE(YEAR(tbl_LoanData[[#This Row],[Application Date]]),MONTH(tbl_LoanData[[#This Row],[Application Date]]),1) -> 44927 | AM4: =IF(AND(tbl_LoanData[[#This Row],[Application Date]]>=EOMONTH(TODAY(),-1)+1,tbl_LoanData[[#This Row],[Application Date]]<=TODAY()),tbl_LoanData[[#This Row],[Loan Amount]],0) -> 0 | AN4: =tbl_LoanData[[#This Row],[Amount Paid]]-(Q4-X4) -> 104640.8 | AO4: =IF(tbl_LoanData[[#This Row],[Application Status]]="Approved",1,0) -> 1 | AP4: =IF(AND(J4>=DATE(YEAR(TODAY()),MONTH(TODAY()),1),J4<=TODAY()),"Current MTD",IF(AND(J4>=EOMONTH(TODAY(),-2)+1,J4<=EOMONTH(TODAY(),-1)),"Previous MTD","")) | AQ4: =IF(AND(J4>=DATE(YEAR(TODAY()),MONTH(TODAY()),1),J4<=TODAY()),TEXT(DATE(YEAR(TODAY()),MONTH(TODAY()),1),"mmm d")&"–"&DAY(TODAY()),IF(AND(J4>=EOMONTH(TODAY(),-2)+1,J4<=EOMONTH(TODAY(),-1)),""&TEXT(EOMONTH(TODAY(),-2)+1,"mmm d")&"–"&DAY(TODAY()),""))
A5: LN-100217 | B5: CUS-200217 | C5: Rodel | D5: Ocampo | E5: Pascual | F5: 31 | G5: Male | H5: Malolos | I5: Region III (Central Luzon) | J5: 44952 | K5: 44959 | L5: SUV | M5: Kia | N5: Sportage | O5: 1936000 | P5: 746800 | Q5: 1189200 | R5: 36 | S5: 14.47 | T5: 47373.1 | U5: Approved | V5: Closed - Fully Paid | W5: 1705431.7 | X5: 0 | Y5: 1705431.7 | Z5: 0 | AA5: Current | AB5: Makati | AC5: D. Morales | AD5: Monthly | AE5: 61.43 | AF5: 0 | AG5: Low Risk | AH5: 7 | AI5: =IF(F5<25,"18-24",IF(F5<35,"25-34",IF(F5<45,"35-44",IF(F5<55,"45-54",IF(F5<65,"55-64","65+"))))) -> 25-34 | AJ5: =YEAR(tbl_LoanData[[#This Row],[Application Date]]) -> 2023 | AK5: =TEXT(tbl_LoanData[[#This Row],[Application Date]],"MMMM") -> January | AL5: =DATE(YEAR(tbl_LoanData[[#This Row],[Application Date]]),MONTH(tbl_LoanData[[#This Row],[Application Date]]),1) -> 44927 | AM5: =IF(AND(tbl_LoanData[[#This Row],[Application Date]]>=EOMONTH(TODAY(),-1)+1,tbl_LoanData[[#This Row],[Application Date]]<=TODAY()),tbl_LoanData[[#This Row],[Loan Amount]],0) -> 0 | AN5: =tbl_LoanData[[#This Row],[Amount Paid]]-(Q5-X5) -> 516231.72 | AO5: =IF(tbl_LoanData[[#This Row],[Application Status]]="Approved",1,0) -> 1 | AP5: =IF(AND(J5>=DATE(YEAR(TODAY()),MONTH(TODAY()),1),J5<=TODAY()),"Current MTD",IF(AND(J5>=EOMONTH(TODAY(),-2)+1,J5<=EOMONTH(TODAY(),-1)),"Previous MTD","")) | AQ5: =IF(AND(J5>=DATE(YEAR(TODAY()),MONTH(TODAY()),1),J5<=TODAY()),TEXT(DATE(YEAR(TODAY()),MONTH(TODAY()),1),"mmm d")&"–"&DAY(TODAY()),IF(AND(J5>=EOMONTH(TODAY(),-2)+1,J5<=EOMONTH(TODAY(),-1)),""&TEXT(EOMONTH(TODAY(),-2)+1,"mmm d")&"–"&DAY(TODAY()),""))
A6: LN-100228 | B6: CUS-200228 | C6: Analyn | D6: Castillo | E6: Marquez | F6: 33 | G6: Female | H6: Caloocan | I6: NCR | J6: 44953 | K6: 44974 | L6: Pickup | M6: Nissan | N6: Navara | O6: 1382000 | P6: 182700 | Q6: 1199300 | R6: 36 | S6: 14.03 | T6: 47335.7 | U6: Approved | V6: Closed - Fully Paid | W6: 1704085.4 | X6: 0 | Y6: 1704085.4 | Z6: 0 | AA6: Current | AB6: Pampanga | AC6: H. Isip | AD6: Monthly | AE6: 86.78 | AF6: 0 | AG6: Low Risk | AH6: 21 | AI6: =IF(F6<25,"18-24",IF(F6<35,"25-34",IF(F6<45,"35-44",IF(F6<55,"45-54",IF(F6<65,"55-64","65+"))))) -> 25-34 | AJ6: =YEAR(tbl_LoanData[[#This Row],[Application Date]]) -> 2023 | AK6: =TEXT(tbl_LoanData[[#This Row],[Application Date]],"MMMM") -> January | AL6: =DATE(YEAR(tbl_LoanData[[#This Row],[Application Date]]),MONTH(tbl_LoanData[[#This Row],[Application Date]]),1) -> 44927 | AM6: =IF(AND(tbl_LoanData[[#This Row],[Application Date]]>=EOMONTH(TODAY(),-1)+1,tbl_LoanData[[#This Row],[Application Date]]<=TODAY()),tbl_LoanData[[#This Row],[Loan Amount]],0) -> 0 | AN6: =tbl_LoanData[[#This Row],[Amount Paid]]-(Q6-X6) -> 504785.37 | AO6: =IF(tbl_LoanData[[#This Row],[Application Status]]="Approved",1,0) -> 1 | AP6: =IF(AND(J6>=DATE(YEAR(TODAY()),MONTH(TODAY()),1),J6<=TODAY()),"Current MTD",IF(AND(J6>=EOMONTH(TODAY(),-2)+1,J6<=EOMONTH(TODAY(),-1)),"Previous MTD","")) | AQ6: =IF(AND(J6>=DATE(YEAR(TODAY()),MONTH(TODAY()),1),J6<=TODAY()),TEXT(DATE(YEAR(TODAY()),MONTH(TODAY()),1),"mmm d")&"–"&DAY(TODAY()),IF(AND(J6>=EOMONTH(TODAY(),-2)+1,J6<=EOMONTH(TODAY(),-1)),""&TEXT(EOMONTH(TODAY(),-2)+1,"mmm d")&"–"&DAY(TODAY()),""))
A7: LN-100253 | B7: CUS-200253 | C7: Vicente | D7: Fernandez | E7: Sarmiento | F7: 23 | G7: Male | H7: San Pablo | I7: Region IV-A (CALABARZON) | J7: 44957 | K7: 44972 | L7: Sedan | M7: Hyundai | N7: Elantra | O7: 1208000 | P7: 361400 | Q7: 846600 | R7: 36 | S7: 14.33 | T7: 33626.48 | U7: Approved | V7: Closed - Fully Paid | W7: 1210553.3 | X7: 0 | Y7: 1210553.3 | Z7: 0 | AA7: Current | AB7: Makati | AC7: J. Espino | AD7: Monthly | AE7: 70.08 | AF7: 0 | AG7: Low Risk | AH7: 15 | AI7: =IF(F7<25,"18-24",IF(F7<35,"25-34",IF(F7<45,"35-44",IF(F7<55,"45-54",IF(F7<65,"55-64","65+"))))) -> 18-24 | AJ7: =YEAR(tbl_LoanData[[#This Row],[Application Date]]) -> 2023 | AK7: =TEXT(tbl_LoanData[[#This Row],[Application Date]],"MMMM") -> January | AL7: =DATE(YEAR(tbl_LoanData[[#This Row],[Application Date]]),MONTH(tbl_LoanData[[#This Row],[Application Date]]),1) -> 44927 | AM7: =IF(AND(tbl_LoanData[[#This Row],[Application Date]]>=EOMONTH(TODAY(),-1)+1,tbl_LoanData[[#This Row],[Application Date]]<=TODAY()),tbl_LoanData[[#This Row],[Loan Amount]],0) -> 0 | AN7: =tbl_LoanData[[#This Row],[Amount Paid]]-(Q7-X7) -> 363953.34 | AO7: =IF(tbl_LoanData[[#This Row],[Application Status]]="Approved",1,0) -> 1 | AP7: =IF(AND(J7>=DATE(YEAR(TODAY()),MONTH(TODAY()),1),J7<=TODAY()),"Current MTD",IF(AND(J7>=EOMONTH(TODAY(),-2)+1,J7<=EOMONTH(TODAY(),-1)),"Previous MTD","")) | AQ7: =IF(AND(J7>=DATE(YEAR(TODAY()),MONTH(TODAY()),1),J7<=TODAY()),TEXT(DATE(YEAR(TODAY()),MONTH(TODAY()),1),"mmm d")&"–"&DAY(TODAY()),IF(AND(J7>=EOMONTH(TODAY(),-2)+1,J7<=EOMONTH(TODAY(),-1)),""&TEXT(EOMONTH(TODAY(),-2)+1,"mmm d")&"–"&DAY(TODAY()),""))
A8: LN-100310 | B8: CUS-200310 | C8: Roberto | D8: Salazar | E8: Quiambao | F8: 38 | G8: Male | H8: Iloilo City | I8: Region VI (Western Visayas) | J8: 44951 | L8: Truck | M8: Fuso | N8: Canter | O8: 3233000 | P8: 387000 | Q8: 2846000 | R8: 24 | S8: 14.5 | T8: 152972.5 | U8: Rejected | V8: Not Applicable | W8: 0 | X8: 0 | Y8: 3671340 | Z8: 0 | AA8: Not Applicable | AB8: Pampanga | AC8: D. Morales | AD8: Monthly | AE8: 88.03 | AF8: 0 | AG8: Not Applicable | AI8: =IF(F8<25,"18-24",IF(F8<35,"25-34",IF(F8<45,"35-44",IF(F8<55,"45-54",IF(F8<65,"55-64","65+"))))) -> 35-44 | AJ8: =YEAR(tbl_LoanData[[#This Row],[Application Date]]) -> 2023 | AK8: =TEXT(tbl_LoanData[[#This Row],[Application Date]],"MMMM") -> January | AL8: =DATE(YEAR(tbl_LoanData[[#This Row],[Application Date]]),MONTH(tbl_LoanData[[#This Row],[Application Date]]),1) -> 44927 | AM8: =IF(AND(tbl_LoanData[[#This Row],[Application Date]]>=EOMONTH(TODAY(),-1)+1,tbl_LoanData[[#This Row],[Application Date]]<=TODAY()),tbl_LoanData[[#This Row],[Loan Amount]],0) -> 0 | AN8: =tbl_LoanData[[#This Row],[Amount Paid]]-(Q8-X8) -> -2846000 | AO8: =IF(tbl_LoanData[[#This Row],[Application Status]]="Approved",1,0) -> 0 | AP8: =IF(AND(J8>=DATE(YEAR(TODAY()),MONTH(TODAY()),1),J8<=TODAY()),"Current MTD",IF(AND(J8>=EOMONTH(TODAY(),-2)+1,J8<=EOMONTH(TODAY(),-1)),"Previous MTD","")) | AQ8: =IF(AND(J8>=DATE(YEAR(TODAY()),MONTH(TODAY()),1),J8<=TODAY()),TEXT(DATE(YEAR(TODAY()),MONTH(TODAY()),1),"mmm d")&"–"&DAY(TODAY()),IF(AND(J8>=EOMONTH(TODAY(),-2)+1,J8<=EOMONTH(TODAY(),-1)),""&TEXT(EOMONTH(TODAY(),-2)+1,"mmm d")&"–"&DAY(TODAY()),""))
A9: LN-100343 | B9: CUS-200343 | C9: Cristina | D9: Cruz | E9: Guevarra | F9: 24 | G9: Female | H9: Lucena | I9: Region IV-A (CALABARZON) | J9: 44951 | L9: Pickup | M9: Nissan | N9: Navara | O9: 1652000 | P9: 561500 | Q9: 1090500 | R9: 36 | S9: 13.59 | T9: 42641.58 | U9: Rejected | V9: Not Applicable | W9: 0 | X9: 0 | Y9: 1535096.9 | Z9: 0 | AA9: Not Applicable | AB9: Quezon City | AC9: G. Bunag | AD9: Monthly | AE9: 66.01 | AF9: 0 | AG9: Not Applicable | AI9: =IF(F9<25,"18-24",IF(F9<35,"25-34",IF(F9<45,"35-44",IF(F9<55,"45-54",IF(F9<65,"55-64","65+"))))) -> 18-24 | AJ9: =YEAR(tbl_LoanData[[#This Row],[Application Date]]) -> 2023 | AK9: =TEXT(tbl_LoanData[[#This Row],[Application Date]],"MMMM") -> January | AL9: =DATE(YEAR(tbl_LoanData[[#This Row],[Application Date]]),MONTH(tbl_LoanData[[#This Row],[Application Date]]),1) -> 44927 | AM9: =IF(AND(tbl_LoanData[[#This Row],[Application Date]]>=EOMONTH(TODAY(),-1)+1,tbl_LoanData[[#This Row],[Application Date]]<=TODAY()),tbl_LoanData[[#This Row],[Loan Amount]],0) -> 0 | AN9: =tbl_LoanData[[#This Row],[Amount Paid]]-(Q9-X9) -> -1090500 | AO9: =IF(tbl_LoanData[[#This Row],[Application Status]]="Approved",1,0) -> 0 | AP9: =IF(AND(J9>=DATE(YEAR(TODAY()),MONTH(TODAY()),1),J9<=TODAY()),"Current MTD",IF(AND(J9>=EOMONTH(TODAY(),-2)+1,J9<=EOMONTH(TODAY(),-1)),"Previous MTD","")) | AQ9: =IF(AND(J9>=DATE(YEAR(TODAY()),MONTH(TODAY()),1),J9<=TODAY()),TEXT(DATE(YEAR(TODAY()),MONTH(TODAY()),1),"mmm d")&"–"&DAY(TODAY()),IF(AND(J9>=EOMONTH(TODAY(),-2)+1,J9<=EOMONTH(TODAY(),-1)),""&TEXT(EOMONTH(TODAY(),-2)+1,"mmm d")&"–"&DAY(TODAY()),""))
A10: LN-100348 | B10: CUS-200348 | C10: Kristine | D10: Gonzales | E10: Tolentino | F10: 52 | G10: Female | H10: Lapu-Lapu | I10: Region VII (Central Visayas) | J10: 44944 | K10: 44963 | L10: Truck | M10: Fuso | N10: Canter | O10: 2606000 | P10: 285400 | Q10: 2320600 | R10: 48 | S10: 11.85 | T10: 71261.76 | U10: Approved | V10: Active | W10: 2921732.2 | X10: 498832.24 | Y10: 3420564.4 | Z10: 30 | AA10: 1-30 Days | AB10: Manila | AC10: F. Lacson | AD10: Monthly | AE10: 89.05 | AF10: 1 | AG10: Low Risk | AH10: 19 | AI10: =IF(F10<25,"18-24",IF(F10<35,"25-34",IF(F10<45,"35-44",IF(F10<55,"45-54",IF(F10<65,"55-64","65+"))))) -> 45-54 | AJ10: =YEAR(tbl_LoanData[[#This Row],[Application Date]]) -> 2023 | AK10: =TEXT(tbl_LoanData[[#This Row],[Application Date]],"MMMM") -> January | AL10: =DATE(YEAR(tbl_LoanData[[#This Row],[Application Date]]),MONTH(tbl_LoanData[[#This Row],[Application Date]]),1) -> 44927 | AM10: =IF(AND(tbl_LoanData[[#This Row],[Application Date]]>=EOMONTH(TODAY(),-1)+1,tbl_LoanData[[#This Row],[Application Date]]<=TODAY()),tbl_LoanData[[#This Row],[Loan Amount]],0) -> 0 | AN10: =tbl_LoanData[[#This Row],[Amount Paid]]-(Q10-X10) -> 1099964.4 | AO10: =IF(tbl_LoanData[[#This Row],[Application Status]]="Approved",1,0) -> 1 | AP10: =IF(AND(J10>=DATE(YEAR(TODAY()),MONTH(TODAY()),1),J10<=TODAY()),"Current MTD",IF(AND(J10>=EOMONTH(TODAY(),-2)+1,J10<=EOMONTH(TODAY(),-1)),"Previous MTD","")) | AQ10: =IF(AND(J10>=DATE(YEAR(TODAY()),MONTH(TODAY()),1),J10<=TODAY()),TEXT(DATE(YEAR(TODAY()),MONTH(TODAY()),1),"mmm d")&"–"&DAY(TODAY()),IF(AND(J10>=EOMONTH(TODAY(),-2)+1,J10<=EOMONTH(TODAY(),-1)),""&TEXT(EOMONTH(TODAY(),-2)+1,"mmm d")&"–"&DAY(TODAY()),""))
A11: LN-100384 | B11: CUS-200384 | C11: Vincent | D11: Del Rosario | E11: Quiambao | F11: 35 | G11: Male | H11: Paranaque | I11: NCR | J11: 44938 | K11: 44958 | L11: Sedan | M11: Nissan | N11: Sylphy | O11: 1591000 | P11: 582300 | Q11: 1008700 | R11: 36 | S11: 14.16 | T11: 39922.1 | U11: Approved | V11: Defaulted | W11: 1237585.1 | X11: 199610.66 | Y11: 1437195.8 | Z11: 155 | AA11: Over 90 Days | AB11: Manila | AC11: A. Ramirez | AD11: Monthly | AE11: 63.4 | AF11: 5 | AG11: High Risk | AH11: 20 | AI11: =IF(F11<25,"18-24",IF(F11<35,"25-34",IF(F11<45,"35-44",IF(F11<55,"45-54",IF(F11<65,"55-64","65+"))))) -> 35-44 | AJ11: =YEAR(tbl_LoanData[[#This Row],[Application Date]]) -> 2023 | AK11: =TEXT(tbl_LoanData[[#This Row],[Application Date]],"MMMM") -> January | AL11: =DATE(YEAR(tbl_LoanData[[#This Row],[Application Date]]),MONTH(tbl_LoanData[[#This Row],[Application Date]]),1) -> 44927 | AM11: =IF(AND(tbl_LoanData[[#This Row],[Application Date]]>=EOMONTH(TODAY(),-1)+1,tbl_LoanData[[#This Row],[Application Date]]<=TODAY()),tbl_LoanData[[#This Row],[Loan Amount]],0) -> 0 | AN11: =tbl_LoanData[[#This Row],[Amount Paid]]-(Q11-X11) -> 428495.76 | AO11: =IF(tbl_LoanData[[#This Row],[Application Status]]="Approved",1,0) -> 1 | AP11: =IF(AND(J11>=DATE(YEAR(TODAY()),MONTH(TODAY()),1),J11<=TODAY()),"Current MTD",IF(AND(J11>=EOMONTH(TODAY(),-2)+1,J11<=EOMONTH(TODAY(),-1)),"Previous MTD","")) | AQ11: =IF(AND(J11>=DATE(YEAR(TODAY()),MONTH(TODAY()),1),J11<=TODAY()),TEXT(DATE(YEAR(TODAY()),MONTH(TODAY()),1),"mmm d")&"–"&DAY(TODAY()),IF(AND(J11>=EOMONTH(TODAY(),-2)+1,J11<=EOMONTH(TODAY(),-1)),""&TEXT(EOMONTH(TODAY(),-2)+1,"mmm d")&"–"&DAY(TODAY()),""))
A12: LN-100420 | B12: CUS-200420 | C12: Maria | D12: Cruz | E12: Aguilar | F12: 44 | G12: Female | H12: Mandaluyong | I12: NCR | J12: 44929 | K12: 44947 | L12: MPV/Van | M12: Mitsubishi | N12: Xpander | O12: 2123000 | P12: 618400 | Q12: 1504600 | R12: 36 | S12: 9.08 | T12: 53179.25 | U12: Approved | V12: Closed - Fully Paid | W12: 1914453 | X12: 0 | Y12: 1914453 | Z12: 0 | AA12: Current | AB12: Manila | AC12: C. Villareal | AD12: Monthly | AE12: 70.87 | AF12: 0 | AG12: Low Risk | AH12: 18 | AI12: =IF(F12<25,"18-24",IF(F12<35,"25-34",IF(F12<45,"35-44",IF(F12<55,"45-54",IF(F12<65,"55-64","65+"))))) -> 35-44 | AJ12: =YEAR(tbl_LoanData[[#This Row],[Application Date]]) -> 2023 | AK12: =TEXT(tbl_LoanData[[#This Row],[Application Date]],"MMMM") -> January | AL12: =DATE(YEAR(tbl_LoanData[[#This Row],[Application Date]]),MONTH(tbl_LoanData[[#This Row],[Application Date]]),1) -> 44927 | AM12: =IF(AND(tbl_LoanData[[#This Row],[Application Date]]>=EOMONTH(TODAY(),-1)+1,tbl_LoanData[[#This Row],[Application Date]]<=TODAY()),tbl_LoanData[[#This Row],[Loan Amount]],0) -> 0 | AN12: =tbl_LoanData[[#This Row],[Amount Paid]]-(Q12-X12) -> 409853.04 | AO12: =IF(tbl_LoanData[[#This Row],[Application Status]]="Approved",1,0) -> 1 | AP12: =IF(AND(J12>=DATE(YEAR(TODAY()),MONTH(TODAY()),1),J12<=TODAY()),"Current MTD",IF(AND(J12>=EOMONTH(TODAY(),-2)+1,J12<=EOMONTH(TODAY(),-1)),"Previous MTD","")) | AQ12: =IF(AND(J12>=DATE(YEAR(TODAY()),MONTH(TODAY()),1),J12<=TODAY()),TEXT(DATE(YEAR(TODAY()),MONTH(TODAY()),1),"mmm d")&"–"&DAY(TODAY()),IF(AND(J12>=EOMONTH(TODAY(),-2)+1,J12<=EOMONTH(TODAY(),-1)),""&TEXT(EOMONTH(TODAY(),-2)+1,"mmm d")&"–"&DAY(TODAY()),""))
A13: LN-100657 | B13: CUS-200657 | C13: Melchor | D13: Domingo | E13: Del Rosario | F13: 24 | G13: Male | H13: San Fernando (Pampanga) | I13: Region III (Central Luzon) | J13: 44944 | K13: 44949 | L13: Sedan | M13: Mitsubishi | N13: Mirage G4 | O13: 1411000 | P13: 410300 | Q13: 1000700 | R13: 48 | S13: 6.89 | T13: 26593.6 | U13: Approved | V13: Active | W13: 1116931.2 | X13: 159561.72 | Y13: 1276492.9 | Z13: 29 | AA13: 1-30 Days | AB13: Quezon City | AC13: I. Cabrera | AD13: Monthly | AE13: 70.92 | AF13: 1 | AG13: Low Risk | AH13: 5 | AI13: =IF(F13<25,"18-24",IF(F13<35,"25-34",IF(F13<45,"35-44",IF(F13<55,"45-54",IF(F13<65,"55-64","65+"))))) -> 18-24 | AJ13: =YEAR(tbl_LoanData[[#This Row],[Application Date]]) -> 2023 | AK13: =TEXT(tbl_LoanData[[#This Row],[Application Date]],"MMMM") -> January | AL13: =DATE(YEAR(tbl_LoanData[[#This Row],[Application Date]]),MONTH(tbl_LoanData[[#This Row],[Application Date]]),1) -> 44927 | AM13: =IF(AND(tbl_LoanData[[#This Row],[Application Date]]>=EOMONTH(TODAY(),-1)+1,tbl_LoanData[[#This Row],[Application Date]]<=TODAY()),tbl_LoanData[[#This Row],[Loan Amount]],0) -> 0 | AN13: =tbl_LoanData[[#This Row],[Amount Paid]]-(Q13-X13) -> 275792.92 | AO13: =IF(tbl_LoanData[[#This Row],[Application Status]]="Approved",1,0) -> 1 | AP13: =IF(AND(J13>=DATE(YEAR(TODAY()),MONTH(TODAY()),1),J13<=TODAY()),"Current MTD",IF(AND(J13>=EOMONTH(TODAY(),-2)+1,J13<=EOMONTH(TODAY(),-1)),"Previous MTD","")) | AQ13: =IF(AND(J13>=DATE(YEAR(TODAY()),MONTH(TODAY()),1),J13<=TODAY()),TEXT(DATE(YEAR(TODAY()),MONTH(TODAY()),1),"mmm d")&"–"&DAY(TODAY()),IF(AND(J13>=EOMONTH(TODAY(),-2)+1,J13<=EOMONTH(TODAY(),-1)),""&TEXT(EOMONTH(TODAY(),-2)+1,"mmm d")&"–"&DAY(TODAY()),""))
A14: LN-100714 | B14: CUS-200714 | C14: Marites | D14: Reyes | E14: Rosales | F14: 60 | G14: Female | H14: Vigan | I14: Region I (Ilocos Region) | J14: 44928 | L14: MPV/Van | M14: Honda | N14: Mobilio | O14: 1717000 | P14: 648000 | Q14: 1069000 | R14: 48 | S14: 12.92 | T14: 33780.4 | U14: Rejected | V14: Not Applicable | W14: 0 | X14: 0 | Y14: 1621459.2 | Z14: 0 | AA14: Not Applicable | AB14: Baguio | AC14: H. Isip | AD14: Monthly | AE14: 62.26 | AF14: 0 | AG14: Not Applicable | AI14: =IF(F14<25,"18-24",IF(F14<35,"25-34",IF(F14<45,"35-44",IF(F14<55,"45-54",IF(F14<65,"55-64","65+"))))) -> 55-64 | AJ14: =YEAR(tbl_LoanData[[#This Row],[Application Date]]) -> 2023 | AK14: =TEXT(tbl_LoanData[[#This Row],[Application Date]],"MMMM") -> January | AL14: =DATE(YEAR(tbl_LoanData[[#This Row],[Application Date]]),MONTH(tbl_LoanData[[#This Row],[Application Date]]),1) -> 44927 | AM14: =IF(AND(tbl_LoanData[[#This Row],[Application Date]]>=EOMONTH(TODAY(),-1)+1,tbl_LoanData[[#This Row],[Application Date]]<=TODAY()),tbl_LoanData[[#This Row],[Loan Amount]],0) -> 0 | AN14: =tbl_LoanData[[#This Row],[Amount Paid]]-(Q14-X14) -> -1069000 | AO14: =IF(tbl_LoanData[[#This Row],[Application Status]]="Approved",1,0) -> 0 | AP14: =IF(AND(J14>=DATE(YEAR(TODAY()),MONTH(TODAY()),1),J14<=TODAY()),"Current MTD",IF(AND(J14>=EOMONTH(TODAY(),-2)+1,J14<=EOMONTH(TODAY(),-1)),"Previous MTD","")) | AQ14: =IF(AND(J14>=DATE(YEAR(TODAY()),MONTH(TODAY()),1),J14<=TODAY()),TEXT(DATE(YEAR(TODAY()),MONTH(TODAY()),1),"mmm d")&"–"&DAY(TODAY()),IF(AND(J14>=EOMONTH(TODAY(),-2)+1,J14<=EOMONTH(TODAY(),-1)),""&TEXT(EOMONTH(TODAY(),-2)+1,"mmm d")&"–"&DAY(TODAY()),""))
A15: LN-100721 | B15: CUS-200721 | C15: Bienvenido | D15: Reyes | E15: Sarmiento | F15: 26 | G15: Male | H15: Davao City | I15: Region XI (Davao Region) | J15: 44928 | K15: 44938 | L15: Pickup | M15: Mitsubishi | N15: Strada | O15: 1761000 | P15: 429500 | Q15: 1331500 | R15: 24 | S15: 6.98 | T15: 63224.06 | U15: Approved | V15: Closed - Fully Paid | W15: 1517377.4 | X15: 0 | Y15: 1517377.4 | Z15: 0 | AA15: Current | AB15: Pampanga | AC15: F. Lacson | AD15: Monthly | AE15: 75.61 | AF15: 0 | AG15: Low Risk | AH15: 10 | AI15: =IF(F15<25,"18-24",IF(F15<35,"25-34",IF(F15<45,"35-44",IF(F15<55,"45-54",IF(F15<65,"55-64","65+"))))) -> 25-34 | AJ15: =YEAR(tbl_LoanData[[#This Row],[Application Date]]) -> 2023 | AK15: =TEXT(tbl_LoanData[[#This Row],[Application Date]],"MMMM") -> January | AL15: =DATE(YEAR(tbl_LoanData[[#This Row],[Application Date]]),MONTH(tbl_LoanData[[#This Row],[Application Date]]),1) -> 44927 | AM15: =IF(AND(tbl_LoanData[[#This Row],[Application Date]]>=EOMONTH(TODAY(),-1)+1,tbl_LoanData[[#This Row],[Application Date]]<=TODAY()),tbl_LoanData[[#This Row],[Loan Amount]],0) -> 0 | AN15: =tbl_LoanData[[#This Row],[Amount Paid]]-(Q15-X15) -> 185877.4 | AO15: =IF(tbl_LoanData[[#This Row],[Application Status]]="Approved",1,0) -> 1 | AP15: =IF(AND(J15>=DATE(YEAR(TODAY()),MONTH(TODAY()),1),J15<=TODAY()),"Current MTD",IF(AND(J15>=EOMONTH(TODAY(),-2)+1,J15<=EOMONTH(TODAY(),-1)),"Previous MTD","")) | AQ15: =IF(AND(J15>=DATE(YEAR(TODAY()),MONTH(TODAY()),1),J15<=TODAY()),TEXT(DATE(YEAR(TODAY()),MONTH(TODAY()),1),"mmm d")&"–"&DAY(TODAY()),IF(AND(J15>=EOMONTH(TODAY(),-2)+1,J15<=EOMONTH(TODAY(),-1)),""&TEXT(EOMONTH(TODAY(),-2)+1,"mmm d")&"–"&DAY(TODAY()),""))
A16: LN-100739 | B16: CUS-200739 | C16: Federico | D16: Ocampo | E16: Gonzales | F16: 34 | G16: Male | H16: Bacolod | I16: Region VI (Western Visayas) | J16: 44933 | K16: 44938 | L16: MPV/Van | M16: Honda | N16: Mobilio | O16: 1654000 | P16: 175600 | Q16: 1478400 | R16: 36 | S16: 14.61 | T16: 59066.19 | U16: Approved | V16: Closed - Fully Paid | W16: 2126382.7 | X16: 0 | Y16: 2126382.7 | Z16: 0 | AA16: Current | AB16: CDO | AC16: I. Cabrera | AD16: Monthly | AE16: 89.38 | AF16: 0 | AG16: Low Risk | AH16: 5 | AI16: =IF(F16<25,"18-24",IF(F16<35,"25-34",IF(F16<45,"35-44",IF(F16<55,"45-54",IF(F16<65,"55-64","65+"))))) -> 25-34 | AJ16: =YEAR(tbl_LoanData[[#This Row],[Application Date]]) -> 2023 | AK16: =TEXT(tbl_LoanData[[#This Row],[Application Date]],"MMMM") -> January | AL16: =DATE(YEAR(tbl_LoanData[[#This Row],[Application Date]]),MONTH(tbl_LoanData[[#This Row],[Application Date]]),1) -> 44927 | AM16: =IF(AND(tbl_LoanData[[#This Row],[Application Date]]>=EOMONTH(TODAY(),-1)+1,tbl_LoanData[[#This Row],[Application Date]]<=TODAY()),tbl_LoanData[[#This Row],[Loan Amount]],0) -> 0 | AN16: =tbl_LoanData[[#This Row],[Amount Paid]]-(Q16-X16) -> 647982.72 | AO16: =IF(tbl_LoanData[[#This Row],[Application Status]]="Approved",1,0) -> 1 | AP16: =IF(AND(J16>=DATE(YEAR(TODAY()),MONTH(TODAY()),1),J16<=TODAY()),"Current MTD",IF(AND(J16>=EOMONTH(TODAY(),-2)+1,J16<=EOMONTH(TODAY(),-1)),"Previous MTD","")) | AQ16: =IF(AND(J16>=DATE(YEAR(TODAY()),MONTH(TODAY()),1),J16<=TODAY()),TEXT(DATE(YEAR(TODAY()),MONTH(TODAY()),1),"mmm d")&"–"&DAY(TODAY()),IF(AND(J16>=EOMONTH(TODAY(),-2)+1,J16<=EOMONTH(TODAY(),-1)),""&TEXT(EOMONTH(TODAY(),-2)+1,"mmm d")&"–"&DAY(TODAY()),""))
A17: LN-100781 | B17: CUS-200781 | C17: Herminia | D17: Pascual | E17: Pascual | F17: 52 | G17: Female | H17: Cabanatuan | I17: Region III (Central Luzon) | J17: 44952 | L17: SUV | M17: Toyota | N17: Fortuner | O17: 2195000 | P17: 748600 | Q17: 1446400 | R17: 60 | S17: 6.79 | T17: 32290.88 | U17: Rejected | V17: Not Applicable | W17: 0 | X17: 0 | Y17: 1937452.8 | Z17: 0 | AA17: Not Applicable | AB17: Cebu | AC17: I. Cabrera | AD17: Monthly | AE17: 65.9 | AF17: 0 | AG17: Not Applicable | AI17: =IF(F17<25,"18-24",IF(F17<35,"25-34",IF(F17<45,"35-44",IF(F17<55,"45-54",IF(F17<65,"55-64","65+"))))) -> 45-54 | AJ17: =YEAR(tbl_LoanData[[#This Row],[Application Date]]) -> 2023 | AK17: =TEXT(tbl_LoanData[[#This Row],[Application Date]],"MMMM") -> January | AL17: =DATE(YEAR(tbl_LoanData[[#This Row],[Application Date]]),MONTH(tbl_LoanData[[#This Row],[Application Date]]),1) -> 44927 | AM17: =IF(AND(tbl_LoanData[[#This Row],[Application Date]]>=EOMONTH(TODAY(),-1)+1,tbl_LoanData[[#This Row],[Application Date]]<=TODAY()),tbl_LoanData[[#This Row],[Loan Amount]],0) -> 0 | AN17: =tbl_LoanData[[#This Row],[Amount Paid]]-(Q17-X17) -> -1446400 | AO17: =IF(tbl_LoanData[[#This Row],[Application Status]]="Approved",1,0) -> 0 | AP17: =IF(AND(J17>=DATE(YEAR(TODAY()),MONTH(TODAY()),1),J17<=TODAY()),"Current MTD",IF(AND(J17>=EOMONTH(TODAY(),-2)+1,J17<=EOMONTH(TODAY(),-1)),"Previous MTD","")) | AQ17: =IF(AND(J17>=DATE(YEAR(TODAY()),MONTH(TODAY()),1),J17<=TODAY()),TEXT(DATE(YEAR(TODAY()),MONTH(TODAY()),1),"mmm d")&"–"&DAY(TODAY()),IF(AND(J17>=EOMONTH(TODAY(),-2)+1,J17<=EOMONTH(TODAY(),-1)),""&TEXT(EOMONTH(TODAY(),-2)+1,"mmm d")&"–"&DAY(TODAY()),""))
A18: LN-100842 | B18: CUS-200842 | C18: Efren | D18: Bautista | E18: Pascual | F18: 30 | G18: Male | H18: Marikina | I18: NCR | J18: 44934 | L18: Truck | M18: Hino | N18: 500 Series | O18: 3675000 | P18: 815700 | Q18: 2859300 | R18: 60 | S18: 8.72 | T18: 68432.58 | U18: Rejected | V18: Not Applicable | W18: 0 | X18: 0 | Y18: 4105954.8 | Z18: 0 | AA18: Not Applicable | AB18: Cebu | AC18: D. Morales | AD18: Monthly | AE18: 77.8 | AF18: 0 | AG18: Not Applicable | AI18: =IF(F18<25,"18-24",IF(F18<35,"25-34",IF(F18<45,"35-44",IF(F18<55,"45-54",IF(F18<65,"55-64","65+"))))) -> 25-34 | AJ18: =YEAR(tbl_LoanData[[#This Row],[Application Date]]) -> 2023 | AK18: =TEXT(tbl_LoanData[[#This Row],[Application Date]],"MMMM") -> January | AL18: =DATE(YEAR(tbl_LoanData[[#This Row],[Application Date]]),MONTH(tbl_LoanData[[#This Row],[Application Date]]),1) -> 44927 | AM18: =IF(AND(tbl_LoanData[[#This Row],[Application Date]]>=EOMONTH(TODAY(),-1)+1,tbl_LoanData[[#This Row],[Application Date]]<=TODAY()),tbl_LoanData[[#This Row],[Loan Amount]],0) -> 0 | AN18: =tbl_LoanData[[#This Row],[Amount Paid]]-(Q18-X18) -> -2859300 | AO18: =IF(tbl_LoanData[[#This Row],[Application Status]]="Approved",1,0) -> 0 | AP18: =IF(AND(J18>=DATE(YEAR(TODAY()),MONTH(TODAY()),1),J18<=TODAY()),"Current MTD",IF(AND(J18>=EOMONTH(TODAY(),-2)+1,J18<=EOMONTH(TODAY(),-1)),"Previous MTD","")) | AQ18: =IF(AND(J18>=DATE(YEAR(TODAY()),MONTH(TODAY()),1),J18<=TODAY()),TEXT(DATE(YEAR(TODAY()),MONTH(TODAY()),1),"mmm d")&"–"&DAY(TODAY()),IF(AND(J18>=EOMONTH(TODAY(),-2)+1,J18<=EOMONTH(TODAY(),-1)),""&TEXT(EOMONTH(TODAY(),-2)+1,"mmm d")&"–"&DAY(TODAY()),""))
A19: LN-100871 | B19: CUS-200871 | C19: Danilo | D19: Gonzales | E19: Aquino | F19: 51 | G19: Male | H19: Lipa | I19: Region IV-A (CALABARZON) | J19: 44927 | K19: 44941 | L19: Pickup | M19: Ford | N19: Ranger | O19: 1808000 | P19: 303200 | Q19: 1504800 | R19: 36 | S19: 8.2 | T19: 52082.8 | U19: Approved | V19: Defaulted | W19: 1770815.2 | X19: 104165.6 | Y19: 1874980.8 | Z19: 60 | AA19: 31-60 Days | AB19: Iloilo | AC19: J. Espino | AD19: Monthly | AE19: 83.23 | AF19: 2 | AG19: Medium RIsk | AH19: 14 | AI19: =IF(F19<25,"18-24",IF(F19<35,"25-34",IF(F19<45,"35-44",IF(F19<55,"45-54",IF(F19<65,"55-64","65+"))))) -> 45-54 | AJ19: =YEAR(tbl_LoanData[[#This Row],[Application Date]]) -> 2023 | AK19: =TEXT(tbl_LoanData[[#This Row],[Application Date]],"MMMM") -> January | AL19: =DATE(YEAR(tbl_LoanData[[#This Row],[Application Date]]),MONTH(tbl_LoanData[[#This Row],[Application Date]]),1) -> 44927 | AM19: =IF(AND(tbl_LoanData[[#This Row],[Application Date]]>=EOMONTH(TODAY(),-1)+1,tbl_LoanData[[#This Row],[Application Date]]<=TODAY()),tbl_LoanData[[#This Row],[Loan Amount]],0) -> 0 | AN19: =tbl_LoanData[[#This Row],[Amount Paid]]-(Q19-X19) -> 370180.8 | AO19: =IF(tbl_LoanData[[#This Row],[Application Status]]="Approved",1,0) -> 1 | AP19: =IF(AND(J19>=DATE(YEAR(TODAY()),MONTH(TODAY()),1),J19<=TODAY()),"Current MTD",IF(AND(J19>=EOMONTH(TODAY(),-2)+1,J19<=EOMONTH(TODAY(),-1)),"Previous MTD","")) | AQ19: =IF(AND(J19>=DATE(YEAR(TODAY()),MONTH(TODAY()),1),J19<=TODAY()),TEXT(DATE(YEAR(TODAY()),MONTH(TODAY()),1),"mmm d")&"–"&DAY(TODAY()),IF(AND(J19>=EOMONTH(TODAY(),-2)+1,J19<=EOMONTH(TODAY(),-1)),""&TEXT(EOMONTH(TODAY(),-2)+1,"mmm d")&"–"&DAY(TODAY()),""))
A20: LN-100919 | B20: CUS-200919 | C20: Hazel | D20: Domingo | E20: Pascual | F20: 64 | G20: Female | H20: Cagayan de Oro | I20: Region X (Northern Mindanao) | J20: 44956 | L20: SUV | M20: Mitsubishi | N20: Xpander Cross | O20: 1292000 | P20: 486500 | Q20: 805500 | R20: 24 | S20: 10.17 | T20: 40389.11 | U20: Pending | V20: Not Applicable | W20: 0 | X20: 0 | Y20: 969338.7 | Z20: 0 | AA20: Not Applicable | AB20: Baguio | AC20: B. Santiago | AD20: Monthly | AE20: 62.35 | AF20: 0 | AG20: Not Applicable | AI20: =IF(F20<25,"18-24",IF(F20<35,"25-34",IF(F20<45,"35-44",IF(F20<55,"45-54",IF(F20<65,"55-64","65+"))))) -> 55-64 | AJ20: =YEAR(tbl_LoanData[[#This Row],[Application Date]]) -> 2023 | AK20: =TEXT(tbl_LoanData[[#This Row],[Application Date]],"MMMM") -> January | AL20: =DATE(YEAR(tbl_LoanData[[#This Row],[Application Date]]),MONTH(tbl_LoanData[[#This Row],[Application Date]]),1) -> 44927 | AM20: =IF(AND(tbl_LoanData[[#This Row],[Application Date]]>=EOMONTH(TODAY(),-1)+1,tbl_LoanData[[#This Row],[Application Date]]<=TODAY()),tbl_LoanData[[#This Row],[Loan Amount]],0) -> 0 | AN20: =tbl_LoanData[[#This Row],[Amount Paid]]-(Q20-X20) -> -805500 | AO20: =IF(tbl_LoanData[[#This Row],[Application Status]]="Approved",1,0) -> 0 | AP20: =IF(AND(J20>=DATE(YEAR(TODAY()),MONTH(TODAY()),1),J20<=TODAY()),"Current MTD",IF(AND(J20>=EOMONTH(TODAY(),-2)+1,J20<=EOMONTH(TODAY(),-1)),"Previous MTD","")) | AQ20: =IF(AND(J20>=DATE(YEAR(TODAY()),MONTH(TODAY()),1),J20<=TODAY()),TEXT(DATE(YEAR(TODAY()),MONTH(TODAY()),1),"mmm d")&"–"&DAY(TODAY()),IF(AND(J20>=EOMONTH(TODAY(),-2)+1,J20<=EOMONTH(TODAY(),-1)),""&TEXT(EOMONTH(TODAY(),-2)+1,"mmm d")&"–"&DAY(TODAY()),""))
A21: LN-100958 | B21: CUS-200958 | C21: Christian | D21: Cruz | E21: Cortez | F21: 48 | G21: Male | H21: General Santos | I21: Region XII (SOCCSKSARGEN) | J21: 44957 | K21: 44967 | L21: Pickup | M21: Nissan | N21: Navara | O21: 1807000 | P21: 414800 | Q21: 1392200 | R21: 36 | S21: 13.87 | T21: 54763.73 | U21: Approved | V21: Defaulted | W21: 1861966.8 | X21: 109527.6 | Y21: 1971494.4 | Z21: 62 | AA21: 61-90 Days | AB21: Iloilo | AC21: J. Espino | AD21: Monthly | AE21: 77.04 | AF21: 2 | AG21: High Risk | AH21: 10 | AI21: =IF(F21<25,"18-24",IF(F21<35,"25-34",IF(F21<45,"35-44",IF(F21<55,"45-54",IF(F21<65,"55-64","65+"))))) -> 45-54 | AJ21: =YEAR(tbl_LoanData[[#This Row],[Application Date]]) -> 2023 | AK21: =TEXT(tbl_LoanData[[#This Row],[Application Date]],"MMMM") -> January | AL21: =DATE(YEAR(tbl_LoanData[[#This Row],[Application Date]]),MONTH(tbl_LoanData[[#This Row],[Application Date]]),1) -> 44927 | AM21: =IF(AND(tbl_LoanData[[#This Row],[Application Date]]>=EOMONTH(TODAY(),-1)+1,tbl_LoanData[[#This Row],[Application Date]]<=TODAY()),tbl_LoanData[[#This Row],[Loan Amount]],0) -> 0 | AN21: =tbl_LoanData[[#This Row],[Amount Paid]]-(Q21-X21) -> 579294.42 | AO21: =IF(tbl_LoanData[[#This Row],[Application Status]]="Approved",1,0) -> 1 | AP21: =IF(AND(J21>=DATE(YEAR(TODAY()),MONTH(TODAY()),1),J21<=TODAY()),"Current MTD",IF(AND(J21>=EOMONTH(TODAY(),-2)+1,J21<=EOMONTH(TODAY(),-1)),"Previous MTD","")) | AQ21: =IF(AND(J21>=DATE(YEAR(TODAY()),MONTH(TODAY()),1),J21<=TODAY()),TEXT(DATE(YEAR(TODAY()),MONTH(TODAY()),1),"mmm d")&"–"&DAY(TODAY()),IF(AND(J21>=EOMONTH(TODAY(),-2)+1,J21<=EOMONTH(TODAY(),-1)),""&TEXT(EOMONTH(TODAY(),-2)+1,"mmm d")&"–"&DAY(TODAY()),""))
A22: LN-100977 | B22: CUS-200977 | C22: Efren | D22: Ramos | E22: Aguilar | F22: 39 | G22: Male | H22: Lucena | I22: Region IV-A (CALABARZON) | J22: 44934 | K22: 44953 | L22: Sedan | M22: Mitsubishi | N22: Mirage G4 | O22: 968000 | P22: 126100 | Q22: 841900 | R22: 48 | S22: 8.3 | T22: 23362.72 | U22: Approved | V22: Active | W22: 911146.08 | X22: 210264.72 | Y22: 1121410.8 | Z22: 128 | AA22: Over 90 Days | AB22: Iloilo | AC22: J. Espino | AD22: Monthly | AE22: 86.97 | AF22: 4 | AG22: High Risk | AH22: 19 | AI22: =IF(F22<25,"18-24",IF(F22<35,"25-34",IF(F22<45,"35-44",IF(F22<55,"45-54",IF(F22<65,"55-64","65+"))))) -> 35-44 | AJ22: =YEAR(tbl_LoanData[[#This Row],[Application Date]]) -> 2023 | AK22: =TEXT(tbl_LoanData[[#This Row],[Application Date]],"MMMM") -> January | AL22: =DATE(YEAR(tbl_LoanData[[#This Row],[Application Date]]),MONTH(tbl_LoanData[[#This Row],[Application Date]]),1) -> 44927 | AM22: =IF(AND(tbl_LoanData[[#This Row],[Application Date]]>=EOMONTH(TODAY(),-1)+1,tbl_LoanData[[#This Row],[Application Date]]<=TODAY()),tbl_LoanData[[#This Row],[Loan Amount]],0) -> 0 | AN22: =tbl_LoanData[[#This Row],[Amount Paid]]-(Q22-X22) -> 279510.8 | AO22: =IF(tbl_LoanData[[#This Row],[Application Status]]="Approved",1,0) -> 1 | AP22: =IF(AND(J22>=DATE(YEAR(TODAY()),MONTH(TODAY()),1),J22<=TODAY()),"Current MTD",IF(AND(J22>=EOMONTH(TODAY(),-2)+1,J22<=EOMONTH(TODAY(),-1)),"Previous MTD","")) | AQ22: =IF(AND(J22>=DATE(YEAR(TODAY()),MONTH(TODAY()),1),J22<=TODAY()),TEXT(DATE(YEAR(TODAY()),MONTH(TODAY()),1),"mmm d")&"–"&DAY(TODAY()),IF(AND(J22>=EOMONTH(TODAY(),-2)+1,J22<=EOMONTH(TODAY(),-1)),""&TEXT(EOMONTH(TODAY(),-2)+1,"mmm d")&"–"&DAY(TODAY()),""))
A23: LN-101017 | B23: CUS-201017 | C23: Camille | D23: Garcia | E23: Torres | F23: 62 | G23: Female | H23: Naga (Camarines Sur) | I23: Region V (Bicol Region) | J23: 44931 | K23: 44941 | L23: Sedan | M23: Honda | N23: Civic | O23: 999000 | P23: 341700 | Q23: 657300 | R23: 36 | S23: 5.26 | T23: 21139.5 | U23: Approved | V23: Defaulted | W23: 739882.5 | X23: 21139.44 | Y23: 761021.94 | Z23: 32 | AA23: 31-60 Days | AB23: Makati | AC23: D. Morales | AD23: Monthly | AE23: 65.8 | AF23: 1 | AG23: Medium RIsk | AH23: 10 | AI23: =IF(F23<25,"18-24",IF(F23<35,"25-34",IF(F23<45,"35-44",IF(F23<55,"45-54",IF(F23<65,"55-64","65+"))))) -> 55-64 | AJ23: =YEAR(tbl_LoanData[[#This Row],[Application Date]]) -> 2023 | AK23: =TEXT(tbl_LoanData[[#This Row],[Application Date]],"MMMM") -> January | AL23: =DATE(YEAR(tbl_LoanData[[#This Row],[Application Date]]),MONTH(tbl_LoanData[[#This Row],[Application Date]]),1) -> 44927 | AM23: =IF(AND(tbl_LoanData[[#This Row],[Application Date]]>=EOMONTH(TODAY(),-1)+1,tbl_LoanData[[#This Row],[Application Date]]<=TODAY()),tbl_LoanData[[#This Row],[Loan Amount]],0) -> 0 | AN23: =tbl_LoanData[[#This Row],[Amount Paid]]-(Q23-X23) -> 103721.94 | AO23: =IF(tbl_LoanData[[#This Row],[Application Status]]="Approved",1,0) -> 1 | AP23: =IF(AND(J23>=DATE(YEAR(TODAY()),MONTH(TODAY()),1),J23<=TODAY()),"Current MTD",IF(AND(J23>=EOMONTH(TODAY(),-2)+1,J23<=EOMONTH(TODAY(),-1)),"Previous MTD","")) | AQ23: =IF(AND(J23>=DATE(YEAR(TODAY()),MONTH(TODAY()),1),J23<=TODAY()),TEXT(DATE(YEAR(TODAY()),MONTH(TODAY()),1),"mmm d")&"–"&DAY(TODAY()),IF(AND(J23>=EOMONTH(TODAY(),-2)+1,J23<=EOMONTH(TODAY(),-1)),""&TEXT(EOMONTH(TODAY(),-2)+1,"mmm d")&"–"&DAY(TODAY()),""))
A24: LN-101054 | B24: CUS-201054 | C24: Reynaldo | D24: Domingo | E24: Santos | F24: 48 | G24: Male | H24: Cagayan de Oro | I24: Region X (Northern Mindanao) | J24: 44932 | K24: 44946 | L24: Sedan | M24: Hyundai | N24: Accent | O24: 1538000 | P24: 300900 | Q24: 1237100 | R24: 36 | S24: 8.26 | T24: 42879.26 | U24: Approved | V24: Closed - Fully Paid | W24: 1543653.4 | X24: 0 | Y24: 1543653.4 | Z24: 0 | AA24: Current | AB24: Baguio | AC24: F. Lacson | AD24: Monthly | AE24: 80.44 | AF24: 0 | AG24: Low Risk | AH24: 14 | AI24: =IF(F24<25,"18-24",IF(F24<35,"25-34",IF(F24<45,"35-44",IF(F24<55,"45-54",IF(F24<65,"55-64","65+"))))) -> 45-54 | AJ24: =YEAR(tbl_LoanData[[#This Row],[Application Date]]) -> 2023 | AK24: =TEXT(tbl_LoanData[[#This Row],[Application Date]],"MMMM") -> January | AL24: =DATE(YEAR(tbl_LoanData[[#This Row],[Application Date]]),MONTH(tbl_LoanData[[#This Row],[Application Date]]),1) -> 44927 | AM24: =IF(AND(tbl_LoanData[[#This Row],[Application Date]]>=EOMONTH(TODAY(),-1)+1,tbl_LoanData[[#This Row],[Application Date]]<=TODAY()),tbl_LoanData[[#This Row],[Loan Amount]],0) -> 0 | AN24: =tbl_LoanData[[#This Row],[Amount Paid]]-(Q24-X24) -> 306553.38 | AO24: =IF(tbl_LoanData[[#This Row],[Application Status]]="Approved",1,0) -> 1 | AP24: =IF(AND(J24>=DATE(YEAR(TODAY()),MONTH(TODAY()),1),J24<=TODAY()),"Current MTD",IF(AND(J24>=EOMONTH(TODAY(),-2)+1,J24<=EOMONTH(TODAY(),-1)),"Previous MTD","")) | AQ24: =IF(AND(J24>=DATE(YEAR(TODAY()),MONTH(TODAY()),1),J24<=TODAY()),TEXT(DATE(YEAR(TODAY()),MONTH(TODAY()),1),"mmm d")&"–"&DAY(TODAY()),IF(AND(J24>=EOMONTH(TODAY(),-2)+1,J24<=EOMONTH(TODAY(),-1)),""&TEXT(EOMONTH(TODAY(),-2)+1,"mmm d")&"–"&DAY(TODAY()),""))
A25: LN-101135 | B25: CUS-201135 | C25: Michael | D25: Ocampo | E25: Marquez | F25: 28 | G25: Male | H25: Antipolo | I25: Region IV-A (CALABARZON) | J25: 44952 | L25: Sedan | M25: Toyota | N25: Camry | O25: 1271000 | P25: 487200 | Q25: 783800 | R25: 48 | S25: 12.05 | T25: 24199.82 | U25: Rejected | V25: Not Applicable | W25: 0 | X25: 0 | Y25: 1161591.6 | Z25: 0 | AA25: Not Applicable | AB25: Baguio | AC25: F. Lacson | AD25: Monthly | AE25: 61.67 | AF25: 0 | AG25: Not Applicable | AI25: =IF(F25<25,"18-24",IF(F25<35,"25-34",IF(F25<45,"35-44",IF(F25<55,"45-54",IF(F25<65,"55-64","65+"))))) -> 25-34 | AJ25: =YEAR(tbl_LoanData[[#This Row],[Application Date]]) -> 2023 | AK25: =TEXT(tbl_LoanData[[#This Row],[Application Date]],"MMMM") -> January | AL25: =DATE(YEAR(tbl_LoanData[[#This Row],[Application Date]]),MONTH(tbl_LoanData[[#This Row],[Application Date]]),1) -> 44927 | AM25: =IF(AND(tbl_LoanData[[#This Row],[Application Date]]>=EOMONTH(TODAY(),-1)+1,tbl_LoanData[[#This Row],[Application Date]]<=TODAY()),tbl_LoanData[[#This Row],[Loan Amount]],0) -> 0 | AN25: =tbl_LoanData[[#This Row],[Amount Paid]]-(Q25-X25) -> -783800 | AO25: =IF(tbl_LoanData[[#This Row],[Application Status]]="Approved",1,0) -> 0 | AP25: =IF(AND(J25>=DATE(YEAR(TODAY()),MONTH(TODAY()),1),J25<=TODAY()),"Current MTD",IF(AND(J25>=EOMONTH(TODAY(),-2)+1,J25<=EOMONTH(TODAY(),-1)),"Previous MTD","")) | AQ25: =IF(AND(J25>=DATE(YEAR(TODAY()),MONTH(TODAY()),1),J25<=TODAY()),TEXT(DATE(YEAR(TODAY()),MONTH(TODAY()),1),"mmm d")&"–"&DAY(TODAY()),IF(AND(J25>=EOMONTH(TODAY(),-2)+1,J25<=EOMONTH(TODAY(),-1)),""&TEXT(EOMONTH(TODAY(),-2)+1,"mmm d")&"–"&DAY(TODAY()),""))
A26: LN-101243 | B26: CUS-201243 | C26: Angelo | D26: Rivera | E26: Rivera | F26: 63 | G26: Male | H26: Calamba | I26: Region IV-A (CALABARZON) | J26: 44953 | K26: 44963 | L26: SUV | M26: Kia | N26: Seltos | O26: 1524000 | P26: 601700 | Q26: 922300 | R26: 36 | S26: 5.31 | T26: 29700.62 | U26: Approved | V26: Closed - Fully Paid | W26: 1069222.4 | X26: 0 | Y26: 1069222.4 | Z26: 0 | AA26: Current | AB26: Quezon City | AC26: A. Ramirez | AD26: Monthly | AE26: 60.52 | AF26: 0 | AG26: Low Risk | AH26: 10 | AI26: =IF(F26<25,"18-24",IF(F26<35,"25-34",IF(F26<45,"35-44",IF(F26<55,"45-54",IF(F26<65,"55-64","65+"))))) -> 55-64 | AJ26: =YEAR(tbl_LoanData[[#This Row],[Application Date]]) -> 2023 | AK26: =TEXT(tbl_LoanData[[#This Row],[Application Date]],"MMMM") -> January | AL26: =DATE(YEAR(tbl_LoanData[[#This Row],[Application Date]]),MONTH(tbl_LoanData[[#This Row],[Application Date]]),1) -> 44927 | AM26: =IF(AND(tbl_LoanData[[#This Row],[Application Date]]>=EOMONTH(TODAY(),-1)+1,tbl_LoanData[[#This Row],[Application Date]]<=TODAY()),tbl_LoanData[[#This Row],[Loan Amount]],0) -> 0 | AN26: =tbl_LoanData[[#This Row],[Amount Paid]]-(Q26-X26) -> 146922.39 | AO26: =IF(tbl_LoanData[[#This Row],[Application Status]]="Approved",1,0) -> 1 | AP26: =IF(AND(J26>=DATE(YEAR(TODAY()),MONTH(TODAY()),1),J26<=TODAY()),"Current MTD",IF(AND(J26>=EOMONTH(TODAY(),-2)+1,J26<=EOMONTH(TODAY(),-1)),"Previous MTD","")) | AQ26: =IF(AND(J26>=DATE(YEAR(TODAY()),MONTH(TODAY()),1),J26<=TODAY()),TEXT(DATE(YEAR(TODAY()),MONTH(TODAY()),1),"mmm d")&"–"&DAY(TODAY()),IF(AND(J26>=EOMONTH(TODAY(),-2)+1,J26<=EOMONTH(TODAY(),-1)),""&TEXT(EOMONTH(TODAY(),-2)+1,"mmm d")&"–"&DAY(TODAY()),""))
A27: LN-101244 | B27: CUS-201244 | C27: Teodoro | D27: Aquino | E27: Gonzales | F27: 41 | G27: Male | H27: Bacolod | I27: Region VI (Western Visayas) | J27: 44956 | L27: MPV/Van | M27: Nissan | N27: Urvan | O27: 1336000 | P27: 226000 | Q27: 1110000 | R27: 12 | S27: 11.49 | T27: 103128.25 | U27: Rejected | V27: Not Applicable | W27: 0 | X27: 0 | Y27: 1237539 | Z27: 0 | AA27: Not Applicable | AB27: Manila | AC27: I. Cabrera | AD27: Monthly | AE27: 83.08 | AF27: 0 | AG27: Not Applicable | AI27: =IF(F27<25,"18-24",IF(F27<35,"25-34",IF(F27<45,"35-44",IF(F27<55,"45-54",IF(F27<65,"55-64","65+"))))) -> 35-44 | AJ27: =YEAR(tbl_LoanData[[#This Row],[Application Date]]) -> 2023 | AK27: =TEXT(tbl_LoanData[[#This Row],[Application Date]],"MMMM") -> January | AL27: =DATE(YEAR(tbl_LoanData[[#This Row],[Application Date]]),MONTH(tbl_LoanData[[#This Row],[Application Date]]),1) -> 44927 | AM27: =IF(AND(tbl_LoanData[[#This Row],[Application Date]]>=EOMONTH(TODAY(),-1)+1,tbl_LoanData[[#This Row],[Application Date]]<=TODAY()),tbl_LoanData[[#This Row],[Loan Amount]],0) -> 0 | AN27: =tbl_LoanData[[#This Row],[Amount Paid]]-(Q27-X27) -> -1110000 | AO27: =IF(tbl_LoanData[[#This Row],[Application Status]]="Approved",1,0) -> 0 | AP27: =IF(AND(J27>=DATE(YEAR(TODAY()),MONTH(TODAY()),1),J27<=TODAY()),"Current MTD",IF(AND(J27>=EOMONTH(TODAY(),-2)+1,J27<=EOMONTH(TODAY(),-1)),"Previous MTD","")) | AQ27: =IF(AND(J27>=DATE(YEAR(TODAY()),MONTH(TODAY()),1),J27<=TODAY()),TEXT(DATE(YEAR(TODAY()),MONTH(TODAY()),1),"mmm d")&"–"&DAY(TODAY()),IF(AND(J27>=EOMONTH(TODAY(),-2)+1,J27<=EOMONTH(TODAY(),-1)),""&TEXT(EOMONTH(TODAY(),-2)+1,"mmm d")&"–"&DAY(TODAY()),""))
A28: LN-101267 | B28: CUS-201267 | C28: Bea | D28: Salazar | E28: Umali | F28: 54 | G28: Female | H28: Naga (Camarines Sur) | I28: Region V (Bicol Region) | J28: 44957 | L28: MPV/Van | M28: Toyota | N28: Avanza | O28: 973000 | P28: 195700 | Q28: 777300 | R28: 24 | S28: 7.21 | T28: 37057.78 | U28: Rejected | V28: Not Applicable | W28: 0 | X28: 0 | Y28: 889386.66 | Z28: 0 | AA28: Not Applicable | AB28: Manila | AC28: A. Ramirez | AD28: Monthly | AE28: 79.89 | AF28: 0 | AG28: Not Applicable | AI28: =IF(F28<25,"18-24",IF(F28<35,"25-34",IF(F28<45,"35-44",IF(F28<55,"45-54",IF(F28<65,"55-64","65+"))))) -> 45-54 | AJ28: =YEAR(tbl_LoanData[[#This Row],[Application Date]]) -> 2023 | AK28: =TEXT(tbl_LoanData[[#This Row],[Application Date]],"MMMM") -> January | AL28: =DATE(YEAR(tbl_LoanData[[#This Row],[Application Date]]),MONTH(tbl_LoanData[[#This Row],[Application Date]]),1) -> 44927 | AM28: =IF(AND(tbl_LoanData[[#This Row],[Application Date]]>=EOMONTH(TODAY(),-1)+1,tbl_LoanData[[#This Row],[Application Date]]<=TODAY()),tbl_LoanData[[#This Row],[Loan Amount]],0) -> 0 | AN28: =tbl_LoanData[[#This Row],[Amount Paid]]-(Q28-X28) -> -777300 | AO28: =IF(tbl_LoanData[[#This Row],[Application Status]]="Approved",1,0) -> 0 | AP28: =IF(AND(J28>=DATE(YEAR(TODAY()),MONTH(TODAY()),1),J28<=TODAY()),"Current MTD",IF(AND(J28>=EOMONTH(TODAY(),-2)+1,J28<=EOMONTH(TODAY(),-1)),"Previous MTD","")) | AQ28: =IF(AND(J28>=DATE(YEAR(TODAY()),MONTH(TODAY()),1),J28<=TODAY()),TEXT(DATE(YEAR(TODAY()),MONTH(TODAY()),1),"mmm d")&"–"&DAY(TODAY()),IF(AND(J28>=EOMONTH(TODAY(),-2)+1,J28<=EOMONTH(TODAY(),-1)),""&TEXT(EOMONTH(TODAY(),-2)+1,"mmm d")&"–"&DAY(TODAY()),""))
A29: LN-101285 | B29: CUS-201285 | C29: Marites | D29: Del Rosario | E29: Salazar | F29: 41 | G29: Female | H29: Angeles City | I29: Region III (Central Luzon) | J29: 44942 | K29: 44955 | L29: SUV | M29: Hyundai | N29: Tucson | O29: 1893000 | P29: 421700 | Q29: 1471300 | R29: 24 | S29: 5.79 | T29: 68403.19 | U29: Approved | V29: Closed - Fully Paid | W29: 1641676.5 | X29: 0 | Y29: 1641676.5 | Z29: 0 | AA29: Current | AB29: Baguio | AC29: D. Morales | AD29: Monthly | AE29: 77.72 | AF29: 0 | AG29: Low Risk | AH29: 13 | AI29: =IF(F29<25,"18-24",IF(F29<35,"25-34",IF(F29<45,"35-44",IF(F29<55,"45-54",IF(F29<65,"55-64","65+"))))) -> 35-44 | AJ29: =YEAR(tbl_LoanData[[#This Row],[Application Date]]) -> 2023 | AK29: =TEXT(tbl_LoanData[[#This Row],[Application Date]],"MMMM") -> January | AL29: =DATE(YEAR(tbl_LoanData[[#This Row],[Application Date]]),MONTH(tbl_LoanData[[#This Row],[Application Date]]),1) -> 44927 | AM29: =IF(AND(tbl_LoanData[[#This Row],[Application Date]]>=EOMONTH(TODAY(),-1)+1,tbl_LoanData[[#This Row],[Application Date]]<=TODAY()),tbl_LoanData[[#This Row],[Loan Amount]],0) -> 0 | AN29: =tbl_LoanData[[#This Row],[Amount Paid]]-(Q29-X29) -> 170376.54 | AO29: =IF(tbl_LoanData[[#This Row],[Application Status]]="Approved",1,0) -> 1 | AP29: =IF(AND(J29>=DATE(YEAR(TODAY()),MONTH(TODAY()),1),J29<=TODAY()),"Current MTD",IF(AND(J29>=EOMONTH(TODAY(),-2)+1,J29<=EOMONTH(TODAY(),-1)),"Previous MTD","")) | AQ29: =IF(AND(J29>=DATE(YEAR(TODAY()),MONTH(TODAY()),1),J29<=TODAY()),TEXT(DATE(YEAR(TODAY()),MONTH(TODAY()),1),"mmm d")&"–"&DAY(TODAY()),IF(AND(J29>=EOMONTH(TODAY(),-2)+1,J29<=EOMONTH(TODAY(),-1)),""&TEXT(EOMONTH(TODAY(),-2)+1,"mmm d")&"–"&DAY(TODAY()),""))
A30: LN-101358 | B30: CUS-201358 | C30: Marites | D30: Reyes | E30: Sarmiento | F30: 51 | G30: Female | H30: Cavite City | I30: Region IV-A (CALABARZON) | J30: 44934 | K30: 44943 | L30: Sedan | M30: Nissan | N30: Sylphy | O30: 887000 | P30: 238300 | Q30: 648700 | R30: 36 | S30: 6.03 | T30: 21279.16 | U30: Approved | V30: Closed - Fully Paid | W30: 766049.83 | X30: 0 | Y30: 766049.83 | Z30: 0 | AA30: Current | AB30: Pampanga | AC30: E. Ferrer | AD30: Monthly | AE30: 73.13 | AF30: 0 | AG30: Low Risk | AH30: 9 | AI30: =IF(F30<25,"18-24",IF(F30<35,"25-34",IF(F30<45,"35-44",IF(F30<55,"45-54",IF(F30<65,"55-64","65+"))))) -> 45-54 | AJ30: =YEAR(tbl_LoanData[[#This Row],[Application Date]]) -> 2023 | AK30: =TEXT(tbl_LoanData[[#This Row],[Application Date]],"MMMM") -> January | AL30: =DATE(YEAR(tbl_LoanData[[#This Row],[Application Date]]),MONTH(tbl_LoanData[[#This Row],[Application Date]]),1) -> 44927 | AM30: =IF(AND(tbl_LoanData[[#This Row],[Application Date]]>=EOMONTH(TODAY(),-1)+1,tbl_LoanData[[#This Row],[Application Date]]<=TODAY()),tbl_LoanData[[#This Row],[Loan Amount]],0) -> 0 | AN30: =tbl_LoanData[[#This Row],[Amount Paid]]-(Q30-X30) -> 117349.83 | AO30: =IF(tbl_LoanData[[#This Row],[Application Status]]="Approved",1,0) -> 1 | AP30: =IF(AND(J30>=DATE(YEAR(TODAY()),MONTH(TODAY()),1),J30<=TODAY()),"Current MTD",IF(AND(J30>=EOMONTH(TODAY(),-2)+1,J30<=EOMONTH(TODAY(),-1)),"Previous MTD","")) | AQ30: =IF(AND(J30>=DATE(YEAR(TODAY()),MONTH(TODAY()),1),J30<=TODAY()),TEXT(DATE(YEAR(TODAY()),MONTH(TODAY()),1),"mmm d")&"–"&DAY(TODAY()),IF(AND(J30>=EOMONTH(TODAY(),-2)+1,J30<=EOMONTH(TODAY(),-1)),""&TEXT(EOMONTH(TODAY(),-2)+1,"mmm d")&"–"&DAY(TODAY()),""))
A31: LN-101376 | B31: CUS-201376 | C31: Fe | D31: Castillo | E31: Umali | F31: 28 | G31: Female | H31: Olongapo | I31: Region III (Central Luzon) | J31: 44946 | L31: Sedan | M31: Nissan | N31: Almera | O31: 1500000 | P31: 476500 | Q31: 1023500 | R31: 48 | S31: 10.45 | T31: 30235.9 | U31: Rejected | V31: Not Applicable | W31: 0 | X31: 0 | Y31: 1451323 | Z31: 0 | AA31: Not Applicable | AB31: Cebu | AC31: J. Espino | AD31: Monthly | AE31: 68.23 | AF31: 0 | AG31: Not Applicable | AI31: =IF(F31<25,"18-24",IF(F31<35,"25-34",IF(F31<45,"35-44",IF(F31<55,"45-54",IF(F31<65,"55-64","65+"))))) -> 25-34 | AJ31: =YEAR(tbl_LoanData[[#This Row],[Application Date]]) -> 2023 | AK31: =TEXT(tbl_LoanData[[#This Row],[Application Date]],"MMMM") -> January | AL31: =DATE(YEAR(tbl_LoanData[[#This Row],[Application Date]]),MONTH(tbl_LoanData[[#This Row],[Application Date]]),1) -> 44927 | AM31: =IF(AND(tbl_LoanData[[#This Row],[Application Date]]>=EOMONTH(TODAY(),-1)+1,tbl_LoanData[[#This Row],[Application Date]]<=TODAY()),tbl_LoanData[[#This Row],[Loan Amount]],0) -> 0 | AN31: =tbl_LoanData[[#This Row],[Amount Paid]]-(Q31-X31) -> -1023500 | AO31: =IF(tbl_LoanData[[#This Row],[Application Status]]="Approved",1,0) -> 0 | AP31: =IF(AND(J31>=DATE(YEAR(TODAY()),MONTH(TODAY()),1),J31<=TODAY()),"Current MTD",IF(AND(J31>=EOMONTH(TODAY(),-2)+1,J31<=EOMONTH(TODAY(),-1)),"Previous MTD","")) | AQ31: =IF(AND(J31>=DATE(YEAR(TODAY()),MONTH(TODAY()),1),J31<=TODAY()),TEXT(DATE(YEAR(TODAY()),MONTH(TODAY()),1),"mmm d")&"–"&DAY(TODAY()),IF(AND(J31>=EOMONTH(TODAY(),-2)+1,J31<=EOMONTH(TODAY(),-1)),""&TEXT(EOMONTH(TODAY(),-2)+1,"mmm d")&"–"&DAY(TODAY()),""))
A32: LN-101676 | B32: CUS-201676 | C32: Teresa | D32: Cruz | E32: Panganiban | F32: 61 | G32: Female | H32: San Fernando (Pampanga) | I32: Region III (Central Luzon) | J32: 44951 | K32: 44963 | L32: Sedan | M32: Honda | N32: City | O32: 1259000 | P32: 158400 | Q32: 1100600 | R32: 24 | S32: 12.09 | T32: 56946.88 | U32: Approved | V32: Closed - Fully Paid | W32: 1366725.1 | X32: 0 | Y32: 1366725.1 | Z32: 0 | AA32: Current | AB32: Manila | AC32: C. Villareal | AD32: Monthly | AE32: 87.42 | AF32: 0 | AG32: Low Risk | AH32: 12 | AI32: =IF(F32<25,"18-24",IF(F32<35,"25-34",IF(F32<45,"35-44",IF(F32<55,"45-54",IF(F32<65,"55-64","65+"))))) -> 55-64 | AJ32: =YEAR(tbl_LoanData[[#This Row],[Application Date]]) -> 2023 | AK32: =TEXT(tbl_LoanData[[#This Row],[Application Date]],"MMMM") -> January | AL32: =DATE(YEAR(tbl_LoanData[[#This Row],[Application Date]]),MONTH(tbl_LoanData[[#This Row],[Application Date]]),1) -> 44927 | AM32: =IF(AND(tbl_LoanData[[#This Row],[Application Date]]>=EOMONTH(TODAY(),-1)+1,tbl_LoanData[[#This Row],[Application Date]]<=TODAY()),tbl_LoanData[[#This Row],[Loan Amount]],0) -> 0 | AN32: =tbl_LoanData[[#This Row],[Amount Paid]]-(Q32-X32) -> 266125.08 | AO32: =IF(tbl_LoanData[[#This Row],[Application Status]]="Approved",1,0) -> 1 | AP32: =IF(AND(J32>=DATE(YEAR(TODAY()),MONTH(TODAY()),1),J32<=TODAY()),"Current MTD",IF(AND(J32>=EOMONTH(TODAY(),-2)+1,J32<=EOMONTH(TODAY(),-1)),"Previous MTD","")) | AQ32: =IF(AND(J32>=DATE(YEAR(TODAY()),MONTH(TODAY()),1),J32<=TODAY()),TEXT(DATE(YEAR(TODAY()),MONTH(TODAY()),1),"mmm d")&"–"&DAY(TODAY()),IF(AND(J32>=EOMONTH(TODAY(),-2)+1,J32<=EOMONTH(TODAY(),-1)),""&TEXT(EOMONTH(TODAY(),-2)+1,"mmm d")&"–"&DAY(TODAY()),""))
A33: LN-101914 | B33: CUS-201914 | C33: Rafael | D33: Santos | E33: Mendoza | F33: 32 | G33: Male | H33: General Santos | I33: Region XII (SOCCSKSARGEN) | J33: 44934 | K33: 44940 | L33: MPV/Van | M33: Mitsubishi | N33: Xpander | O33: 1155000 | P33: 303800 | Q33: 851200 | R33: 60 | S33: 12.54 | T33: 23081.71 | U33: Approved | V33: Active | W33: 992513.53 | X33: 392388.87 | Y33: 1384902.4 | Z33: 0 | AA33: Current | AB33: Quezon City | AC33: J. Espino | AD33: Monthly | AE33: 73.7 | AF33: 0 | AG33: Low Risk | AH33: 6 | AI33: =IF(F33<25,"18-24",IF(F33<35,"25-34",IF(F33<45,"35-44",IF(F33<55,"45-54",IF(F33<65,"55-64","65+"))))) -> 25-34 | AJ33: =YEAR(tbl_LoanData[[#This Row],[Application Date]]) -> 2023 | AK33: =TEXT(tbl_LoanData[[#This Row],[Application Date]],"MMMM") -> January | AL33: =DATE(YEAR(tbl_LoanData[[#This Row],[Application Date]]),MONTH(tbl_LoanData[[#This Row],[Application Date]]),1) -> 44927 | AM33: =IF(AND(tbl_LoanData[[#This Row],[Application Date]]>=EOMONTH(TODAY(),-1)+1,tbl_LoanData[[#This Row],[Application Date]]<=TODAY()),tbl_LoanData[[#This Row],[Loan Amount]],0) -> 0 | AN33: =tbl_LoanData[[#This Row],[Amount Paid]]-(Q33-X33) -> 533702.4 | AO33: =IF(tbl_LoanData[[#This Row],[Application Status]]="Approved",1,0) -> 1 | AP33: =IF(AND(J33>=DATE(YEAR(TODAY()),MONTH(TODAY()),1),J33<=TODAY()),"Current MTD",IF(AND(J33>=EOMONTH(TODAY(),-2)+1,J33<=EOMONTH(TODAY(),-1)),"Previous MTD","")) | AQ33: =IF(AND(J33>=DATE(YEAR(TODAY()),MONTH(TODAY()),1),J33<=TODAY()),TEXT(DATE(YEAR(TODAY()),MONTH(TODAY()),1),"mmm d")&"–"&DAY(TODAY()),IF(AND(J33>=EOMONTH(TODAY(),-2)+1,J33<=EOMONTH(TODAY(),-1)),""&TEXT(EOMONTH(TODAY(),-2)+1,"mmm d")&"–"&DAY(TODAY()),""))
A34: LN-101916 | B34: CUS-201916 | C34: Imelda | D34: Castillo | E34: Bautista | F34: 59 | G34: Female | H34: Antipolo | I34: Region IV-A (CALABARZON) | J34: 44952 | K34: 44971 | L34: SUV | M34: Ford | N34: Everest | O34: 1863000 | P34: 500000 | Q34: 1363000 | R34: 36 | S34: 8.19 | T34: 47163.59 | U34: Approved | V34: Closed - Fully Paid | W34: 1697889.1 | X34: 0 | Y34: 1697889.1 | Z34: 0 | AA34: Current | AB34: Quezon City | AC34: D. Morales | AD34: Monthly | AE34: 73.16 | AF34: 0 | AG34: Low Risk | AH34: 19 | AI34: =IF(F34<25,"18-24",IF(F34<35,"25-34",IF(F34<45,"35-44",IF(F34<55,"45-54",IF(F34<65,"55-64","65+"))))) -> 55-64 | AJ34: =YEAR(tbl_LoanData[[#This Row],[Application Date]]) -> 2023 | AK34: =TEXT(tbl_LoanData[[#This Row],[Application Date]],"MMMM") -> January | AL34: =DATE(YEAR(tbl_LoanData[[#This Row],[Application Date]]),MONTH(tbl_LoanData[[#This Row],[Application Date]]),1) -> 44927 | AM34: =IF(AND(tbl_LoanData[[#This Row],[Application Date]]>=EOMONTH(TODAY(),-1)+1,tbl_LoanData[[#This Row],[Application Date]]<=TODAY()),tbl_LoanData[[#This Row],[Loan Amount]],0) -> 0 | AN34: =tbl_LoanData[[#This Row],[Amount Paid]]-(Q34-X34) -> 334889.1 | AO34: =IF(tbl_LoanData[[#This Row],[Application Status]]="Approved",1,0) -> 1 | AP34: =IF(AND(J34>=DATE(YEAR(TODAY()),MONTH(TODAY()),1),J34<=TODAY()),"Current MTD",IF(AND(J34>=EOMONTH(TODAY(),-2)+1,J34<=EOMONTH(TODAY(),-1)),"Previous MTD","")) | AQ34: =IF(AND(J34>=DATE(YEAR(TODAY()),MONTH(TODAY()),1),J34<=TODAY()),TEXT(DATE(YEAR(TODAY()),MONTH(TODAY()),1),"mmm d")&"–"&DAY(TODAY()),IF(AND(J34>=EOMONTH(TODAY(),-2)+1,J34<=EOMONTH(TODAY(),-1)),""&TEXT(EOMONTH(TODAY(),-2)+1,"mmm d")&"–"&DAY(TODAY()),""))
A35: LN-101979 | B35: CUS-201979 | C35: Gil | D35: Villanueva | E35: Pascual | F35: 33 | G35: Male | H35: Taguig | I35: NCR | J35: 44956 | K35: 44968 | L35: Sedan | M35: Hyundai | N35: Accent | O35: 1008000 | P35: 225100 | Q35: 782900 | R35: 12 | S35: 14.06 | T35: 74414.64 | U35: Approved | V35: Closed - Fully Paid | W35: 892975.74 | X35: 0 | Y35: 892975.74 | Z35: 0 | AA35: Current | AB35: Baguio | AC35: F. Lacson | AD35: Monthly | AE35: 77.67 | AF35: 0 | AG35: Low Risk | AH35: 12 | AI35: =IF(F35<25,"18-24",IF(F35<35,"25-34",IF(F35<45,"35-44",IF(F35<55,"45-54",IF(F35<65,"55-64","65+"))))) -> 25-34 | AJ35: =YEAR(tbl_LoanData[[#This Row],[Application Date]]) -> 2023 | AK35: =TEXT(tbl_LoanData[[#This Row],[Application Date]],"MMMM") -> January | AL35: =DATE(YEAR(tbl_LoanData[[#This Row],[Application Date]]),MONTH(tbl_LoanData[[#This Row],[Application Date]]),1) -> 44927 | AM35: =IF(AND(tbl_LoanData[[#This Row],[Application Date]]>=EOMONTH(TODAY(),-1)+1,tbl_LoanData[[#This Row],[Application Date]]<=TODAY()),tbl_LoanData[[#This Row],[Loan Amount]],0) -> 0 | AN35: =tbl_LoanData[[#This Row],[Amount Paid]]-(Q35-X35) -> 110075.74 | AO35: =IF(tbl_LoanData[[#This Row],[Application Status]]="Approved",1,0) -> 1 | AP35: =IF(AND(J35>=DATE(YEAR(TODAY()),MONTH(TODAY()),1),J35<=TODAY()),"Current MTD",IF(AND(J35>=EOMONTH(TODAY(),-2)+1,J35<=EOMONTH(TODAY(),-1)),"Previous MTD","")) | AQ35: =IF(AND(J35>=DATE(YEAR(TODAY()),MONTH(TODAY()),1),J35<=TODAY()),TEXT(DATE(YEAR(TODAY()),MONTH(TODAY()),1),"mmm d")&"–"&DAY(TODAY()),IF(AND(J35>=EOMONTH(TODAY(),-2)+1,J35<=EOMONTH(TODAY(),-1)),""&TEXT(EOMONTH(TODAY(),-2)+1,"mmm d")&"–"&DAY(TODAY()),""))
A36: LN-102030 | B36: CUS-202030 | C36: Juan | D36: Fernandez | E36: Guevarra | F36: 38 | G36: Male | H36: Laoag | I36: Region I (Ilocos Region) | J36: 44941 | K36: 44953 | L36: SUV | M36: Hyundai | N36: Creta | O36: 1715000 | P36: 397000 | Q36: 1318000 | R36: 48 | S36: 6.4 | T36: 34487.67 | U36: Approved | V36: Active | W36: 1482969.8 | X36: 172438.19 | Y36: 1655408 | Z36: 0 | AA36: Current | AB36: Pampanga | AC36: J. Espino | AD36: Monthly | AE36: 76.85 | AF36: 0 | AG36: Low Risk | AH36: 12 | AI36: =IF(F36<25,"18-24",IF(F36<35,"25-34",IF(F36<45,"35-44",IF(F36<55,"45-54",IF(F36<65,"55-64","65+"))))) -> 35-44 | AJ36: =YEAR(tbl_LoanData[[#This Row],[Application Date]]) -> 2023 | AK36: =TEXT(tbl_LoanData[[#This Row],[Application Date]],"MMMM") -> January | AL36: =DATE(YEAR(tbl_LoanData[[#This Row],[Application Date]]),MONTH(tbl_LoanData[[#This Row],[Application Date]]),1) -> 44927 | AM36: =IF(AND(tbl_LoanData[[#This Row],[Application Date]]>=EOMONTH(TODAY(),-1)+1,tbl_LoanData[[#This Row],[Application Date]]<=TODAY()),tbl_LoanData[[#This Row],[Loan Amount]],0) -> 0 | AN36: =tbl_LoanData[[#This Row],[Amount Paid]]-(Q36-X36) -> 337408 | AO36: =IF(tbl_LoanData[[#This Row],[Application Status]]="Approved",1,0) -> 1 | AP36: =IF(AND(J36>=DATE(YEAR(TODAY()),MONTH(TODAY()),1),J36<=TODAY()),"Current MTD",IF(AND(J36>=EOMONTH(TODAY(),-2)+1,J36<=EOMONTH(TODAY(),-1)),"Previous MTD","")) | AQ36: =IF(AND(J36>=DATE(YEAR(TODAY()),MONTH(TODAY()),1),J36<=TODAY()),TEXT(DATE(YEAR(TODAY()),MONTH(TODAY()),1),"mmm d")&"–"&DAY(TODAY()),IF(AND(J36>=EOMONTH(TODAY(),-2)+1,J36<=EOMONTH(TODAY(),-1)),""&TEXT(EOMONTH(TODAY(),-2)+1,"mmm d")&"–"&DAY(TODAY()),""))
A37: LN-102055 | B37: CUS-202055 | C37: Federico | D37: Domingo | E37: Zamora | F37: 34 | G37: Male | H37: Santa Rosa | I37: Region IV-A (CALABARZON) | J37: 44951 | K37: 44972 | L37: MPV/Van | M37: Honda | N37: Mobilio | O37: 1913000 | P37: 653800 | Q37: 1259200 | R37: 48 | S37: 6.34 | T37: 32886.11 | U37: Approved | V37: Active | W37: 1282558.3 | X37: 295974.83 | Y37: 1578533.1 | Z37: 90 | AA37: 61-90 Days | AB37: Cebu | AC37: C. Villareal | AD37: Monthly | AE37: 65.82 | AF37: 3 | AG37: High Risk | AH37: 21 | AI37: =IF(F37<25,"18-24",IF(F37<35,"25-34",IF(F37<45,"35-44",IF(F37<55,"45-54",IF(F37<65,"55-64","65+"))))) -> 25-34 | AJ37: =YEAR(tbl_LoanData[[#This Row],[Application Date]]) -> 2023 | AK37: =TEXT(tbl_LoanData[[#This Row],[Application Date]],"MMMM") -> January | AL37: =DATE(YEAR(tbl_LoanData[[#This Row],[Application Date]]),MONTH(tbl_LoanData[[#This Row],[Application Date]]),1) -> 44927 | AM37: =IF(AND(tbl_LoanData[[#This Row],[Application Date]]>=EOMONTH(TODAY(),-1)+1,tbl_LoanData[[#This Row],[Application Date]]<=TODAY()),tbl_LoanData[[#This Row],[Loan Amount]],0) -> 0 | AN37: =tbl_LoanData[[#This Row],[Amount Paid]]-(Q37-X37) -> 319333.12 | AO37: =IF(tbl_LoanData[[#This Row],[Application Status]]="Approved",1,0) -> 1 | AP37: =IF(AND(J37>=DATE(YEAR(TODAY()),MONTH(TODAY()),1),J37<=TODAY()),"Current MTD",IF(AND(J37>=EOMONTH(TODAY(),-2)+1,J37<=EOMONTH(TODAY(),-1)),"Previous MTD","")) | AQ37: =IF(AND(J37>=DATE(YEAR(TODAY()),MONTH(TODAY()),1),J37<=TODAY()),TEXT(DATE(YEAR(TODAY()),MONTH(TODAY()),1),"mmm d")&"–"&DAY(TODAY()),IF(AND(J37>=EOMONTH(TODAY(),-2)+1,J37<=EOMONTH(TODAY(),-1)),""&TEXT(EOMONTH(TODAY(),-2)+1,"mmm d")&"–"&DAY(TODAY()),""))
A38: LN-102111 | B38: CUS-202111 | C38: Ricardo | D38: Ramos | E38: Ybanez | F38: 52 | G38: Male | H38: General Santos | I38: Region XII (SOCCSKSARGEN) | J38: 44950 | K38: 44957 | L38: SUV | M38: Honda | N38: CR-V | O38: 2541000 | P38: 514000 | Q38: 2027000 | R38: 12 | S38: 8.05 | T38: 182514.46 | U38: Approved | V38: Defaulted | W38: 547543.38 | X38: 1642630.1 | Y38: 2190173.5 | Z38: 279 | AA38: Over 90 Days | AB38: Pampanga | AC38: I. Cabrera | AD38: Monthly | AE38: 79.77 | AF38: 9 | AG38: High Risk | AH38: 7 | AI38: =IF(F38<25,"18-24",IF(F38<35,"25-34",IF(F38<45,"35-44",IF(F38<55,"45-54",IF(F38<65,"55-64","65+"))))) -> 45-54 | AJ38: =YEAR(tbl_LoanData[[#This Row],[Application Date]]) -> 2023 | AK38: =TEXT(tbl_LoanData[[#This Row],[Application Date]],"MMMM") -> January | AL38: =DATE(YEAR(tbl_LoanData[[#This Row],[Application Date]]),MONTH(tbl_LoanData[[#This Row],[Application Date]]),1) -> 44927 | AM38: =IF(AND(tbl_LoanData[[#This Row],[Application Date]]>=EOMONTH(TODAY(),-1)+1,tbl_LoanData[[#This Row],[Application Date]]<=TODAY()),tbl_LoanData[[#This Row],[Loan Amount]],0) -> 0 | AN38: =tbl_LoanData[[#This Row],[Amount Paid]]-(Q38-X38) -> 163173.5 | AO38: =IF(tbl_LoanData[[#This Row],[Application Status]]="Approved",1,0) -> 1 | AP38: =IF(AND(J38>=DATE(YEAR(TODAY()),MONTH(TODAY()),1),J38<=TODAY()),"Current MTD",IF(AND(J38>=EOMONTH(TODAY(),-2)+1,J38<=EOMONTH(TODAY(),-1)),"Previous MTD","")) | AQ38: =IF(AND(J38>=DATE(YEAR(TODAY()),MONTH(TODAY()),1),J38<=TODAY()),TEXT(DATE(YEAR(TODAY()),MONTH(TODAY()),1),"mmm d")&"–"&DAY(TODAY()),IF(AND(J38>=EOMONTH(TODAY(),-2)+1,J38<=EOMONTH(TODAY(),-1)),""&TEXT(EOMONTH(TODAY(),-2)+1,"mmm d")&"–"&DAY(TODAY()),""))
A39: LN-102129 | B39: CUS-202129 | C39: Michael | D39: Domingo | E39: Salazar | F39: 52 | G39: Male | H39: Tacloban | I39: Region VIII (Eastern Visayas) | J39: 44949 | L39: SUV | M39: Honda | N39: BR-V | O39: 2483000 | P39: 286100 | Q39: 2196900 | R39: 18 | S39: 8.84 | T39: 138233.83 | U39: Rejected | V39: Not Applicable | W39: 0 | X39: 0 | Y39: 2488208.9 | Z39: 0 | AA39: Not Applicable | AB39: Pampanga | AC39: G. Bunag | AD39: Monthly | AE39: 88.48 | AF39: 0 | AG39: Not Applicable | AI39: =IF(F39<25,"18-24",IF(F39<35,"25-34",IF(F39<45,"35-44",IF(F39<55,"45-54",IF(F39<65,"55-64","65+"))))) -> 45-54 | AJ39: =YEAR(tbl_LoanData[[#This Row],[Application Date]]) -> 2023 | AK39: =TEXT(tbl_LoanData[[#This Row],[Application Date]],"MMMM") -> January | AL39: =DATE(YEAR(tbl_LoanData[[#This Row],[Application Date]]),MONTH(tbl_LoanData[[#This Row],[Application Date]]),1) -> 44927 | AM39: =IF(AND(tbl_LoanData[[#This Row],[Application Date]]>=EOMONTH(TODAY(),-1)+1,tbl_LoanData[[#This Row],[Application Date]]<=TODAY()),tbl_LoanData[[#This Row],[Loan Amount]],0) -> 0 | AN39: =tbl_LoanData[[#This Row],[Amount Paid]]-(Q39-X39) -> -2196900 | AO39: =IF(tbl_LoanData[[#This Row],[Application Status]]="Approved",1,0) -> 0 | AP39: =IF(AND(J39>=DATE(YEAR(TODAY()),MONTH(TODAY()),1),J39<=TODAY()),"Current MTD",IF(AND(J39>=EOMONTH(TODAY(),-2)+1,J39<=EOMONTH(TODAY(),-1)),"Previous MTD","")) | AQ39: =IF(AND(J39>=DATE(YEAR(TODAY()),MONTH(TODAY()),1),J39<=TODAY()),TEXT(DATE(YEAR(TODAY()),MONTH(TODAY()),1),"mmm d")&"–"&DAY(TODAY()),IF(AND(J39>=EOMONTH(TODAY(),-2)+1,J39<=EOMONTH(TODAY(),-1)),""&TEXT(EOMONTH(TODAY(),-2)+1,"mmm d")&"–"&DAY(TODAY()),""))
A40: LN-102230 | B40: CUS-202230 | C40: Vicente | D40: Ocampo | E40: Quiambao | F40: 57 | G40: Male | H40: Bacolod | I40: Region VI (Western Visayas) | J40: 44931 | K40: 44943 | L40: SUV | M40: Ford | N40: Everest | O40: 2544000 | P40: 765000 | Q40: 1779000 | R40: 24 | S40: 6.5 | T40: 83761.25 | U40: Approved | V40: Closed - Fully Paid | W40: 2010270 | X40: 0 | Y40: 2010270 | Z40: 0 | AA40: Current | AB40: Manila | AC40: A. Ramirez | AD40: Monthly | AE40: 69.93 | AF40: 0 | AG40: Low Risk | AH40: 12 | AI40: =IF(F40<25,"18-24",IF(F40<35,"25-34",IF(F40<45,"35-44",IF(F40<55,"45-54",IF(F40<65,"55-64","65+"))))) -> 55-64 | AJ40: =YEAR(tbl_LoanData[[#This Row],[Application Date]]) -> 2023 | AK40: =TEXT(tbl_LoanData[[#This Row],[Application Date]],"MMMM") -> January | AL40: =DATE(YEAR(tbl_LoanData[[#This Row],[Application Date]]),MONTH(tbl_LoanData[[#This Row],[Application Date]]),1) -> 44927 | AM40: =IF(AND(tbl_LoanData[[#This Row],[Application Date]]>=EOMONTH(TODAY(),-1)+1,tbl_LoanData[[#This Row],[Application Date]]<=TODAY()),tbl_LoanData[[#This Row],[Loan Amount]],0) -> 0 | AN40: =tbl_LoanData[[#This Row],[Amount Paid]]-(Q40-X40) -> 231270 | AO40: =IF(tbl_LoanData[[#This Row],[Application Status]]="Approved",1,0) -> 1 | AP40: =IF(AND(J40>=DATE(YEAR(TODAY()),MONTH(TODAY()),1),J40<=TODAY()),"Current MTD",IF(AND(J40>=EOMONTH(TODAY(),-2)+1,J40<=EOMONTH(TODAY(),-1)),"Previous MTD","")) | AQ40: =IF(AND(J40>=DATE(YEAR(TODAY()),MONTH(TODAY()),1),J40<=TODAY()),TEXT(DATE(YEAR(TODAY()),MONTH(TODAY()),1),"mmm d")&"–"&DAY(TODAY()),IF(AND(J40>=EOMONTH(TODAY(),-2)+1,J40<=EOMONTH(TODAY(),-1)),""&TEXT(EOMONTH(TODAY(),-2)+1,"mmm d")&"–"&DAY(TODAY()),""))
A41: LN-102308 | B41: CUS-202308 | C41: Grace | D41: Pascual | E41: Del Rosario | F41: 55 | G41: Female | H41: San Fernando (Pampanga) | I41: Region III (Central Luzon) | J41: 44932 | K41: 44945 | L41: Motorcycle | M41: Yamaha | N41: Mio i125 | O41: 185000 | P41: 44000 | Q41: 141000 | R41: 12 | S41: 9.88 | T41: 12910.9 | U41: Approved | V41: Defaulted | W41: 129109 | X41: 25821.8 | Y41: 154930.8 | Z41: 56 | AA41: 31-60 Days | AB41: Cavite | AC41: B. Santiago | AD41: Monthly | AE41: 76.22 | AF41: 2 | AG41: Medium RIsk | AH41: 13 | AI41: =IF(F41<25,"18-24",IF(F41<35,"25-34",IF(F41<45,"35-44",IF(F41<55,"45-54",IF(F41<65,"55-64","65+"))))) -> 55-64 | AJ41: =YEAR(tbl_LoanData[[#This Row],[Application Date]]) -> 2023 | AK41: =TEXT(tbl_LoanData[[#This Row],[Application Date]],"MMMM") -> January | AL41: =DATE(YEAR(tbl_LoanData[[#This Row],[Application Date]]),MONTH(tbl_LoanData[[#This Row],[Application Date]]),1) -> 44927 | AM41: =IF(AND(tbl_LoanData[[#This Row],[Application Date]]>=EOMONTH(TODAY(),-1)+1,tbl_LoanData[[#This Row],[Application Date]]<=TODAY()),tbl_LoanData[[#This Row],[Loan Amount]],0) -> 0 | AN41: =tbl_LoanData[[#This Row],[Amount Paid]]-(Q41-X41) -> 13930.8 | AO41: =IF(tbl_LoanData[[#This Row],[Application Status]]="Approved",1,0) -> 1 | AP41: =IF(AND(J41>=DATE(YEAR(TODAY()),MONTH(TODAY()),1),J41<=TODAY()),"Current MTD",IF(AND(J41>=EOMONTH(TODAY(),-2)+1,J41<=EOMONTH(TODAY(),-1)),"Previous MTD","")) | AQ41: =IF(AND(J41>=DATE(YEAR(TODAY()),MONTH(TODAY()),1),J41<=TODAY()),TEXT(DATE(YEAR(TODAY()),MONTH(TODAY()),1),"mmm d")&"–"&DAY(TODAY()),IF(AND(J41>=EOMONTH(TODAY(),-2)+1,J41<=EOMONTH(TODAY(),-1)),""&TEXT(EOMONTH(TODAY(),-2)+1,"mmm d")&"–"&DAY(TODAY()),""))
A42: LN-102339 | B42: CUS-202339 | C42: Reynaldo | D42: Bautista | E42: Wenceslao | F42: 63 | G42: Male | H42: Batangas City | I42: Region IV-A (CALABARZON) | J42: 44929 | L42: Motorcycle | M42: Suzuki | N42: Raider R150 | O42: 232000 | P42: 67900 | Q42: 164100 | R42: 24 | S42: 12.21 | T42: 8507.22 | U42: Rejected | V42: Not Applicable | W42: 0 | X42: 0 | Y42: 204173.22 | Z42: 0 | AA42: Not Applicable | AB42: Davao | AC42: F. Lacson | AD42: Monthly | AE42: 70.73 | AF42: 0 | AG42: Not Applicable | AI42: =IF(F42<25,"18-24",IF(F42<35,"25-34",IF(F42<45,"35-44",IF(F42<55,"45-54",IF(F42<65,"55-64","65+"))))) -> 55-64 | AJ42: =YEAR(tbl_LoanData[[#This Row],[Application Date]]) -> 2023 | AK42: =TEXT(tbl_LoanData[[#This Row],[Application Date]],"MMMM") -> January | AL42: =DATE(YEAR(tbl_LoanData[[#This Row],[Application Date]]),MONTH(tbl_LoanData[[#This Row],[Application Date]]),1) -> 44927 | AM42: =IF(AND(tbl_LoanData[[#This Row],[Application Date]]>=EOMONTH(TODAY(),-1)+1,tbl_LoanData[[#This Row],[Application Date]]<=TODAY()),tbl_LoanData[[#This Row],[Loan Amount]],0) -> 0 | AN42: =tbl_LoanData[[#This Row],[Amount Paid]]-(Q42-X42) -> -164100 | AO42: =IF(tbl_LoanData[[#This Row],[Application Status]]="Approved",1,0) -> 0 | AP42: =IF(AND(J42>=DATE(YEAR(TODAY()),MONTH(TODAY()),1),J42<=TODAY()),"Current MTD",IF(AND(J42>=EOMONTH(TODAY(),-2)+1,J42<=EOMONTH(TODAY(),-1)),"Previous MTD","")) | AQ42: =IF(AND(J42>=DATE(YEAR(TODAY()),MONTH(TODAY()),1),J42<=TODAY()),TEXT(DATE(YEAR(TODAY()),MONTH(TODAY()),1),"mmm d")&"–"&DAY(TODAY()),IF(AND(J42>=EOMONTH(TODAY(),-2)+1,J42<=EOMONTH(TODAY(),-1)),""&TEXT(EOMONTH(TODAY(),-2)+1,"mmm d")&"–"&DAY(TODAY()),""))
A43: LN-102340 | B43: CUS-202340 | C43: Carlos | D43: Salazar | E43: Ybanez | F43: 52 | G43: Male | H43: Dagupan | I43: Region I (Ilocos Region) | J43: 44935 | L43: MPV/Van | M43: Honda | N43: Mobilio | O43: 1868000 | P43: 411300 | Q43: 1456700 | R43: 36 | S43: 14.86 | T43: 58502.69 | U43: Pending | V43: Not Applicable | W43: 0 | X43: 0 | Y43: 2106096.9 | Z43: 0 | AA43: Not Applicable | AB43: Cebu | AC43: B. Santiago | AD43: Monthly | AE43: 77.98 | AF43: 0 | AG43: Not Applicable | AI43: =IF(F43<25,"18-24",IF(F43<35,"25-34",IF(F43<45,"35-44",IF(F43<55,"45-54",IF(F43<65,"55-64","65+"))))) -> 45-54 | AJ43: =YEAR(tbl_LoanData[[#This Row],[Application Date]]) -> 2023 | AK43: =TEXT(tbl_LoanData[[#This Row],[Application Date]],"MMMM") -> January | AL43: =DATE(YEAR(tbl_LoanData[[#This Row],[Application Date]]),MONTH(tbl_LoanData[[#This Row],[Application Date]]),1) -> 44927 | AM43: =IF(AND(tbl_LoanData[[#This Row],[Application Date]]>=EOMONTH(TODAY(),-1)+1,tbl_LoanData[[#This Row],[Application Date]]<=TODAY()),tbl_LoanData[[#This Row],[Loan Amount]],0) -> 0 | AN43: =tbl_LoanData[[#This Row],[Amount Paid]]-(Q43-X43) -> -1456700 | AO43: =IF(tbl_LoanData[[#This Row],[Application Status]]="Approved",1,0) -> 0 | AP43: =IF(AND(J43>=DATE(YEAR(TODAY()),MONTH(TODAY()),1),J43<=TODAY()),"Current MTD",IF(AND(J43>=EOMONTH(TODAY(),-2)+1,J43<=EOMONTH(TODAY(),-1)),"Previous MTD","")) | AQ43: =IF(AND(J43>=DATE(YEAR(TODAY()),MONTH(TODAY()),1),J43<=TODAY()),TEXT(DATE(YEAR(TODAY()),MONTH(TODAY()),1),"mmm d")&"–"&DAY(TODAY()),IF(AND(J43>=EOMONTH(TODAY(),-2)+1,J43<=EOMONTH(TODAY(),-1)),""&TEXT(EOMONTH(TODAY(),-2)+1,"mmm d")&"–"&DAY(TODAY()),""))
A44: LN-102394 | B44: CUS-202394 | C44: Erlinda | D44: Castillo | E44: Ramos | F44: 53 | G44: Female | H44: Calamba | I44: Region IV-A (CALABARZON) | J44: 44932 | K44: 44942 | L44: Sedan | M44: Mitsubishi | N44: Mirage G4 | O44: 1023000 | P44: 151400 | Q44: 871600 | R44: 24 | S44: 14.55 | T44: 46884.82 | U44: Approved | V44: Closed - Fully Paid | W44: 1125235.6 | X44: 0 | Y44: 1125235.6 | Z44: 0 | AA44: Current | AB44: Baguio | AC44: G. Bunag | AD44: Monthly | AE44: 85.2 | AF44: 0 | AG44: Low Risk | AH44: 10 | AI44: =IF(F44<25,"18-24",IF(F44<35,"25-34",IF(F44<45,"35-44",IF(F44<55,"45-54",IF(F44<65,"55-64","65+"))))) -> 45-54 | AJ44: =YEAR(tbl_LoanData[[#This Row],[Application Date]]) -> 2023 | AK44: =TEXT(tbl_LoanData[[#This Row],[Application Date]],"MMMM") -> January | AL44: =DATE(YEAR(tbl_LoanData[[#This Row],[Application Date]]),MONTH(tbl_LoanData[[#This Row],[Application Date]]),1) -> 44927 | AM44: =IF(AND(tbl_LoanData[[#This Row],[Application Date]]>=EOMONTH(TODAY(),-1)+1,tbl_LoanData[[#This Row],[Application Date]]<=TODAY()),tbl_LoanData[[#This Row],[Loan Amount]],0) -> 0 | AN44: =tbl_LoanData[[#This Row],[Amount Paid]]-(Q44-X44) -> 253635.6 | AO44: =IF(tbl_LoanData[[#This Row],[Application Status]]="Approved",1,0) -> 1 | AP44: =IF(AND(J44>=DATE(YEAR(TODAY()),MONTH(TODAY()),1),J44<=TODAY()),"Current MTD",IF(AND(J44>=EOMONTH(TODAY(),-2)+1,J44<=EOMONTH(TODAY(),-1)),"Previous MTD","")) | AQ44: =IF(AND(J44>=DATE(YEAR(TODAY()),MONTH(TODAY()),1),J44<=TODAY()),TEXT(DATE(YEAR(TODAY()),MONTH(TODAY()),1),"mmm d")&"–"&DAY(TODAY()),IF(AND(J44>=EOMONTH(TODAY(),-2)+1,J44<=EOMONTH(TODAY(),-1)),""&TEXT(EOMONTH(TODAY(),-2)+1,"mmm d")&"–"&DAY(TODAY()),""))
A45: LN-102548 | B45: CUS-202548 | C45: Carlos | D45: Garcia | E45: Mendoza | F45: 32 | G45: Male | H45: Olongapo | I45: Region III (Central Luzon) | J45: 44956 | L45: SUV | M45: Hyundai | N45: Creta | O45: 2272000 | P45: 592000 | Q45: 1680000 | R45: 24 | S45: 9.23 | T45: 82922 | U45: Rejected | V45: Not Applicable | W45: 0 | X45: 0 | Y45: 1990128 | Z45: 0 | AA45: Not Applicable | AB45: Pampanga | AC45: H. Isip | AD45: Monthly | AE45: 73.94 | AF45: 0 | AG45: Not Applicable | AI45: =IF(F45<25,"18-24",IF(F45<35,"25-34",IF(F45<45,"35-44",IF(F45<55,"45-54",IF(F45<65,"55-64","65+"))))) -> 25-34 | AJ45: =YEAR(tbl_LoanData[[#This Row],[Application Date]]) -> 2023 | AK45: =TEXT(tbl_LoanData[[#This Row],[Application Date]],"MMMM") -> January | AL45: =DATE(YEAR(tbl_LoanData[[#This Row],[Application Date]]),MONTH(tbl_LoanData[[#This Row],[Application Date]]),1) -> 44927 | AM45: =IF(AND(tbl_LoanData[[#This Row],[Application Date]]>=EOMONTH(TODAY(),-1)+1,tbl_LoanData[[#This Row],[Application Date]]<=TODAY()),tbl_LoanData[[#This Row],[Loan Amount]],0) -> 0 | AN45: =tbl_LoanData[[#This Row],[Amount Paid]]-(Q45-X45) -> -1680000 | AO45: =IF(tbl_LoanData[[#This Row],[Application Status]]="Approved",1,0) -> 0 | AP45: =IF(AND(J45>=DATE(YEAR(TODAY()),MONTH(TODAY()),1),J45<=TODAY()),"Current MTD",IF(AND(J45>=EOMONTH(TODAY(),-2)+1,J45<=EOMONTH(TODAY(),-1)),"Previous MTD","")) | AQ45: =IF(AND(J45>=DATE(YEAR(TODAY()),MONTH(TODAY()),1),J45<=TODAY()),TEXT(DATE(YEAR(TODAY()),MONTH(TODAY()),1),"mmm d")&"–"&DAY(TODAY()),IF(AND(J45>=EOMONTH(TODAY(),-2)+1,J45<=EOMONTH(TODAY(),-1)),""&TEXT(EOMONTH(TODAY(),-2)+1,"mmm d")&"–"&DAY(TODAY()),""))
A46: LN-102600 | B46: CUS-202600 | C46: Manuel | D46: Ramos | E46: Ignacio | F46: 29 | G46: Male | H46: Antipolo | I46: Region IV-A (CALABARZON) | J46: 44940 | K46: 44954 | L46: Sedan | M46: Nissan | N46: Sylphy | O46: 805000 | P46: 239400 | Q46: 565600 | R46: 24 | S46: 11.05 | T46: 28774.9 | U46: Approved | V46: Closed - Fully Paid | W46: 690597.6 | X46: 0 | Y46: 690597.6 | Z46: 0 | AA46: Current | AB46: Pampanga | AC46: F. Lacson | AD46: Monthly | AE46: 70.26 | AF46: 0 | AG46: Low Risk | AH46: 14 | AI46: =IF(F46<25,"18-24",IF(F46<35,"25-34",IF(F46<45,"35-44",IF(F46<55,"45-54",IF(F46<65,"55-64","65+"))))) -> 25-34 | AJ46: =YEAR(tbl_LoanData[[#This Row],[Application Date]]) -> 2023 | AK46: =TEXT(tbl_LoanData[[#This Row],[Application Date]],"MMMM") -> January | AL46: =DATE(YEAR(tbl_LoanData[[#This Row],[Application Date]]),MONTH(tbl_LoanData[[#This Row],[Application Date]]),1) -> 44927 | AM46: =IF(AND(tbl_LoanData[[#This Row],[Application Date]]>=EOMONTH(TODAY(),-1)+1,tbl_LoanData[[#This Row],[Application Date]]<=TODAY()),tbl_LoanData[[#This Row],[Loan Amount]],0) -> 0 | AN46: =tbl_LoanData[[#This Row],[Amount Paid]]-(Q46-X46) -> 124997.6 | AO46: =IF(tbl_LoanData[[#This Row],[Application Status]]="Approved",1,0) -> 1 | AP46: =IF(AND(J46>=DATE(YEAR(TODAY()),MONTH(TODAY()),1),J46<=TODAY()),"Current MTD",IF(AND(J46>=EOMONTH(TODAY(),-2)+1,J46<=EOMONTH(TODAY(),-1)),"Previous MTD","")) | AQ46: =IF(AND(J46>=DATE(YEAR(TODAY()),MONTH(TODAY()),1),J46<=TODAY()),TEXT(DATE(YEAR(TODAY()),MONTH(TODAY()),1),"mmm d")&"–"&DAY(TODAY()),IF(AND(J46>=EOMONTH(TODAY(),-2)+1,J46<=EOMONTH(TODAY(),-1)),""&TEXT(EOMONTH(TODAY(),-2)+1,"mmm d")&"–"&DAY(TODAY()),""))
A47: LN-102617 | B47: CUS-202617 | C47: Faith | D47: Rivera | E47: Ybanez | F47: 51 | G47: Female | H47: Pasig | I47: NCR | J47: 44934 | K47: 44945 | L47: SUV | M47: Kia | N47: Seltos | O47: 2277000 | P47: 656300 | Q47: 1620700 | R47: 24 | S47: 7.25 | T47: 77320.9 | U47: Approved | V47: Closed - Fully Paid | W47: 1855701.5 | X47: 0 | Y47: 1855701.5 | Z47: 0 | AA47: Current | AB47: Makati | AC47: A. Ramirez | AD47: Monthly | AE47: 71.18 | AF47: 0 | AG47: Low Risk | AH47: 11 | AI47: =IF(F47<25,"18-24",IF(F47<35,"25-34",IF(F47<45,"35-44",IF(F47<55,"45-54",IF(F47<65,"55-64","65+"))))) -> 45-54 | AJ47: =YEAR(tbl_LoanData[[#This Row],[Application Date]]) -> 2023 | AK47: =TEXT(tbl_LoanData[[#This Row],[Application Date]],"MMMM") -> January | AL47: =DATE(YEAR(tbl_LoanData[[#This Row],[Application Date]]),MONTH(tbl_LoanData[[#This Row],[Application Date]]),1) -> 44927 | AM47: =IF(AND(tbl_LoanData[[#This Row],[Application Date]]>=EOMONTH(TODAY(),-1)+1,tbl_LoanData[[#This Row],[Application Date]]<=TODAY()),tbl_LoanData[[#This Row],[Loan Amount]],0) -> 0 | AN47: =tbl_LoanData[[#This Row],[Amount Paid]]-(Q47-X47) -> 235001.5 | AO47: =IF(tbl_LoanData[[#This Row],[Application Status]]="Approved",1,0) -> 1 | AP47: =IF(AND(J47>=DATE(YEAR(TODAY()),MONTH(TODAY()),1),J47<=TODAY()),"Current MTD",IF(AND(J47>=EOMONTH(TODAY(),-2)+1,J47<=EOMONTH(TODAY(),-1)),"Previous MTD","")) | AQ47: =IF(AND(J47>=DATE(YEAR(TODAY()),MONTH(TODAY()),1),J47<=TODAY()),TEXT(DATE(YEAR(TODAY()),MONTH(TODAY()),1),"mmm d")&"–"&DAY(TODAY()),IF(AND(J47>=EOMONTH(TODAY(),-2)+1,J47<=EOMONTH(TODAY(),-1)),""&TEXT(EOMONTH(TODAY(),-2)+1,"mmm d")&"–"&DAY(TODAY()),""))
A48: LN-102649 | B48: CUS-202649 | C48: Dianne | D48: Rivera | E48: Ramos | F48: 27 | G48: Female | H48: Cagayan de Oro | I48: Region X (Northern Mindanao) | J48: 44934 | K48: 44955 | L48: MPV/Van | M48: Toyota | N48: Avanza | O48: 882000 | P48: 161500 | Q48: 720500 | R48: 36 | S48: 11.47 | T48: 26900.67 | U48: Approved | V48: Closed - Fully Paid | W48: 968424.05 | X48: 0 | Y48: 968424.05 | Z48: 0 | AA48: Current | AB48: Pampanga | AC48: D. Morales | AD48: Monthly | AE48: 81.69 | AF48: 0 | AG48: Low Risk | AH48: 21 | AI48: =IF(F48<25,"18-24",IF(F48<35,"25-34",IF(F48<45,"35-44",IF(F48<55,"45-54",IF(F48<65,"55-64","65+"))))) -> 25-34 | AJ48: =YEAR(tbl_LoanData[[#This Row],[Application Date]]) -> 2023 | AK48: =TEXT(tbl_LoanData[[#This Row],[Application Date]],"MMMM") -> January | AL48: =DATE(YEAR(tbl_LoanData[[#This Row],[Application Date]]),MONTH(tbl_LoanData[[#This Row],[Application Date]]),1) -> 44927 | AM48: =IF(AND(tbl_LoanData[[#This Row],[Application Date]]>=EOMONTH(TODAY(),-1)+1,tbl_LoanData[[#This Row],[Application Date]]<=TODAY()),tbl_LoanData[[#This Row],[Loan Amount]],0) -> 0 | AN48: =tbl_LoanData[[#This Row],[Amount Paid]]-(Q48-X48) -> 247924.05 | AO48: =IF(tbl_LoanData[[#This Row],[Application Status]]="Approved",1,0) -> 1 | AP48: =IF(AND(J48>=DATE(YEAR(TODAY()),MONTH(TODAY()),1),J48<=TODAY()),"Current MTD",IF(AND(J48>=EOMONTH(TODAY(),-2)+1,J48<=EOMONTH(TODAY(),-1)),"Previous MTD","")) | AQ48: =IF(AND(J48>=DATE(YEAR(TODAY()),MONTH(TODAY()),1),J48<=TODAY()),TEXT(DATE(YEAR(TODAY()),MONTH(TODAY()),1),"mmm d")&"–"&DAY(TODAY()),IF(AND(J48>=EOMONTH(TODAY(),-2)+1,J48<=EOMONTH(TODAY(),-1)),""&TEXT(EOMONTH(TODAY(),-2)+1,"mmm d")&"–"&DAY(TODAY()),""))
A49: LN-102676 | B49: CUS-202676 | C49: Teodoro | D49: Mendoza | E49: Ramos | F49: 38 | G49: Male | H49: Makati | I49: NCR | J49: 44956 | K49: 44976 | L49: SUV | M49: Toyota | N49: Rush | O49: 2214000 | P49: 273300 | Q49: 1940700 | R49: 60 | S49: 8.09 | T49: 45428.55 | U49: Approved | V49: Active | W49: 1907999.1 | X49: 817714.05 | Y49: 2725713.1 | Z49: 0 | AA49: Current | AB49: Pampanga | AC49: F. Lacson | AD49: Monthly | AE49: 87.66 | AF49: 0 | AG49: Low Risk | AH49: 20 | AI49: =IF(F49<25,"18-24",IF(F49<35,"25-34",IF(F49<45,"35-44",IF(F49<55,"45-54",IF(F49<65,"55-64","65+"))))) -> 35-44 | AJ49: =YEAR(tbl_LoanData[[#This Row],[Application Date]]) -> 2023 | AK49: =TEXT(tbl_LoanData[[#This Row],[Application Date]],"MMMM") -> January | AL49: =DATE(YEAR(tbl_LoanData[[#This Row],[Application Date]]),MONTH(tbl_LoanData[[#This Row],[Application Date]]),1) -> 44927 | AM49: =IF(AND(tbl_LoanData[[#This Row],[Application Date]]>=EOMONTH(TODAY(),-1)+1,tbl_LoanData[[#This Row],[Application Date]]<=TODAY()),tbl_LoanData[[#This Row],[Loan Amount]],0) -> 0 | AN49: =tbl_LoanData[[#This Row],[Amount Paid]]-(Q49-X49) -> 785013.15 | AO49: =IF(tbl_LoanData[[#This Row],[Application Status]]="Approved",1,0) -> 1 | AP49: =IF(AND(J49>=DATE(YEAR(TODAY()),MONTH(TODAY()),1),J49<=TODAY()),"Current MTD",IF(AND(J49>=EOMONTH(TODAY(),-2)+1,J49<=EOMONTH(TODAY(),-1)),"Previous MTD","")) | AQ49: =IF(AND(J49>=DATE(YEAR(TODAY()),MONTH(TODAY()),1),J49<=TODAY()),TEXT(DATE(YEAR(TODAY()),MONTH(TODAY()),1),"mmm d")&"–"&DAY(TODAY()),IF(AND(J49>=EOMONTH(TODAY(),-2)+1,J49<=EOMONTH(TODAY(),-1)),""&TEXT(EOMONTH(TODAY(),-2)+1,"mmm d")&"–"&DAY(TODAY()),""))
A50: LN-102747 | B50: CUS-202747 | C50: Julio | D50: Del Rosario | E50: Cortez | F50: 51 | G50: Male | H50: Las Pinas | I50: NCR | J50: 44952 | K50: 44967 | L50: Motorcycle | M50: Kawasaki | N50: Barako | O50: 206000 | P50: 37000 | Q50: 169000 | R50: 48 | S50: 10.31 | T50: 4972.82 | U50: Approved | V50: Active | W50: 208858.44 | X50: 29837.16 | Y50: 238695.6 | Z50: 0 | AA50: Current | AB50: Cavite | AC50: I. Cabrera | AD50: Monthly | AE50: 82.04 | AF50: 0 | AG50: Low Risk | AH50: 15 | AI50: =IF(F50<25,"18-24",IF(F50<35,"25-34",IF(F50<45,"35-44",IF(F50<55,"45-54",IF(F50<65,"55-64","65+"))))) -> 45-54 | AJ50: =YEAR(tbl_LoanData[[#This Row],[Application Date]]) -> 2023 | AK50: =TEXT(tbl_LoanData[[#This Row],[Application Date]],"MMMM") -> January | AL50: =DATE(YEAR(tbl_LoanData[[#This Row],[Application Date]]),MONTH(tbl_LoanData[[#This Row],[Application Date]]),1) -> 44927 | AM50: =IF(AND(tbl_LoanData[[#This Row],[Application Date]]>=EOMONTH(TODAY(),-1)+1,tbl_LoanData[[#This Row],[Application Date]]<=TODAY()),tbl_LoanData[[#This Row],[Loan Amount]],0) -> 0 | AN50: =tbl_LoanData[[#This Row],[Amount Paid]]-(Q50-X50) -> 69695.6 | AO50: =IF(tbl_LoanData[[#This Row],[Application Status]]="Approved",1,0) -> 1 | AP50: =IF(AND(J50>=DATE(YEAR(TODAY()),MONTH(TODAY()),1),J50<=TODAY()),"Current MTD",IF(AND(J50>=EOMONTH(TODAY(),-2)+1,J50<=EOMONTH(TODAY(),-1)),"Previous MTD","")) | AQ50: =IF(AND(J50>=DATE(YEAR(TODAY()),MONTH(TODAY()),1),J50<=TODAY()),TEXT(DATE(YEAR(TODAY()),MONTH(TODAY()),1),"mmm d")&"–"&DAY(TODAY()),IF(AND(J50>=EOMONTH(TODAY(),-2)+1,J50<=EOMONTH(TODAY(),-1)),""&TEXT(EOMONTH(TODAY(),-2)+1,"mmm d")&"–"&DAY(TODAY()),""))
A51: LN-102838 | B51: CUS-202838 | C51: Salvador | D51: Torres | E51: Lazaro | F51: 42 | G51: Male | H51: Tarlac City | I51: Region III (Central Luzon) | J51: 44933 | K51: 44944 | L51: MPV/Van | M51: Toyota | N51: Hiace | O51: 2112000 | P51: 261500 | Q51: 1850500 | R51: 48 | S51: 13.52 | T51: 59401.05 | U51: Approved | V51: Active | W51: 2316641 | X51: 534609.45 | Y51: 2851250.4 | Z51: 124 | AA51: Over 90 Days | AB51: Makati | AC51: A. Ramirez | AD51: Monthly | AE51: 87.62 | AF51: 4 | AG51: High Risk | AH51: 11 | AI51: =IF(F51<25,"18-24",IF(F51<35,"25-34",IF(F51<45,"35-44",IF(F51<55,"45-54",IF(F51<65,"55-64","65+"))))) -> 35-44 | AJ51: =YEAR(tbl_LoanData[[#This Row],[Application Date]]) -> 2023 | AK51: =TEXT(tbl_LoanData[[#This Row],[Application Date]],"MMMM") -> January | AL51: =DATE(YEAR(tbl_LoanData[[#This Row],[Application Date]]),MONTH(tbl_LoanData[[#This Row],[Application Date]]),1) -> 44927 | AM51: =IF(AND(tbl_LoanData[[#This Row],[Application Date]]>=EOMONTH(TODAY(),-1)+1,tbl_LoanData[[#This Row],[Application Date]]<=TODAY()),tbl_LoanData[[#This Row],[Loan Amount]],0) -> 0 | AN51: =tbl_LoanData[[#This Row],[Amount Paid]]-(Q51-X51) -> 1000750.4 | AO51: =IF(tbl_LoanData[[#This Row],[Application Status]]="Approved",1,0) -> 1 | AP51: =IF(AND(J51>=DATE(YEAR(TODAY()),MONTH(TODAY()),1),J51<=TODAY()),"Current MTD",IF(AND(J51>=EOMONTH(TODAY(),-2)+1,J51<=EOMONTH(TODAY(),-1)),"Previous MTD","")) | AQ51: =IF(AND(J51>=DATE(YEAR(TODAY()),MONTH(TODAY()),1),J51<=TODAY()),TEXT(DATE(YEAR(TODAY()),MONTH(TODAY()),1),"mmm d")&"–"&DAY(TODAY()),IF(AND(J51>=EOMONTH(TODAY(),-2)+1,J51<=EOMONTH(TODAY(),-1)),""&TEXT(EOMONTH(TODAY(),-2)+1,"mmm d")&"–"&DAY(TODAY()),""))
A52: LN-102890 | B52: CUS-202890 | C52: Joseph | D52: Reyes | E52: Aguilar | F52: 30 | G52: Male | H52: Angeles City | I52: Region III (Central Luzon) | J52: 44950 | K52: 44971 | L52: Truck | M52: Hino | N52: 300 Series | O52: 3819000 | P52: 928100 | Q52: 2890900 | R52: 48 | S52: 7.91 | T52: 79282.93 | U52: Approved | V52: Active | W52: 2854185.5 | X52: 951395.28 | Y52: 3805580.8 | Z52: 174 | AA52: Over 90 Days | AB52: Manila | AC52: H. Isip | AD52: Monthly | AE52: 75.7 | AF52: 6 | AG52: High Risk | AH52: 21 | AI52: =IF(F52<25,"18-24",IF(F52<35,"25-34",IF(F52<45,"35-44",IF(F52<55,"45-54",IF(F52<65,"55-64","65+"))))) -> 25-34 | AJ52: =YEAR(tbl_LoanData[[#This Row],[Application Date]]) -> 2023 | AK52: =TEXT(tbl_LoanData[[#This Row],[Application Date]],"MMMM") -> January | AL52: =DATE(YEAR(tbl_LoanData[[#This Row],[Application Date]]),MONTH(tbl_LoanData[[#This Row],[Application Date]]),1) -> 44927 | AM52: =IF(AND(tbl_LoanData[[#This Row],[Application Date]]>=EOMONTH(TODAY(),-1)+1,tbl_LoanData[[#This Row],[Application Date]]<=TODAY()),tbl_LoanData[[#This Row],[Loan Amount]],0) -> 0 | AN52: =tbl_LoanData[[#This Row],[Amount Paid]]-(Q52-X52) -> 914680.76 | AO52: =IF(tbl_LoanData[[#This Row],[Application Status]]="Approved",1,0) -> 1 | AP52: =IF(AND(J52>=DATE(YEAR(TODAY()),MONTH(TODAY()),1),J52<=TODAY()),"Current MTD",IF(AND(J52>=EOMONTH(TODAY(),-2)+1,J52<=EOMONTH(TODAY(),-1)),"Previous MTD","")) | AQ52: =IF(AND(J52>=DATE(YEAR(TODAY()),MONTH(TODAY()),1),J52<=TODAY()),TEXT(DATE(YEAR(TODAY()),MONTH(TODAY()),1),"mmm d")&"–"&DAY(TODAY()),IF(AND(J52>=EOMONTH(TODAY(),-2)+1,J52<=EOMONTH(TODAY(),-1)),""&TEXT(EOMONTH(TODAY(),-2)+1,"mmm d")&"–"&DAY(TODAY()),""))
A53: LN-102896 | B53: CUS-202896 | C53: Andrea | D53: Fernandez | E53: Santos | F53: 37 | G53: Female | H53: Vigan | I53: Region I (Ilocos Region) | J53: 44931 | K53: 44939 | L53: SUV | M53: Kia | N53: Seltos | O53: 2298000 | P53: 341700 | Q53: 1956300 | R53: 12 | S53: 7.44 | T53: 175154.06 | U53: Approved | V53: Closed - Fully Paid | W53: 2101848.7 | X53: 0 | Y53: 2101848.7 | Z53: 0 | AA53: Current | AB53: Manila | AC53: A. Ramirez | AD53: Monthly | AE53: 85.13 | AF53: 0 | AG53: Low Risk | AH53: 8 | AI53: =IF(F53<25,"18-24",IF(F53<35,"25-34",IF(F53<45,"35-44",IF(F53<55,"45-54",IF(F53<65,"55-64","65+"))))) -> 35-44 | AJ53: =YEAR(tbl_LoanData[[#This Row],[Application Date]]) -> 2023 | AK53: =TEXT(tbl_LoanData[[#This Row],[Application Date]],"MMMM") -> January | AL53: =DATE(YEAR(tbl_LoanData[[#This Row],[Application Date]]),MONTH(tbl_LoanData[[#This Row],[Application Date]]),1) -> 44927 | AM53: =IF(AND(tbl_LoanData[[#This Row],[Application Date]]>=EOMONTH(TODAY(),-1)+1,tbl_LoanData[[#This Row],[Application Date]]<=TODAY()),tbl_LoanData[[#This Row],[Loan Amount]],0) -> 0 | AN53: =tbl_LoanData[[#This Row],[Amount Paid]]-(Q53-X53) -> 145548.72 | AO53: =IF(tbl_LoanData[[#This Row],[Application Status]]="Approved",1,0) -> 1 | AP53: =IF(AND(J53>=DATE(YEAR(TODAY()),MONTH(TODAY()),1),J53<=TODAY()),"Current MTD",IF(AND(J53>=EOMONTH(TODAY(),-2)+1,J53<=EOMONTH(TODAY(),-1)),"Previous MTD","")) | AQ53: =IF(AND(J53>=DATE(YEAR(TODAY()),MONTH(TODAY()),1),J53<=TODAY()),TEXT(DATE(YEAR(TODAY()),MONTH(TODAY()),1),"mmm d")&"–"&DAY(TODAY()),IF(AND(J53>=EOMONTH(TODAY(),-2)+1,J53<=EOMONTH(TODAY(),-1)),""&TEXT(EOMONTH(TODAY(),-2)+1,"mmm d")&"–"&DAY(TODAY()),""))
A54: LN-102973 | B54: CUS-202973 | C54: Marites | D54: Torres | E54: Manalo | F54: 41 | G54: Female | H54: Mandaue | I54: Region VII (Central Visayas) | J54: 44948 | K54: 44953 | L54: Motorcycle | M54: Honda | N54: ADV 160 | O54: 150000 | P54: 17300 | Q54: 132700 | R54: 24 | S54: 14.53 | T54: 7135.94 | U54: Approved | V54: Defaulted | W54: 164126.62 | X54: 7136 | Y54: 171262.62 | Z54: 29 | AA54: 1-30 Days | AB54: Manila | AC54: A. Ramirez | AD54: Monthly | AE54: 88.47 | AF54: 1 | AG54: Low Risk | AH54: 5 | AI54: =IF(F54<25,"18-24",IF(F54<35,"25-34",IF(F54<45,"35-44",IF(F54<55,"45-54",IF(F54<65,"55-64","65+"))))) -> 35-44 | AJ54: =YEAR(tbl_LoanData[[#This Row],[Application Date]]) -> 2023 | AK54: =TEXT(tbl_LoanData[[#This Row],[Application Date]],"MMMM") -> January | AL54: =DATE(YEAR(tbl_LoanData[[#This Row],[Application Date]]),MONTH(tbl_LoanData[[#This Row],[Application Date]]),1) -> 44927 | AM54: =IF(AND(tbl_LoanData[[#This Row],[Application Date]]>=EOMONTH(TODAY(),-1)+1,tbl_LoanData[[#This Row],[Application Date]]<=TODAY()),tbl_LoanData[[#This Row],[Loan Amount]],0) -> 0 | AN54: =tbl_LoanData[[#This Row],[Amount Paid]]-(Q54-X54) -> 38562.62 | AO54: =IF(tbl_LoanData[[#This Row],[Application Status]]="Approved",1,0) -> 1 | AP54: =IF(AND(J54>=DATE(YEAR(TODAY()),MONTH(TODAY()),1),J54<=TODAY()),"Current MTD",IF(AND(J54>=EOMONTH(TODAY(),-2)+1,J54<=EOMONTH(TODAY(),-1)),"Previous MTD","")) | AQ54: =IF(AND(J54>=DATE(YEAR(TODAY()),MONTH(TODAY()),1),J54<=TODAY()),TEXT(DATE(YEAR(TODAY()),MONTH(TODAY()),1),"mmm d")&"–"&DAY(TODAY()),IF(AND(J54>=EOMONTH(TODAY(),-2)+1,J54<=EOMONTH(TODAY(),-1)),""&TEXT(EOMONTH(TODAY(),-2)+1,"mmm d")&"–"&DAY(TODAY()),""))
A55: LN-103008 | B55: CUS-203008 | C55: Efren | D55: Castillo | E55: Marquez | F55: 50 | G55: Male | H55: San Pablo | I55: Region IV-A (CALABARZON) | J55: 44927 | K55: 44944 | L55: Motorcycle | M55: Honda | N55: Beat | O55: 166000 | P55: 47900 | Q55: 118100 | R55: 24 | S55: 9.55 | T55: 5860.71 | U55: Approved | V55: Closed - Fully Paid | W55: 140657.1 | X55: 0 | Y55: 140657.1 | Z55: 0 | AA55: Current | AB55: Quezon City | AC55: G. Bunag | AD55: Monthly | AE55: 71.14 | AF55: 0 | AG55: Low Risk | AH55: 17 | AI55: =IF(F55<25,"18-24",IF(F55<35,"25-34",IF(F55<45,"35-44",IF(F55<55,"45-54",IF(F55<65,"55-64","65+"))))) -> 45-54 | AJ55: =YEAR(tbl_LoanData[[#This Row],[Application Date]]) -> 2023 | AK55: =TEXT(tbl_LoanData[[#This Row],[Application Date]],"MMMM") -> January | AL55: =DATE(YEAR(tbl_LoanData[[#This Row],[Application Date]]),MONTH(tbl_LoanData[[#This Row],[Application Date]]),1) -> 44927 | AM55: =IF(AND(tbl_LoanData[[#This Row],[Application Date]]>=EOMONTH(TODAY(),-1)+1,tbl_LoanData[[#This Row],[Application Date]]<=TODAY()),tbl_LoanData[[#This Row],[Loan Amount]],0) -> 0 | AN55: =tbl_LoanData[[#This Row],[Amount Paid]]-(Q55-X55) -> 22557.1 | AO55: =IF(tbl_LoanData[[#This Row],[Application Status]]="Approved",1,0) -> 1 | AP55: =IF(AND(J55>=DATE(YEAR(TODAY()),MONTH(TODAY()),1),J55<=TODAY()),"Current MTD",IF(AND(J55>=EOMONTH(TODAY(),-2)+1,J55<=EOMONTH(TODAY(),-1)),"Previous MTD","")) | AQ55: =IF(AND(J55>=DATE(YEAR(TODAY()),MONTH(TODAY()),1),J55<=TODAY()),TEXT(DATE(YEAR(TODAY()),MONTH(TODAY()),1),"mmm d")&"–"&DAY(TODAY()),IF(AND(J55>=EOMONTH(TODAY(),-2)+1,J55<=EOMONTH(TODAY(),-1)),""&TEXT(EOMONTH(TODAY(),-2)+1,"mmm d")&"–"&DAY(TODAY()),""))
A56: LN-103016 | B56: CUS-203016 | C56: Dianne | D56: Aquino | E56: Rosario | F56: 41 | G56: Female | H56: Vigan | I56: Region I (Ilocos Region) | J56: 44949 | K56: 44959 | L56: Sedan | M56: Hyundai | N56: Elantra | O56: 1491000 | P56: 183900 | Q56: 1307100 | R56: 24 | S56: 12.7 | T56: 68295.97 | U56: Approved | V56: Closed - Fully Paid | W56: 1639103.4 | X56: 0 | Y56: 1639103.4 | Z56: 0 | AA56: Current | AB56: CDO | AC56: H. Isip | AD56: Monthly | AE56: 87.67 | AF56: 0 | AG56: Low Risk | AH56: 10 | AI56: =IF(F56<25,"18-24",IF(F56<35,"25-34",IF(F56<45,"35-44",IF(F56<55,"45-54",IF(F56<65,"55-64","65+"))))) -> 35-44 | AJ56: =YEAR(tbl_LoanData[[#This Row],[Application Date]]) -> 2023 | AK56: =TEXT(tbl_LoanData[[#This Row],[Application Date]],"MMMM") -> January | AL56: =DATE(YEAR(tbl_LoanData[[#This Row],[Application Date]]),MONTH(tbl_LoanData[[#This Row],[Application Date]]),1) -> 44927 | AM56: =IF(AND(tbl_LoanData[[#This Row],[Application Date]]>=EOMONTH(TODAY(),-1)+1,tbl_LoanData[[#This Row],[Application Date]]<=TODAY()),tbl_LoanData[[#This Row],[Loan Amount]],0) -> 0 | AN56: =tbl_LoanData[[#This Row],[Amount Paid]]-(Q56-X56) -> 332003.4 | AO56: =IF(tbl_LoanData[[#This Row],[Application Status]]="Approved",1,0) -> 1 | AP56: =IF(AND(J56>=DATE(YEAR(TODAY()),MONTH(TODAY()),1),J56<=TODAY()),"Current MTD",IF(AND(J56>=EOMONTH(TODAY(),-2)+1,J56<=EOMONTH(TODAY(),-1)),"Previous MTD","")) | AQ56: =IF(AND(J56>=DATE(YEAR(TODAY()),MONTH(TODAY()),1),J56<=TODAY()),TEXT(DATE(YEAR(TODAY()),MONTH(TODAY()),1),"mmm d")&"–"&DAY(TODAY()),IF(AND(J56>=EOMONTH(TODAY(),-2)+1,J56<=EOMONTH(TODAY(),-1)),""&TEXT(EOMONTH(TODAY(),-2)+1,"mmm d")&"–"&DAY(TODAY()),""))
A57: LN-103019 | B57: CUS-203019 | C57: Jose | D57: Mendoza | E57: Torres | F57: 62 | G57: Male | H57: Cebu City | I57: Region VII (Central Visayas) | J57: 44944 | K57: 44963 | L57: Motorcycle | M57: Yamaha | N57: Mio i125 | O57: 116000 | P57: 35400 | Q57: 80600 | R57: 36 | S57: 10.69 | T57: 2956.9 | U57: Approved | V57: Closed - Fully Paid | W57: 106448.42 | X57: 0 | Y57: 106448.42 | Z57: 0 | AA57: Current | AB57: Manila | AC57: G. Bunag | AD57: Monthly | AE57: 69.48 | AF57: 0 | AG57: Low Risk | AH57: 19 | AI57: =IF(F57<25,"18-24",IF(F57<35,"25-34",IF(F57<45,"35-44",IF(F57<55,"45-54",IF(F57<65,"55-64","65+"))))) -> 55-64 | AJ57: =YEAR(tbl_LoanData[[#This Row],[Application Date]]) -> 2023 | AK57: =TEXT(tbl_LoanData[[#This Row],[Application Date]],"MMMM") -> January | AL57: =DATE(YEAR(tbl_LoanData[[#This Row],[Application Date]]),MONTH(tbl_LoanData[[#This Row],[Application Date]]),1) -> 44927 | AM57: =IF(AND(tbl_LoanData[[#This Row],[Application Date]]>=EOMONTH(TODAY(),-1)+1,tbl_LoanData[[#This Row],[Application Date]]<=TODAY()),tbl_LoanData[[#This Row],[Loan Amount]],0) -> 0 | AN57: =tbl_LoanData[[#This Row],[Amount Paid]]-(Q57-X57) -> 25848.42 | AO57: =IF(tbl_LoanData[[#This Row],[Application Status]]="Approved",1,0) -> 1 | AP57: =IF(AND(J57>=DATE(YEAR(TODAY()),MONTH(TODAY()),1),J57<=TODAY()),"Current MTD",IF(AND(J57>=EOMONTH(TODAY(),-2)+1,J57<=EOMONTH(TODAY(),-1)),"Previous MTD","")) | AQ57: =IF(AND(J57>=DATE(YEAR(TODAY()),MONTH(TODAY()),1),J57<=TODAY()),TEXT(DATE(YEAR(TODAY()),MONTH(TODAY()),1),"mmm d")&"–"&DAY(TODAY()),IF(AND(J57>=EOMONTH(TODAY(),-2)+1,J57<=EOMONTH(TODAY(),-1)),""&TEXT(EOMONTH(TODAY(),-2)+1,"mmm d")&"–"&DAY(TODAY()),""))
... A60: LN-103163 | B60: CUS-203163 | C60: Angela | D60: Aquino | E60: Tolentino | F60: 31 | G60: Female | H60: Zamboanga City | I60: Region IX (Zamboanga Peninsula) | J60: 44940 | K60: 44944 | L60: Sedan | M60: Hyundai | N60: Elantra | O60: 1139000 | P60: 410900 | Q60: 728100 | R60: 24 | S60: 10.69 | T60: 36823.66 | U60: Approved | V60: Closed - Fully Paid | W60: 883767.78 | X60: 0 | Y60: 883767.78 | Z60: 0 | AA60: Current | AB60: Davao | AC60: E. Ferrer | AD60: Monthly | AE60: 63.92 | AF60: 0 | AG60: Low Risk | AH60: 4 | AI60: =IF(F60<25,"18-24",IF(F60<35,"25-34",IF(F60<45,"35-44",IF(F60<55,"45-54",IF(F60<65,"55-64","65+"))))) -> 25-34 | AJ60: =YEAR(tbl_LoanData[[#This Row],[Application Date]]) -> 2023 | AK60: =TEXT(tbl_LoanData[[#This Row],[Application Date]],"MMMM") -> January | AL60: =DATE(YEAR(tbl_LoanData[[#This Row],[Application Date]]),MONTH(tbl_LoanData[[#This Row],[Application Date]]),1) -> 44927 | AM60: =IF(AND(tbl_LoanData[[#This Row],[Application Date]]>=EOMONTH(TODAY(),-1)+1,tbl_LoanData[[#This Row],[Application Date]]<=TODAY()),tbl_LoanData[[#This Row],[Loan Amount]],0) -> 0 | AN60: =tbl_LoanData[[#This Row],[Amount Paid]]-(Q60-X60) -> 155667.78 | AO60: =IF(tbl_LoanData[[#This Row],[Application Status]]="Approved",1,0) -> 1 | AP60: =IF(AND(J60>=DATE(YEAR(TODAY()),MONTH(TODAY()),1),J60<=TODAY()),"Current MTD",IF(AND(J60>=EOMONTH(TODAY(),-2)+1,J60<=EOMONTH(TODAY(),-1)),"Previous MTD","")) | AQ60: =IF(AND(J60>=DATE(YEAR(TODAY()),MONTH(TODAY()),1),J60<=TODAY()),TEXT(DATE(YEAR(TODAY()),MONTH(TODAY()),1),"mmm d")&"–"&DAY(TODAY()),IF(AND(J60>=EOMONTH(TODAY(),-2)+1,J60<=EOMONTH(TODAY(),-1)),""&TEXT(EOMONTH(TODAY(),-2)+1,"mmm d")&"–"&DAY(TODAY()),""))
A61: LN-103169 | B61: CUS-203169 | C61: Ana | D61: Garcia | E61: Zamora | F61: 25 | G61: Female | H61: Calamba | I61: Region IV-A (CALABARZON) | J61: 44937 | L61: Motorcycle | M61: Yamaha | N61: Aerox | O61: 247000 | P61: 62000 | Q61: 185000 | R61: 48 | S61: 5.99 | T61: 4777.62 | U61: Rejected | V61: Not Applicable | W61: 0 | X61: 0 | Y61: 229326 | Z61: 0 | AA61: Not Applicable | AB61: Cavite | AC61: E. Ferrer | AD61: Monthly | AE61: 74.9 | AF61: 0 | AG61: Not Applicable | AI61: =IF(F61<25,"18-24",IF(F61<35,"25-34",IF(F61<45,"35-44",IF(F61<55,"45-54",IF(F61<65,"55-64","65+"))))) -> 25-34 | AJ61: =YEAR(tbl_LoanData[[#This Row],[Application Date]]) -> 2023 | AK61: =TEXT(tbl_LoanData[[#This Row],[Application Date]],"MMMM") -> January | AL61: =DATE(YEAR(tbl_LoanData[[#This Row],[Application Date]]),MONTH(tbl_LoanData[[#This Row],[Application Date]]),1) -> 44927 | AM61: =IF(AND(tbl_LoanData[[#This Row],[Application Date]]>=EOMONTH(TODAY(),-1)+1,tbl_LoanData[[#This Row],[Application Date]]<=TODAY()),tbl_LoanData[[#This Row],[Loan Amount]],0) -> 0 | AN61: =tbl_LoanData[[#This Row],[Amount Paid]]-(Q61-X61) -> -185000 | AO61: =IF(tbl_LoanData[[#This Row],[Application Status]]="Approved",1,0) -> 0 | AP61: =IF(AND(J61>=DATE(YEAR(TODAY()),MONTH(TODAY()),1),J61<=TODAY()),"Current MTD",IF(AND(J61>=EOMONTH(TODAY(),-2)+1,J61<=EOMONTH(TODAY(),-1)),"Previous MTD","")) | AQ61: =IF(AND(J61>=DATE(YEAR(TODAY()),MONTH(TODAY()),1),J61<=TODAY()),TEXT(DATE(YEAR(TODAY()),MONTH(TODAY()),1),"mmm d")&"–"&DAY(TODAY()),IF(AND(J61>=EOMONTH(TODAY(),-2)+1,J61<=EOMONTH(TODAY(),-1)),""&TEXT(EOMONTH(TODAY(),-2)+1,"mmm d")&"–"&DAY(TODAY()),""))
A62: LN-103201 | B62: CUS-203201 | C62: Jennifer | D62: Pascual | E62: Salazar | F62: 58 | G62: Female | H62: Batangas City | I62: Region IV-A (CALABARZON) | J62: 44949 | L62: Pickup | M62: Isuzu | N62: D-Max | O62: 1135000 | P62: 278800 | Q62: 856200 | R62: 36 | S62: 14.42 | T62: 34072 | U62: Rejected | V62: Not Applicable | W62: 0 | X62: 0 | Y62: 1226592.1 | Z62: 0 | AA62: Not Applicable | AB62: Quezon City | AC62: I. Cabrera | AD62: Monthly | AE62: 75.44 | AF62: 0 | AG62: Not Applicable | AI62: =IF(F62<25,"18-24",IF(F62<35,"25-34",IF(F62<45,"35-44",IF(F62<55,"45-54",IF(F62<65,"55-64","65+"))))) -> 55-64 | AJ62: =YEAR(tbl_LoanData[[#This Row],[Application Date]]) -> 2023 | AK62: =TEXT(tbl_LoanData[[#This Row],[Application Date]],"MMMM") -> January | AL62: =DATE(YEAR(tbl_LoanData[[#This Row],[Application Date]]),MONTH(tbl_LoanData[[#This Row],[Application Date]]),1) -> 44927 | AM62: =IF(AND(tbl_LoanData[[#This Row],[Application Date]]>=EOMONTH(TODAY(),-1)+1,tbl_LoanData[[#This Row],[Application Date]]<=TODAY()),tbl_LoanData[[#This Row],[Loan Amount]],0) -> 0 | AN62: =tbl_LoanData[[#This Row],[Amount Paid]]-(Q62-X62) -> -856200 | AO62: =IF(tbl_LoanData[[#This Row],[Application Status]]="Approved",1,0) -> 0 | AP62: =IF(AND(J62>=DATE(YEAR(TODAY()),MONTH(TODAY()),1),J62<=TODAY()),"Current MTD",IF(AND(J62>=EOMONTH(TODAY(),-2)+1,J62<=EOMONTH(TODAY(),-1)),"Previous MTD","")) | AQ62: =IF(AND(J62>=DATE(YEAR(TODAY()),MONTH(TODAY()),1),J62<=TODAY()),TEXT(DATE(YEAR(TODAY()),MONTH(TODAY()),1),"mmm d")&"–"&DAY(TODAY()),IF(AND(J62>=EOMONTH(TODAY(),-2)+1,J62<=EOMONTH(TODAY(),-1)),""&TEXT(EOMONTH(TODAY(),-2)+1,"mmm d")&"–"&DAY(TODAY()),""))
A63: LN-103259 | B63: CUS-203259 | C63: Domingo | D63: Torres | E63: Dela Cruz | F63: 41 | G63: Male | H63: Las Pinas | I63: NCR | J63: 44954 | K63: 44956 | L63: SUV | M63: Mitsubishi | N63: Montero Sport | O63: 2434000 | P63: 246100 | Q63: 2187900 | R63: 24 | S63: 12.23 | T63: 113460.85 | U63: Approved | V63: Defaulted | W63: 2496138.7 | X63: 226921.64 | Y63: 2723060.3 | Z63: 58 | AA63: 31-60 Days | AB63: Makati | AC63: J. Espino | AD63: Monthly | AE63: 89.89 | AF63: 2 | AG63: Medium RIsk | AH63: 2 | AI63: =IF(F63<25,"18-24",IF(F63<35,"25-34",IF(F63<45,"35-44",IF(F63<55,"45-54",IF(F63<65,"55-64","65+"))))) -> 35-44 | AJ63: =YEAR(tbl_LoanData[[#This Row],[Application Date]]) -> 2023 | AK63: =TEXT(tbl_LoanData[[#This Row],[Application Date]],"MMMM") -> January | AL63: =DATE(YEAR(tbl_LoanData[[#This Row],[Application Date]]),MONTH(tbl_LoanData[[#This Row],[Application Date]]),1) -> 44927 | AM63: =IF(AND(tbl_LoanData[[#This Row],[Application Date]]>=EOMONTH(TODAY(),-1)+1,tbl_LoanData[[#This Row],[Application Date]]<=TODAY()),tbl_LoanData[[#This Row],[Loan Amount]],0) -> 0 | AN63: =tbl_LoanData[[#This Row],[Amount Paid]]-(Q63-X63) -> 535160.34 | AO63: =IF(tbl_LoanData[[#This Row],[Application Status]]="Approved",1,0) -> 1 | AP63: =IF(AND(J63>=DATE(YEAR(TODAY()),MONTH(TODAY()),1),J63<=TODAY()),"Current MTD",IF(AND(J63>=EOMONTH(TODAY(),-2)+1,J63<=EOMONTH(TODAY(),-1)),"Previous MTD","")) | AQ63: =IF(AND(J63>=DATE(YEAR(TODAY()),MONTH(TODAY()),1),J63<=TODAY()),TEXT(DATE(YEAR(TODAY()),MONTH(TODAY()),1),"mmm d")&"–"&DAY(TODAY()),IF(AND(J63>=EOMONTH(TODAY(),-2)+1,J63<=EOMONTH(TODAY(),-1)),""&TEXT(EOMONTH(TODAY(),-2)+1,"mmm d")&"–"&DAY(TODAY()),""))
A64: LN-103270 | B64: CUS-203270 | C64: Beatriz | D64: Reyes | E64: Garcia | F64: 54 | G64: Female | H64: Zamboanga City | I64: Region IX (Zamboanga Peninsula) | J64: 44937 | K64: 44958 | L64: MPV/Van | M64: Toyota | N64: Innova | O64: 2010000 | P64: 628600 | Q64: 1381400 | R64: 12 | S64: 8.21 | T64: 124567.74 | U64: Approved | V64: Closed - Fully Paid | W64: 1494812.9 | X64: 0 | Y64: 1494812.9 | Z64: 0 | AA64: Current | AB64: Cebu | AC64: J. Espino | AD64: Monthly | AE64: 68.73 | AF64: 0 | AG64: Low Risk | AH64: 21 | AI64: =IF(F64<25,"18-24",IF(F64<35,"25-34",IF(F64<45,"35-44",IF(F64<55,"45-54",IF(F64<65,"55-64","65+"))))) -> 45-54 | AJ64: =YEAR(tbl_LoanData[[#This Row],[Application Date]]) -> 2023 | AK64: =TEXT(tbl_LoanData[[#This Row],[Application Date]],"MMMM") -> January | AL64: =DATE(YEAR(tbl_LoanData[[#This Row],[Application Date]]),MONTH(tbl_LoanData[[#This Row],[Application Date]]),1) -> 44927 | AM64: =IF(AND(tbl_LoanData[[#This Row],[Application Date]]>=EOMONTH(TODAY(),-1)+1,tbl_LoanData[[#This Row],[Application Date]]<=TODAY()),tbl_LoanData[[#This Row],[Loan Amount]],0) -> 0 | AN64: =tbl_LoanData[[#This Row],[Amount Paid]]-(Q64-X64) -> 113412.94 | AO64: =IF(tbl_LoanData[[#This Row],[Application Status]]="Approved",1,0) -> 1 | AP64: =IF(AND(J64>=DATE(YEAR(TODAY()),MONTH(TODAY()),1),J64<=TODAY()),"Current MTD",IF(AND(J64>=EOMONTH(TODAY(),-2)+1,J64<=EOMONTH(TODAY(),-1)),"Previous MTD","")) | AQ64: =IF(AND(J64>=DATE(YEAR(TODAY()),MONTH(TODAY()),1),J64<=TODAY()),TEXT(DATE(YEAR(TODAY()),MONTH(TODAY()),1),"mmm d")&"–"&DAY(TODAY()),IF(AND(J64>=EOMONTH(TODAY(),-2)+1,J64<=EOMONTH(TODAY(),-1)),""&TEXT(EOMONTH(TODAY(),-2)+1,"mmm d")&"–"&DAY(TODAY()),""))
A65: LN-103272 | B65: CUS-203272 | C65: Josefa | D65: Santos | E65: Ramos | F65: 32 | G65: Female | H65: Paranaque | I65: NCR | J65: 44939 | K65: 44943 | L65: Motorcycle | M65: Kawasaki | N65: Barako | O65: 130000 | P65: 33500 | Q65: 96500 | R65: 36 | S65: 11.96 | T65: 3642.34 | U65: Approved | V65: Closed - Fully Paid | W65: 131124.2 | X65: 0 | Y65: 131124.2 | Z65: 0 | AA65: Current | AB65: Davao | AC65: G. Bunag | AD65: Monthly | AE65: 74.23 | AF65: 0 | AG65: Low Risk | AH65: 4 | AI65: =IF(F65<25,"18-24",IF(F65<35,"25-34",IF(F65<45,"35-44",IF(F65<55,"45-54",IF(F65<65,"55-64","65+"))))) -> 25-34 | AJ65: =YEAR(tbl_LoanData[[#This Row],[Application Date]]) -> 2023 | AK65: =TEXT(tbl_LoanData[[#This Row],[Application Date]],"MMMM") -> January | AL65: =DATE(YEAR(tbl_LoanData[[#This Row],[Application Date]]),MONTH(tbl_LoanData[[#This Row],[Application Date]]),1) -> 44927 | AM65: =IF(AND(tbl_LoanData[[#This Row],[Application Date]]>=EOMONTH(TODAY(),-1)+1,tbl_LoanData[[#This Row],[Application Date]]<=TODAY()),tbl_LoanData[[#This Row],[Loan Amount]],0) -> 0 | AN65: =tbl_LoanData[[#This Row],[Amount Paid]]-(Q65-X65) -> 34624.2 | AO65: =IF(tbl_LoanData[[#This Row],[Application Status]]="Approved",1,0) -> 1 | AP65: =IF(AND(J65>=DATE(YEAR(TODAY()),MONTH(TODAY()),1),J65<=TODAY()),"Current MTD",IF(AND(J65>=EOMONTH(TODAY(),-2)+1,J65<=EOMONTH(TODAY(),-1)),"Previous MTD","")) | AQ65: =IF(AND(J65>=DATE(YEAR(TODAY()),MONTH(TODAY()),1),J65<=TODAY()),TEXT(DATE(YEAR(TODAY()),MONTH(TODAY()),1),"mmm d")&"–"&DAY(TODAY()),IF(AND(J65>=EOMONTH(TODAY(),-2)+1,J65<=EOMONTH(TODAY(),-1)),""&TEXT(EOMONTH(TODAY(),-2)+1,"mmm d")&"–"&DAY(TODAY()),""))
A66: LN-103318 | B66: CUS-203318 | C66: Roberto | D66: Del Rosario | E66: Gonzales | F66: 34 | G66: Male | H66: Marikina | I66: NCR | J66: 44949 | K66: 44958 | L66: Motorcycle | M66: Kawasaki | N66: Rouser NS | O66: 101000 | P66: 37200 | Q66: 63800 | R66: 36 | S66: 10.87 | T66: 2350.14 | U66: Approved | V66: Closed - Fully Paid | W66: 84605.18 | X66: 0 | Y66: 84605.18 | Z66: 0 | AA66: Current | AB66: Makati | AC66: B. Santiago | AD66: Monthly | AE66: 63.17 | AF66: 0 | AG66: Low Risk | AH66: 9 | AI66: =IF(F66<25,"18-24",IF(F66<35,"25-34",IF(F66<45,"35-44",IF(F66<55,"45-54",IF(F66<65,"55-64","65+"))))) -> 25-34 | AJ66: =YEAR(tbl_LoanData[[#This Row],[Application Date]]) -> 2023 | AK66: =TEXT(tbl_LoanData[[#This Row],[Application Date]],"MMMM") -> January | AL66: =DATE(YEAR(tbl_LoanData[[#This Row],[Application Date]]),MONTH(tbl_LoanData[[#This Row],[Application Date]]),1) -> 44927 | AM66: =IF(AND(tbl_LoanData[[#This Row],[Application Date]]>=EOMONTH(TODAY(),-1)+1,tbl_LoanData[[#This Row],[Application Date]]<=TODAY()),tbl_LoanData[[#This Row],[Loan Amount]],0) -> 0 | AN66: =tbl_LoanData[[#This Row],[Amount Paid]]-(Q66-X66) -> 20805.18 | AO66: =IF(tbl_LoanData[[#This Row],[Application Status]]="Approved",1,0) -> 1 | AP66: =IF(AND(J66>=DATE(YEAR(TODAY()),MONTH(TODAY()),1),J66<=TODAY()),"Current MTD",IF(AND(J66>=EOMONTH(TODAY(),-2)+1,J66<=EOMONTH(TODAY(),-1)),"Previous MTD","")) | AQ66: =IF(AND(J66>=DATE(YEAR(TODAY()),MONTH(TODAY()),1),J66<=TODAY()),TEXT(DATE(YEAR(TODAY()),MONTH(TODAY()),1),"mmm d")&"–"&DAY(TODAY()),IF(AND(J66>=EOMONTH(TODAY(),-2)+1,J66<=EOMONTH(TODAY(),-1)),""&TEXT(EOMONTH(TODAY(),-2)+1,"mmm d")&"–"&DAY(TODAY()),""))
A67: LN-103343 | B67: CUS-203343 | C67: Efren | D67: Salazar | E67: Valdez | F67: 43 | G67: Male | H67: Santa Rosa | I67: Region IV-A (CALABARZON) | J67: 44937 | K67: 44944 | L67: Motorcycle | M67: Suzuki | N67: Raider R150 | O67: 228000 | P67: 69800 | Q67: 158200 | R67: 12 | S67: 6.15 | T67: 13994.11 | U67: Approved | V67: Defaulted | W67: 153935.21 | X67: 13994.09 | Y67: 167929.3 | Z67: 30 | AA67: 1-30 Days | AB67: Makati | AC67: C. Villareal | AD67: Monthly | AE67: 69.39 | AF67: 1 | AG67: Low Risk | AH67: 7 | AI67: =IF(F67<25,"18-24",IF(F67<35,"25-34",IF(F67<45,"35-44",IF(F67<55,"45-54",IF(F67<65,"55-64","65+"))))) -> 35-44 | AJ67: =YEAR(tbl_LoanData[[#This Row],[Application Date]]) -> 2023 | AK67: =TEXT(tbl_LoanData[[#This Row],[Application Date]],"MMMM") -> January | AL67: =DATE(YEAR(tbl_LoanData[[#This Row],[Application Date]]),MONTH(tbl_LoanData[[#This Row],[Application Date]]),1) -> 44927 | AM67: =IF(AND(tbl_LoanData[[#This Row],[Application Date]]>=EOMONTH(TODAY(),-1)+1,tbl_LoanData[[#This Row],[Application Date]]<=TODAY()),tbl_LoanData[[#This Row],[Loan Amount]],0) -> 0 | AN67: =tbl_LoanData[[#This Row],[Amount Paid]]-(Q67-X67) -> 9729.3 | AO67: =IF(tbl_LoanData[[#This Row],[Application Status]]="Approved",1,0) -> 1 | AP67: =IF(AND(J67>=DATE(YEAR(TODAY()),MONTH(TODAY()),1),J67<=TODAY()),"Current MTD",IF(AND(J67>=EOMONTH(TODAY(),-2)+1,J67<=EOMONTH(TODAY(),-1)),"Previous MTD","")) | AQ67: =IF(AND(J67>=DATE(YEAR(TODAY()),MONTH(TODAY()),1),J67<=TODAY()),TEXT(DATE(YEAR(TODAY()),MONTH(TODAY()),1),"mmm d")&"–"&DAY(TODAY()),IF(AND(J67>=EOMONTH(TODAY(),-2)+1,J67<=EOMONTH(TODAY(),-1)),""&TEXT(EOMONTH(TODAY(),-2)+1,"mmm d")&"–"&DAY(TODAY()),""))
A68: LN-103357 | B68: CUS-203357 | C68: Julio | D68: Reyes | E68: Umali | F68: 48 | G68: Male | H68: Butuan | I68: Region XIII (Caraga) | J68: 44937 | K68: 44950 | L68: Sedan | M68: Hyundai | N68: Elantra | O68: 811000 | P68: 258800 | Q68: 552200 | R68: 24 | S68: 14.54 | T68: 29699.16 | U68: Approved | V68: Closed - Fully Paid | W68: 712779.76 | X68: 0 | Y68: 712779.76 | Z68: 0 | AA68: Current | AB68: Cebu | AC68: B. Santiago | AD68: Monthly | AE68: 68.09 | AF68: 0 | AG68: Low Risk | AH68: 13 | AI68: =IF(F68<25,"18-24",IF(F68<35,"25-34",IF(F68<45,"35-44",IF(F68<55,"45-54",IF(F68<65,"55-64","65+"))))) -> 45-54 | AJ68: =YEAR(tbl_LoanData[[#This Row],[Application Date]]) -> 2023 | AK68: =TEXT(tbl_LoanData[[#This Row],[Application Date]],"MMMM") -> January | AL68: =DATE(YEAR(tbl_LoanData[[#This Row],[Application Date]]),MONTH(tbl_LoanData[[#This Row],[Application Date]]),1) -> 44927 | AM68: =IF(AND(tbl_LoanData[[#This Row],[Application Date]]>=EOMONTH(TODAY(),-1)+1,tbl_LoanData[[#This Row],[Application Date]]<=TODAY()),tbl_LoanData[[#This Row],[Loan Amount]],0) -> 0 | AN68: =tbl_LoanData[[#This Row],[Amount Paid]]-(Q68-X68) -> 160579.76 | AO68: =IF(tbl_LoanData[[#This Row],[Application Status]]="Approved",1,0) -> 1 | AP68: =IF(AND(J68>=DATE(YEAR(TODAY()),MONTH(TODAY()),1),J68<=TODAY()),"Current MTD",IF(AND(J68>=EOMONTH(TODAY(),-2)+1,J68<=EOMONTH(TODAY(),-1)),"Previous MTD","")) | AQ68: =IF(AND(J68>=DATE(YEAR(TODAY()),MONTH(TODAY()),1),J68<=TODAY()),TEXT(DATE(YEAR(TODAY()),MONTH(TODAY()),1),"mmm d")&"–"&DAY(TODAY()),IF(AND(J68>=EOMONTH(TODAY(),-2)+1,J68<=EOMONTH(TODAY(),-1)),""&TEXT(EOMONTH(TODAY(),-2)+1,"mmm d")&"–"&DAY(TODAY()),""))
A69: LN-103431 | B69: CUS-203431 | C69: Veronica | D69: Pascual | E69: Mendoza | F69: 52 | G69: Female | H69: Manila | I69: NCR | J69: 44954 | K69: 44965 | L69: Sedan | M69: Mitsubishi | N69: Mirage G4 | O69: 1450000 | P69: 420400 | Q69: 1029600 | R69: 60 | S69: 9.31 | T69: 25147.98 | U69: Approved | V69: Active | W69: 1056215.2 | X69: 452663.64 | Y69: 1508878.8 | Z69: 0 | AA69: Current | AB69: Baguio | AC69: C. Villareal | AD69: Monthly | AE69: 71.01 | AF69: 0 | AG69: Low Risk | AH69: 11 | AI69: =IF(F69<25,"18-24",IF(F69<35,"25-34",IF(F69<45,"35-44",IF(F69<55,"45-54",IF(F69<65,"55-64","65+"))))) -> 45-54 | AJ69: =YEAR(tbl_LoanData[[#This Row],[Application Date]]) -> 2023 | AK69: =TEXT(tbl_LoanData[[#This Row],[Application Date]],"MMMM") -> January | AL69: =DATE(YEAR(tbl_LoanData[[#This Row],[Application Date]]),MONTH(tbl_LoanData[[#This Row],[Application Date]]),1) -> 44927 | AM69: =IF(AND(tbl_LoanData[[#This Row],[Application Date]]>=EOMONTH(TODAY(),-1)+1,tbl_LoanData[[#This Row],[Application Date]]<=TODAY()),tbl_LoanData[[#This Row],[Loan Amount]],0) -> 0 | AN69: =tbl_LoanData[[#This Row],[Amount Paid]]-(Q69-X69) -> 479278.8 | AO69: =IF(tbl_LoanData[[#This Row],[Application Status]]="Approved",1,0) -> 1 | AP69: =IF(AND(J69>=DATE(YEAR(TODAY()),MONTH(TODAY()),1),J69<=TODAY()),"Current MTD",IF(AND(J69>=EOMONTH(TODAY(),-2)+1,J69<=EOMONTH(TODAY(),-1)),"Previous MTD","")) | AQ69: =IF(AND(J69>=DATE(YEAR(TODAY()),MONTH(TODAY()),1),J69<=TODAY()),TEXT(DATE(YEAR(TODAY()),MONTH(TODAY()),1),"mmm d")&"–"&DAY(TODAY()),IF(AND(J69>=EOMONTH(TODAY(),-2)+1,J69<=EOMONTH(TODAY(),-1)),""&TEXT(EOMONTH(TODAY(),-2)+1,"mmm d")&"–"&DAY(TODAY()),""))
A70: LN-103480 | B70: CUS-203480 | C70: Juan | D70: Pascual | E70: Panganiban | F70: 39 | G70: Male | H70: Cabanatuan | I70: Region III (Central Luzon) | J70: 44949 | K70: 44955 | L70: MPV/Van | M70: Suzuki | N70: Ertiga | O70: 1294000 | P70: 174900 | Q70: 1119100 | R70: 36 | S70: 14.98 | T70: 45056.21 | U70: Approved | V70: Defaulted | W70: 1576967.4 | X70: 45056.19 | Y70: 1622023.5 | Z70: 32 | AA70: 31-60 Days | AB70: Manila | AC70: C. Villareal | AD70: Monthly | AE70: 86.48 | AF70: 1 | AG70: Medium RIsk | AH70: 6 | AI70: =IF(F70<25,"18-24",IF(F70<35,"25-34",IF(F70<45,"35-44",IF(F70<55,"45-54",IF(F70<65,"55-64","65+"))))) -> 35-44 | AJ70: =YEAR(tbl_LoanData[[#This Row],[Application Date]]) -> 2023 | AK70: =TEXT(tbl_LoanData[[#This Row],[Application Date]],"MMMM") -> January | AL70: =DATE(YEAR(tbl_LoanData[[#This Row],[Application Date]]),MONTH(tbl_LoanData[[#This Row],[Application Date]]),1) -> 44927 | AM70: =IF(AND(tbl_LoanData[[#This Row],[Application Date]]>=EOMONTH(TODAY(),-1)+1,tbl_LoanData[[#This Row],[Application Date]]<=TODAY()),tbl_LoanData[[#This Row],[Loan Amount]],0) -> 0 | AN70: =tbl_LoanData[[#This Row],[Amount Paid]]-(Q70-X70) -> 502923.54 | AO70: =IF(tbl_LoanData[[#This Row],[Application Status]]="Approved",1,0) -> 1 | AP70: =IF(AND(J70>=DATE(YEAR(TODAY()),MONTH(TODAY()),1),J70<=TODAY()),"Current MTD",IF(AND(J70>=EOMONTH(TODAY(),-2)+1,J70<=EOMONTH(TODAY(),-1)),"Previous MTD","")) | AQ70: =IF(AND(J70>=DATE(YEAR(TODAY()),MONTH(TODAY()),1),J70<=TODAY()),TEXT(DATE(YEAR(TODAY()),MONTH(TODAY()),1),"mmm d")&"–"&DAY(TODAY()),IF(AND(J70>=EOMONTH(TODAY(),-2)+1,J70<=EOMONTH(TODAY(),-1)),""&TEXT(EOMONTH(TODAY(),-2)+1,"mmm d")&"–"&DAY(TODAY()),""))
A71: LN-103555 | B71: CUS-203555 | C71: Rosa | D71: Castillo | E71: Domingo | F71: 21 | G71: Female | H71: Naga (Camarines Sur) | I71: Region V (Bicol Region) | J71: 44953 | K71: 44964 | L71: Sedan | M71: Hyundai | N71: Elantra | O71: 1509000 | P71: 242000 | Q71: 1267000 | R71: 36 | S71: 14.97 | T71: 51000.27 | U71: Approved | V71: Closed - Fully Paid | W71: 1836009.7 | X71: 0 | Y71: 1836009.7 | Z71: 0 | AA71: Current | AB71: Manila | AC71: G. Bunag | AD71: Monthly | AE71: 83.96 | AF71: 0 | AG71: Low Risk | AH71: 11 | AI71: =IF(F71<25,"18-24",IF(F71<35,"25-34",IF(F71<45,"35-44",IF(F71<55,"45-54",IF(F71<65,"55-64","65+"))))) -> 18-24 | AJ71: =YEAR(tbl_LoanData[[#This Row],[Application Date]]) -> 2023 | AK71: =TEXT(tbl_LoanData[[#This Row],[Application Date]],"MMMM") -> January | AL71: =DATE(YEAR(tbl_LoanData[[#This Row],[Application Date]]),MONTH(tbl_LoanData[[#This Row],[Application Date]]),1) -> 44927 | AM71: =IF(AND(tbl_LoanData[[#This Row],[Application Date]]>=EOMONTH(TODAY(),-1)+1,tbl_LoanData[[#This Row],[Application Date]]<=TODAY()),tbl_LoanData[[#This Row],[Loan Amount]],0) -> 0 | AN71: =tbl_LoanData[[#This Row],[Amount Paid]]-(Q71-X71) -> 569009.7 | AO71: =IF(tbl_LoanData[[#This Row],[Application Status]]="Approved",1,0) -> 1 | AP71: =IF(AND(J71>=DATE(YEAR(TODAY()),MONTH(TODAY()),1),J71<=TODAY()),"Current MTD",IF(AND(J71>=EOMONTH(TODAY(),-2)+1,J71<=EOMONTH(TODAY(),-1)),"Previous MTD","")) | AQ71: =IF(AND(J71>=DATE(YEAR(TODAY()),MONTH(TODAY()),1),J71<=TODAY()),TEXT(DATE(YEAR(TODAY()),MONTH(TODAY()),1),"mmm d")&"–"&DAY(TODAY()),IF(AND(J71>=EOMONTH(TODAY(),-2)+1,J71<=EOMONTH(TODAY(),-1)),""&TEXT(EOMONTH(TODAY(),-2)+1,"mmm d")&"–"&DAY(TODAY()),""))
A72: LN-103620 | B72: CUS-203620 | C72: Wilma | D72: Garcia | E72: Del Rosario | F72: 21 | G72: Female | H72: Vigan | I72: Region I (Ilocos Region) | J72: 44934 | K72: 44937 | L72: MPV/Van | M72: Suzuki | N72: Ertiga | O72: 1004000 | P72: 383400 | Q72: 620600 | R72: 24 | S72: 13.51 | T72: 32845.25 | U72: Approved | V72: Closed - Fully Paid | W72: 788286.12 | X72: 0 | Y72: 788286.12 | Z72: 0 | AA72: Current | AB72: Baguio | AC72: D. Morales | AD72: Monthly | AE72: 61.81 | AF72: 0 | AG72: Low Risk | AH72: 3 | AI72: =IF(F72<25,"18-24",IF(F72<35,"25-34",IF(F72<45,"35-44",IF(F72<55,"45-54",IF(F72<65,"55-64","65+"))))) -> 18-24 | AJ72: =YEAR(tbl_LoanData[[#This Row],[Application Date]]) -> 2023 | AK72: =TEXT(tbl_LoanData[[#This Row],[Application Date]],"MMMM") -> January | AL72: =DATE(YEAR(tbl_LoanData[[#This Row],[Application Date]]),MONTH(tbl_LoanData[[#This Row],[Application Date]]),1) -> 44927 | AM72: =IF(AND(tbl_LoanData[[#This Row],[Application Date]]>=EOMONTH(TODAY(),-1)+1,tbl_LoanData[[#This Row],[Application Date]]<=TODAY()),tbl_LoanData[[#This Row],[Loan Amount]],0) -> 0 | AN72: =tbl_LoanData[[#This Row],[Amount Paid]]-(Q72-X72) -> 167686.12 | AO72: =IF(tbl_LoanData[[#This Row],[Application Status]]="Approved",1,0) -> 1 | AP72: =IF(AND(J72>=DATE(YEAR(TODAY()),MONTH(TODAY()),1),J72<=TODAY()),"Current MTD",IF(AND(J72>=EOMONTH(TODAY(),-2)+1,J72<=EOMONTH(TODAY(),-1)),"Previous MTD","")) | AQ72: =IF(AND(J72>=DATE(YEAR(TODAY()),MONTH(TODAY()),1),J72<=TODAY()),TEXT(DATE(YEAR(TODAY()),MONTH(TODAY()),1),"mmm d")&"–"&DAY(TODAY()),IF(AND(J72>=EOMONTH(TODAY(),-2)+1,J72<=EOMONTH(TODAY(),-1)),""&TEXT(EOMONTH(TODAY(),-2)+1,"mmm d")&"–"&DAY(TODAY()),""))
A73: LN-103658 | B73: CUS-203658 | C73: Dianne | D73: Salazar | E73: Ignacio | F73: 55 | G73: Female | H73: San Pablo | I73: Region IV-A (CALABARZON) | J73: 44930 | K73: 44942 | L73: Sedan | M73: Mitsubishi | N73: Mirage G4 | O73: 1365000 | P73: 462600 | Q73: 902400 | R73: 24 | S73: 14.16 | T73: 48248.32 | U73: Approved | V73: Closed - Fully Paid | W73: 1157959.7 | X73: 0 | Y73: 1157959.7 | Z73: 0 | AA73: Current | AB73: Makati | AC73: I. Cabrera | AD73: Monthly | AE73: 66.11 | AF73: 0 | AG73: Low Risk | AH73: 12 | AI73: =IF(F73<25,"18-24",IF(F73<35,"25-34",IF(F73<45,"35-44",IF(F73<55,"45-54",IF(F73<65,"55-64","65+"))))) -> 55-64 | AJ73: =YEAR(tbl_LoanData[[#This Row],[Application Date]]) -> 2023 | AK73: =TEXT(tbl_LoanData[[#This Row],[Application Date]],"MMMM") -> January | AL73: =DATE(YEAR(tbl_LoanData[[#This Row],[Application Date]]),MONTH(tbl_LoanData[[#This Row],[Application Date]]),1) -> 44927 | AM73: =IF(AND(tbl_LoanData[[#This Row],[Application Date]]>=EOMONTH(TODAY(),-1)+1,tbl_LoanData[[#This Row],[Application Date]]<=TODAY()),tbl_LoanData[[#This Row],[Loan Amount]],0) -> 0 | AN73: =tbl_LoanData[[#This Row],[Amount Paid]]-(Q73-X73) -> 255559.68 | AO73: =IF(tbl_LoanData[[#This Row],[Application Status]]="Approved",1,0) -> 1 | AP73: =IF(AND(J73>=DATE(YEAR(TODAY()),MONTH(TODAY()),1),J73<=TODAY()),"Current MTD",IF(AND(J73>=EOMONTH(TODAY(),-2)+1,J73<=EOMONTH(TODAY(),-1)),"Previous MTD","")) | AQ73: =IF(AND(J73>=DATE(YEAR(TODAY()),MONTH(TODAY()),1),J73<=TODAY()),TEXT(DATE(YEAR(TODAY()),MONTH(TODAY()),1),"mmm d")&"–"&DAY(TODAY()),IF(AND(J73>=EOMONTH(TODAY(),-2)+1,J73<=EOMONTH(TODAY(),-1)),""&TEXT(EOMONTH(TODAY(),-2)+1,"mmm d")&"–"&DAY(TODAY()),""))
A74: LN-103682 | B74: CUS-203682 | C74: Oscar | D74: Castillo | E74: Torres | F74: 37 | G74: Male | H74: General Santos | I74: Region XII (SOCCSKSARGEN) | J74: 44941 | K74: 44950 | L74: Motorcycle | M74: Kawasaki | N74: Barako | O74: 125000 | P74: 19900 | Q74: 105100 | R74: 36 | S74: 13.77 | T74: 4125.47 | U74: Approved | V74: Defaulted | W74: 144391.45 | X74: 4125.36 | Y74: 148516.81 | Z74: 29 | AA74: 1-30 Days | AB74: Makati | AC74: I. Cabrera | AD74: Monthly | AE74: 84.08 | AF74: 1 | AG74: Low Risk | AH74: 9 | AI74: =IF(F74<25,"18-24",IF(F74<35,"25-34",IF(F74<45,"35-44",IF(F74<55,"45-54",IF(F74<65,"55-64","65+"))))) -> 35-44 | AJ74: =YEAR(tbl_LoanData[[#This Row],[Application Date]]) -> 2023 | AK74: =TEXT(tbl_LoanData[[#This Row],[Application Date]],"MMMM") -> January | AL74: =DATE(YEAR(tbl_LoanData[[#This Row],[Application Date]]),MONTH(tbl_LoanData[[#This Row],[Application Date]]),1) -> 44927 | AM74: =IF(AND(tbl_LoanData[[#This Row],[Application Date]]>=EOMONTH(TODAY(),-1)+1,tbl_LoanData[[#This Row],[Application Date]]<=TODAY()),tbl_LoanData[[#This Row],[Loan Amount]],0) -> 0 | AN74: =tbl_LoanData[[#This Row],[Amount Paid]]-(Q74-X74) -> 43416.81 | AO74: =IF(tbl_LoanData[[#This Row],[Application Status]]="Approved",1,0) -> 1 | AP74: =IF(AND(J74>=DATE(YEAR(TODAY()),MONTH(TODAY()),1),J74<=TODAY()),"Current MTD",IF(AND(J74>=EOMONTH(TODAY(),-2)+1,J74<=EOMONTH(TODAY(),-1)),"Previous MTD","")) | AQ74: =IF(AND(J74>=DATE(YEAR(TODAY()),MONTH(TODAY()),1),J74<=TODAY()),TEXT(DATE(YEAR(TODAY()),MONTH(TODAY()),1),"mmm d")&"–"&DAY(TODAY()),IF(AND(J74>=EOMONTH(TODAY(),-2)+1,J74<=EOMONTH(TODAY(),-1)),""&TEXT(EOMONTH(TODAY(),-2)+1,"mmm d")&"–"&DAY(TODAY()),""))
A75: LN-103715 | B75: CUS-203715 | C75: Ofelia | D75: Torres | E75: Panganiban | F75: 32 | G75: Female | H75: Cabanatuan | I75: Region III (Central Luzon) | J75: 44944 | K75: 44961 | L75: Pickup | M75: Nissan | N75: Navara | O75: 1559000 | P75: 239300 | Q75: 1319700 | R75: 36 | S75: 13.4 | T75: 51394.98 | U75: Approved | V75: Closed - Fully Paid | W75: 1850219.4 | X75: 0 | Y75: 1850219.4 | Z75: 0 | AA75: Current | AB75: Pampanga | AC75: B. Santiago | AD75: Monthly | AE75: 84.65 | AF75: 0 | AG75: Low Risk | AH75: 17 | AI75: =IF(F75<25,"18-24",IF(F75<35,"25-34",IF(F75<45,"35-44",IF(F75<55,"45-54",IF(F75<65,"55-64","65+"))))) -> 25-34 | AJ75: =YEAR(tbl_LoanData[[#This Row],[Application Date]]) -> 2023 | AK75: =TEXT(tbl_LoanData[[#This Row],[Application Date]],"MMMM") -> January | AL75: =DATE(YEAR(tbl_LoanData[[#This Row],[Application Date]]),MONTH(tbl_LoanData[[#This Row],[Application Date]]),1) -> 44927 | AM75: =IF(AND(tbl_LoanData[[#This Row],[Application Date]]>=EOMONTH(TODAY(),-1)+1,tbl_LoanData[[#This Row],[Application Date]]<=TODAY()),tbl_LoanData[[#This Row],[Loan Amount]],0) -> 0 | AN75: =tbl_LoanData[[#This Row],[Amount Paid]]-(Q75-X75) -> 530519.4 | AO75: =IF(tbl_LoanData[[#This Row],[Application Status]]="Approved",1,0) -> 1 | AP75: =IF(AND(J75>=DATE(YEAR(TODAY()),MONTH(TODAY()),1),J75<=TODAY()),"Current MTD",IF(AND(J75>=EOMONTH(TODAY(),-2)+1,J75<=EOMONTH(TODAY(),-1)),"Previous MTD","")) | AQ75: =IF(AND(J75>=DATE(YEAR(TODAY()),MONTH(TODAY()),1),J75<=TODAY()),TEXT(DATE(YEAR(TODAY()),MONTH(TODAY()),1),"mmm d")&"–"&DAY(TODAY()),IF(AND(J75>=EOMONTH(TODAY(),-2)+1,J75<=EOMONTH(TODAY(),-1)),""&TEXT(EOMONTH(TODAY(),-2)+1,"mmm d")&"–"&DAY(TODAY()),""))
A76: LN-103841 | B76: CUS-203841 | C76: Rosa | D76: Aguilar | E76: Mendoza | F76: 52 | G76: Female | H76: Zamboanga City | I76: Region IX (Zamboanga Peninsula) | J76: 44957 | L76: MPV/Van | M76: Toyota | N76: Avanza | O76: 1786000 | P76: 584300 | Q76: 1201700 | R76: 36 | S76: 11.45 | T76: 44846.78 | U76: Rejected | V76: Not Applicable | W76: 0 | X76: 0 | Y76: 1614483.9 | Z76: 0 | AA76: Not Applicable | AB76: Davao | AC76: G. Bunag | AD76: Monthly | AE76: 67.28 | AF76: 0 | AG76: Not Applicable | AI76: =IF(F76<25,"18-24",IF(F76<35,"25-34",IF(F76<45,"35-44",IF(F76<55,"45-54",IF(F76<65,"55-64","65+"))))) -> 45-54 | AJ76: =YEAR(tbl_LoanData[[#This Row],[Application Date]]) -> 2023 | AK76: =TEXT(tbl_LoanData[[#This Row],[Application Date]],"MMMM") -> January | AL76: =DATE(YEAR(tbl_LoanData[[#This Row],[Application Date]]),MONTH(tbl_LoanData[[#This Row],[Application Date]]),1) -> 44927 | AM76: =IF(AND(tbl_LoanData[[#This Row],[Application Date]]>=EOMONTH(TODAY(),-1)+1,tbl_LoanData[[#This Row],[Application Date]]<=TODAY()),tbl_LoanData[[#This Row],[Loan Amount]],0) -> 0 | AN76: =tbl_LoanData[[#This Row],[Amount Paid]]-(Q76-X76) -> -1201700 | AO76: =IF(tbl_LoanData[[#This Row],[Application Status]]="Approved",1,0) -> 0 | AP76: =IF(AND(J76>=DATE(YEAR(TODAY()),MONTH(TODAY()),1),J76<=TODAY()),"Current MTD",IF(AND(J76>=EOMONTH(TODAY(),-2)+1,J76<=EOMONTH(TODAY(),-1)),"Previous MTD","")) | AQ76: =IF(AND(J76>=DATE(YEAR(TODAY()),MONTH(TODAY()),1),J76<=TODAY()),TEXT(DATE(YEAR(TODAY()),MONTH(TODAY()),1),"mmm d")&"–"&DAY(TODAY()),IF(AND(J76>=EOMONTH(TODAY(),-2)+1,J76<=EOMONTH(TODAY(),-1)),""&TEXT(EOMONTH(TODAY(),-2)+1,"mmm d")&"–"&DAY(TODAY()),""))
A77: LN-103895 | B77: CUS-203895 | C77: Herminia | D77: Gonzales | E77: Aquino | F77: 39 | G77: Female | H77: Cagayan de Oro | I77: Region X (Northern Mindanao) | J77: 44931 | K77: 44936 | L77: Motorcycle | M77: Suzuki | N77: Skydrive | O77: 163000 | P77: 24300 | Q77: 138700 | R77: 36 | S77: 5.73 | T77: 4515.07 | U77: Approved | V77: Closed - Fully Paid | W77: 162542.53 | X77: 0 | Y77: 162542.53 | Z77: 0 | AA77: Current | AB77: Makati | AC77: J. Espino | AD77: Monthly | AE77: 85.09 | AF77: 0 | AG77: Low Risk | AH77: 5 | AI77: =IF(F77<25,"18-24",IF(F77<35,"25-34",IF(F77<45,"35-44",IF(F77<55,"45-54",IF(F77<65,"55-64","65+"))))) -> 35-44 | AJ77: =YEAR(tbl_LoanData[[#This Row],[Application Date]]) -> 2023 | AK77: =TEXT(tbl_LoanData[[#This Row],[Application Date]],"MMMM") -> January | AL77: =DATE(YEAR(tbl_LoanData[[#This Row],[Application Date]]),MONTH(tbl_LoanData[[#This Row],[Application Date]]),1) -> 44927 | AM77: =IF(AND(tbl_LoanData[[#This Row],[Application Date]]>=EOMONTH(TODAY(),-1)+1,tbl_LoanData[[#This Row],[Application Date]]<=TODAY()),tbl_LoanData[[#This Row],[Loan Amount]],0) -> 0 | AN77: =tbl_LoanData[[#This Row],[Amount Paid]]-(Q77-X77) -> 23842.53 | AO77: =IF(tbl_LoanData[[#This Row],[Application Status]]="Approved",1,0) -> 1 | AP77: =IF(AND(J77>=DATE(YEAR(TODAY()),MONTH(TODAY()),1),J77<=TODAY()),"Current MTD",IF(AND(J77>=EOMONTH(TODAY(),-2)+1,J77<=EOMONTH(TODAY(),-1)),"Previous MTD","")) | AQ77: =IF(AND(J77>=DATE(YEAR(TODAY()),MONTH(TODAY()),1),J77<=TODAY()),TEXT(DATE(YEAR(TODAY()),MONTH(TODAY()),1),"mmm d")&"–"&DAY(TODAY()),IF(AND(J77>=EOMONTH(TODAY(),-2)+1,J77<=EOMONTH(TODAY(),-1)),""&TEXT(EOMONTH(TODAY(),-2)+1,"mmm d")&"–"&DAY(TODAY()),""))
A78: LN-104015 | B78: CUS-204015 | C78: Angelica | D78: Domingo | E78: Pascual | F78: 45 | G78: Female | H78: Paranaque | I78: NCR | J78: 44948 | L78: Sedan | M78: Toyota | N78: Camry | O78: 707000 | P78: 91100 | Q78: 615900 | R78: 36 | S78: 10.62 | T78: 22559.05 | U78: Rejected | V78: Not Applicable | W78: 0 | X78: 0 | Y78: 812125.74 | Z78: 0 | AA78: Not Applicable | AB78: Davao | AC78: A. Ramirez | AD78: Monthly | AE78: 87.11 | AF78: 0 | AG78: Not Applicable | AI78: =IF(F78<25,"18-24",IF(F78<35,"25-34",IF(F78<45,"35-44",IF(F78<55,"45-54",IF(F78<65,"55-64","65+"))))) -> 45-54 | AJ78: =YEAR(tbl_LoanData[[#This Row],[Application Date]]) -> 2023 | AK78: =TEXT(tbl_LoanData[[#This Row],[Application Date]],"MMMM") -> January | AL78: =DATE(YEAR(tbl_LoanData[[#This Row],[Application Date]]),MONTH(tbl_LoanData[[#This Row],[Application Date]]),1) -> 44927 | AM78: =IF(AND(tbl_LoanData[[#This Row],[Application Date]]>=EOMONTH(TODAY(),-1)+1,tbl_LoanData[[#This Row],[Application Date]]<=TODAY()),tbl_LoanData[[#This Row],[Loan Amount]],0) -> 0 | AN78: =tbl_LoanData[[#This Row],[Amount Paid]]-(Q78-X78) -> -615900 | AO78: =IF(tbl_LoanData[[#This Row],[Application Status]]="Approved",1,0) -> 0 | AP78: =IF(AND(J78>=DATE(YEAR(TODAY()),MONTH(TODAY()),1),J78<=TODAY()),"Current MTD",IF(AND(J78>=EOMONTH(TODAY(),-2)+1,J78<=EOMONTH(TODAY(),-1)),"Previous MTD","")) | AQ78: =IF(AND(J78>=DATE(YEAR(TODAY()),MONTH(TODAY()),1),J78<=TODAY()),TEXT(DATE(YEAR(TODAY()),MONTH(TODAY()),1),"mmm d")&"–"&DAY(TODAY()),IF(AND(J78>=EOMONTH(TODAY(),-2)+1,J78<=EOMONTH(TODAY(),-1)),""&TEXT(EOMONTH(TODAY(),-2)+1,"mmm d")&"–"&DAY(TODAY()),""))
A79: LN-104202 | B79: CUS-204202 | C79: Isidro | D79: Fernandez | E79: Flores | F79: 65 | G79: Male | H79: Zamboanga City | I79: Region IX (Zamboanga Peninsula) | J79: 44943 | L79: MPV/Van | M79: Toyota | N79: Avanza | O79: 1522000 | P79: 425700 | Q79: 1096300 | R79: 36 | S79: 14.15 | T79: 43379.98 | U79: Pending | V79: Not Applicable | W79: 0 | X79: 0 | Y79: 1561679.4 | Z79: 0 | AA79: Not Applicable | AB79: CDO | AC79: C. Villareal | AD79: Monthly | AE79: 72.03 | AF79: 0 | AG79: Not Applicable | AI79: =IF(F79<25,"18-24",IF(F79<35,"25-34",IF(F79<45,"35-44",IF(F79<55,"45-54",IF(F79<65,"55-64","65+"))))) -> 65+ | AJ79: =YEAR(tbl_LoanData[[#This Row],[Application Date]]) -> 2023 | AK79: =TEXT(tbl_LoanData[[#This Row],[Application Date]],"MMMM") -> January | AL79: =DATE(YEAR(tbl_LoanData[[#This Row],[Application Date]]),MONTH(tbl_LoanData[[#This Row],[Application Date]]),1) -> 44927 | AM79: =IF(AND(tbl_LoanData[[#This Row],[Application Date]]>=EOMONTH(TODAY(),-1)+1,tbl_LoanData[[#This Row],[Application Date]]<=TODAY()),tbl_LoanData[[#This Row],[Loan Amount]],0) -> 0 | AN79: =tbl_LoanData[[#This Row],[Amount Paid]]-(Q79-X79) -> -1096300 | AO79: =IF(tbl_LoanData[[#This Row],[Application Status]]="Approved",1,0) -> 0 | AP79: =IF(AND(J79>=DATE(YEAR(TODAY()),MONTH(TODAY()),1),J79<=TODAY()),"Current MTD",IF(AND(J79>=EOMONTH(TODAY(),-2)+1,J79<=EOMONTH(TODAY(),-1)),"Previous MTD","")) | AQ79: =IF(AND(J79>=DATE(YEAR(TODAY()),MONTH(TODAY()),1),J79<=TODAY()),TEXT(DATE(YEAR(TODAY()),MONTH(TODAY()),1),"mmm d")&"–"&DAY(TODAY()),IF(AND(J79>=EOMONTH(TODAY(),-2)+1,J79<=EOMONTH(TODAY(),-1)),""&TEXT(EOMONTH(TODAY(),-2)+1,"mmm d")&"–"&DAY(TODAY()),""))
A80: LN-104249 | B80: CUS-204249 | C80: Yolanda | D80: Salazar | E80: Gonzales | F80: 46 | G80: Female | H80: Taguig | I80: NCR | J80: 44927 | L80: SUV | M80: Honda | N80: BR-V | O80: 2299000 | P80: 814600 | Q80: 1484400 | R80: 36 | S80: 14.08 | T80: 58650.29 | U80: Rejected | V80: Not Applicable | W80: 0 | X80: 0 | Y80: 2111410.6 | Z80: 0 | AA80: Not Applicable | AB80: Quezon City | AC80: A. Ramirez | AD80: Monthly | AE80: 64.57 | AF80: 0 | AG80: Not Applicable | AI80: =IF(F80<25,"18-24",IF(F80<35,"25-34",IF(F80<45,"35-44",IF(F80<55,"45-54",IF(F80<65,"55-64","65+"))))) -> 45-54 | AJ80: =YEAR(tbl_LoanData[[#This Row],[Application Date]]) -> 2023 | AK80: =TEXT(tbl_LoanData[[#This Row],[Application Date]],"MMMM") -> January | AL80: =DATE(YEAR(tbl_LoanData[[#This Row],[Application Date]]),MONTH(tbl_LoanData[[#This Row],[Application Date]]),1) -> 44927 | AM80: =IF(AND(tbl_LoanData[[#This Row],[Application Date]]>=EOMONTH(TODAY(),-1)+1,tbl_LoanData[[#This Row],[Application Date]]<=TODAY()),tbl_LoanData[[#This Row],[Loan Amount]],0) -> 0 | AN80: =tbl_LoanData[[#This Row],[Amount Paid]]-(Q80-X80) -> -1484400 | AO80: =IF(tbl_LoanData[[#This Row],[Application Status]]="Approved",1,0) -> 0 | AP80: =IF(AND(J80>=DATE(YEAR(TODAY()),MONTH(TODAY()),1),J80<=TODAY()),"Current MTD",IF(AND(J80>=EOMONTH(TODAY(),-2)+1,J80<=EOMONTH(TODAY(),-1)),"Previous MTD","")) | AQ80: =IF(AND(J80>=DATE(YEAR(TODAY()),MONTH(TODAY()),1),J80<=TODAY()),TEXT(DATE(YEAR(TODAY()),MONTH(TODAY()),1),"mmm d")&"–"&DAY(TODAY()),IF(AND(J80>=EOMONTH(TODAY(),-2)+1,J80<=EOMONTH(TODAY(),-1)),""&TEXT(EOMONTH(TODAY(),-2)+1,"mmm d")&"–"&DAY(TODAY()),""))
A81: LN-104256 | B81: CUS-204256 | C81: Fernando | D81: Bautista | E81: Navarro | F81: 33 | G81: Male | H81: Makati | I81: NCR | J81: 44930 | K81: 44944 | L81: Sedan | M81: Hyundai | N81: Elantra | O81: 1426000 | P81: 346800 | Q81: 1079200 | R81: 24 | S81: 10.06 | T81: 54013.96 | U81: Approved | V81: Defaulted | W81: 1242321.1 | X81: 54013.96 | Y81: 1296335 | Z81: 28 | AA81: 1-30 Days | AB81: Baguio | AC81: E. Ferrer | AD81: Monthly | AE81: 75.68 | AF81: 1 | AG81: Low Risk | AH81: 14 | AI81: =IF(F81<25,"18-24",IF(F81<35,"25-34",IF(F81<45,"35-44",IF(F81<55,"45-54",IF(F81<65,"55-64","65+"))))) -> 25-34 | AJ81: =YEAR(tbl_LoanData[[#This Row],[Application Date]]) -> 2023 | AK81: =TEXT(tbl_LoanData[[#This Row],[Application Date]],"MMMM") -> January | AL81: =DATE(YEAR(tbl_LoanData[[#This Row],[Application Date]]),MONTH(tbl_LoanData[[#This Row],[Application Date]]),1) -> 44927 | AM81: =IF(AND(tbl_LoanData[[#This Row],[Application Date]]>=EOMONTH(TODAY(),-1)+1,tbl_LoanData[[#This Row],[Application Date]]<=TODAY()),tbl_LoanData[[#This Row],[Loan Amount]],0) -> 0 | AN81: =tbl_LoanData[[#This Row],[Amount Paid]]-(Q81-X81) -> 217135.04 | AO81: =IF(tbl_LoanData[[#This Row],[Application Status]]="Approved",1,0) -> 1 | AP81: =IF(AND(J81>=DATE(YEAR(TODAY()),MONTH(TODAY()),1),J81<=TODAY()),"Current MTD",IF(AND(J81>=EOMONTH(TODAY(),-2)+1,J81<=EOMONTH(TODAY(),-1)),"Previous MTD","")) | AQ81: =IF(AND(J81>=DATE(YEAR(TODAY()),MONTH(TODAY()),1),J81<=TODAY()),TEXT(DATE(YEAR(TODAY()),MONTH(TODAY()),1),"mmm d")&"–"&DAY(TODAY()),IF(AND(J81>=EOMONTH(TODAY(),-2)+1,J81<=EOMONTH(TODAY(),-1)),""&TEXT(EOMONTH(TODAY(),-2)+1,"mmm d")&"–"&DAY(TODAY()),""))
A82: LN-104270 | B82: CUS-204270 | C82: Jennifer | D82: Garcia | E82: Dela Cruz | F82: 42 | G82: Female | H82: San Fernando (Pampanga) | I82: Region III (Central Luzon) | J82: 44949 | K82: 44951 | L82: Sedan | M82: Nissan | N82: Almera | O82: 1104000 | P82: 130700 | Q82: 973300 | R82: 24 | S82: 9.86 | T82: 48551.45 | U82: Approved | V82: Closed - Fully Paid | W82: 1165234.8 | X82: 0 | Y82: 1165234.8 | Z82: 0 | AA82: Current | AB82: Baguio | AC82: G. Bunag | AD82: Monthly | AE82: 88.16 | AF82: 0 | AG82: Low Risk | AH82: 2 | AI82: =IF(F82<25,"18-24",IF(F82<35,"25-34",IF(F82<45,"35-44",IF(F82<55,"45-54",IF(F82<65,"55-64","65+"))))) -> 35-44 | AJ82: =YEAR(tbl_LoanData[[#This Row],[Application Date]]) -> 2023 | AK82: =TEXT(tbl_LoanData[[#This Row],[Application Date]],"MMMM") -> January | AL82: =DATE(YEAR(tbl_LoanData[[#This Row],[Application Date]]),MONTH(tbl_LoanData[[#This Row],[Application Date]]),1) -> 44927 | AM82: =IF(AND(tbl_LoanData[[#This Row],[Application Date]]>=EOMONTH(TODAY(),-1)+1,tbl_LoanData[[#This Row],[Application Date]]<=TODAY()),tbl_LoanData[[#This Row],[Loan Amount]],0) -> 0 | AN82: =tbl_LoanData[[#This Row],[Amount Paid]]-(Q82-X82) -> 191934.76 | AO82: =IF(tbl_LoanData[[#This Row],[Application Status]]="Approved",1,0) -> 1 | AP82: =IF(AND(J82>=DATE(YEAR(TODAY()),MONTH(TODAY()),1),J82<=TODAY()),"Current MTD",IF(AND(J82>=EOMONTH(TODAY(),-2)+1,J82<=EOMONTH(TODAY(),-1)),"Previous MTD","")) | AQ82: =IF(AND(J82>=DATE(YEAR(TODAY()),MONTH(TODAY()),1),J82<=TODAY()),TEXT(DATE(YEAR(TODAY()),MONTH(TODAY()),1),"mmm d")&"–"&DAY(TODAY()),IF(AND(J82>=EOMONTH(TODAY(),-2)+1,J82<=EOMONTH(TODAY(),-1)),""&TEXT(EOMONTH(TODAY(),-2)+1,"mmm d")&"–"&DAY(TODAY()),""))
A83: LN-104292 | B83: CUS-204292 | C83: Vincent | D83: Santos | E83: Ramos | F83: 36 | G83: Male | H83: Paranaque | I83: NCR | J83: 44955 | K83: 44959 | L83: Pickup | M83: Nissan | N83: Navara | O83: 1424000 | P83: 558300 | Q83: 865700 | R83: 36 | S83: 14.31 | T83: 34370.69 | U83: Approved | V83: Closed - Fully Paid | W83: 1237345 | X83: 0 | Y83: 1237345 | Z83: 0 | AA83: Current | AB83: Quezon City | AC83: D. Morales | AD83: Monthly | AE83: 60.79 | AF83: 0 | AG83: Low Risk | AH83: 4 | AI83: =IF(F83<25,"18-24",IF(F83<35,"25-34",IF(F83<45,"35-44",IF(F83<55,"45-54",IF(F83<65,"55-64","65+"))))) -> 35-44 | AJ83: =YEAR(tbl_LoanData[[#This Row],[Application Date]]) -> 2023 | AK83: =TEXT(tbl_LoanData[[#This Row],[Application Date]],"MMMM") -> January | AL83: =DATE(YEAR(tbl_LoanData[[#This Row],[Application Date]]),MONTH(tbl_LoanData[[#This Row],[Application Date]]),1) -> 44927 | AM83: =IF(AND(tbl_LoanData[[#This Row],[Application Date]]>=EOMONTH(TODAY(),-1)+1,tbl_LoanData[[#This Row],[Application Date]]<=TODAY()),tbl_LoanData[[#This Row],[Loan Amount]],0) -> 0 | AN83: =tbl_LoanData[[#This Row],[Amount Paid]]-(Q83-X83) -> 371645.01 | AO83: =IF(tbl_LoanData[[#This Row],[Application Status]]="Approved",1,0) -> 1 | AP83: =IF(AND(J83>=DATE(YEAR(TODAY()),MONTH(TODAY()),1),J83<=TODAY()),"Current MTD",IF(AND(J83>=EOMONTH(TODAY(),-2)+1,J83<=EOMONTH(TODAY(),-1)),"Previous MTD","")) | AQ83: =IF(AND(J83>=DATE(YEAR(TODAY()),MONTH(TODAY()),1),J83<=TODAY()),TEXT(DATE(YEAR(TODAY()),MONTH(TODAY()),1),"mmm d")&"–"&DAY(TODAY()),IF(AND(J83>=EOMONTH(TODAY(),-2)+1,J83<=EOMONTH(TODAY(),-1)),""&TEXT(EOMONTH(TODAY(),-2)+1,"mmm d")&"–"&DAY(TODAY()),""))
A84: LN-104318 | B84: CUS-204318 | C84: Imelda | D84: Ramos | E84: Mendoza | F84: 57 | G84: Female | H84: Butuan | I84: Region XIII (Caraga) | J84: 44939 | K84: 44956 | L84: Pickup | M84: Mitsubishi | N84: Strada | O84: 1004000 | P84: 395200 | Q84: 608800 | R84: 24 | S84: 10.33 | T84: 30607.42 | U84: Approved | V84: Closed - Fully Paid | W84: 734578.08 | X84: 0 | Y84: 734578.08 | Z84: 0 | AA84: Current | AB84: Makati | AC84: I. Cabrera | AD84: Monthly | AE84: 60.64 | AF84: 0 | AG84: Low Risk | AH84: 17 | AI84: =IF(F84<25,"18-24",IF(F84<35,"25-34",IF(F84<45,"35-44",IF(F84<55,"45-54",IF(F84<65,"55-64","65+"))))) -> 55-64 | AJ84: =YEAR(tbl_LoanData[[#This Row],[Application Date]]) -> 2023 | AK84: =TEXT(tbl_LoanData[[#This Row],[Application Date]],"MMMM") -> January | AL84: =DATE(YEAR(tbl_LoanData[[#This Row],[Application Date]]),MONTH(tbl_LoanData[[#This Row],[Application Date]]),1) -> 44927 | AM84: =IF(AND(tbl_LoanData[[#This Row],[Application Date]]>=EOMONTH(TODAY(),-1)+1,tbl_LoanData[[#This Row],[Application Date]]<=TODAY()),tbl_LoanData[[#This Row],[Loan Amount]],0) -> 0 | AN84: =tbl_LoanData[[#This Row],[Amount Paid]]-(Q84-X84) -> 125778.08 | AO84: =IF(tbl_LoanData[[#This Row],[Application Status]]="Approved",1,0) -> 1 | AP84: =IF(AND(J84>=DATE(YEAR(TODAY()),MONTH(TODAY()),1),J84<=TODAY()),"Current MTD",IF(AND(J84>=EOMONTH(TODAY(),-2)+1,J84<=EOMONTH(TODAY(),-1)),"Previous MTD","")) | AQ84: =IF(AND(J84>=DATE(YEAR(TODAY()),MONTH(TODAY()),1),J84<=TODAY()),TEXT(DATE(YEAR(TODAY()),MONTH(TODAY()),1),"mmm d")&"–"&DAY(TODAY()),IF(AND(J84>=EOMONTH(TODAY(),-2)+1,J84<=EOMONTH(TODAY(),-1)),""&TEXT(EOMONTH(TODAY(),-2)+1,"mmm d")&"–"&DAY(TODAY()),""))
A85: LN-104323 | B85: CUS-204323 | C85: Isidro | D85: Ocampo | E85: Cortez | F85: 53 | G85: Male | H85: Naga (Camarines Sur) | I85: Region V (Bicol Region) | J85: 44957 | L85: SUV | M85: Ford | N85: Territory | O85: 2194000 | P85: 319800 | Q85: 1874200 | R85: 36 | S85: 12.14 | T85: 71021.77 | U85: Rejected | V85: Not Applicable | W85: 0 | X85: 0 | Y85: 2556783.6 | Z85: 0 | AA85: Not Applicable | AB85: Baguio | AC85: E. Ferrer | AD85: Monthly | AE85: 85.42 | AF85: 0 | AG85: Not Applicable | AI85: =IF(F85<25,"18-24",IF(F85<35,"25-34",IF(F85<45,"35-44",IF(F85<55,"45-54",IF(F85<65,"55-64","65+"))))) -> 45-54 | AJ85: =YEAR(tbl_LoanData[[#This Row],[Application Date]]) -> 2023 | AK85: =TEXT(tbl_LoanData[[#This Row],[Application Date]],"MMMM") -> January | AL85: =DATE(YEAR(tbl_LoanData[[#This Row],[Application Date]]),MONTH(tbl_LoanData[[#This Row],[Application Date]]),1) -> 44927 | AM85: =IF(AND(tbl_LoanData[[#This Row],[Application Date]]>=EOMONTH(TODAY(),-1)+1,tbl_LoanData[[#This Row],[Application Date]]<=TODAY()),tbl_LoanData[[#This Row],[Loan Amount]],0) -> 0 | AN85: =tbl_LoanData[[#This Row],[Amount Paid]]-(Q85-X85) -> -1874200 | AO85: =IF(tbl_LoanData[[#This Row],[Application Status]]="Approved",1,0) -> 0 | AP85: =IF(AND(J85>=DATE(YEAR(TODAY()),MONTH(TODAY()),1),J85<=TODAY()),"Current MTD",IF(AND(J85>=EOMONTH(TODAY(),-2)+1,J85<=EOMONTH(TODAY(),-1)),"Previous MTD","")) | AQ85: =IF(AND(J85>=DATE(YEAR(TODAY()),MONTH(TODAY()),1),J85<=TODAY()),TEXT(DATE(YEAR(TODAY()),MONTH(TODAY()),1),"mmm d")&"–"&DAY(TODAY()),IF(AND(J85>=EOMONTH(TODAY(),-2)+1,J85<=EOMONTH(TODAY(),-1)),""&TEXT(EOMONTH(TODAY(),-2)+1,"mmm d")&"–"&DAY(TODAY()),""))
A86: LN-104337 | B86: CUS-204337 | C86: Teodoro | D86: Ocampo | E86: Macaraeg | F86: 29 | G86: Male | H86: Malolos | I86: Region III (Central Luzon) | J86: 44935 | L86: SUV | M86: Ford | N86: Territory | O86: 1591000 | P86: 273400 | Q86: 1317600 | R86: 24 | S86: 12.34 | T86: 68449.32 | U86: Rejected | V86: Not Applicable | W86: 0 | X86: 0 | Y86: 1642783.7 | Z86: 0 | AA86: Not Applicable | AB86: Pampanga | AC86: C. Villareal | AD86: Monthly | AE86: 82.82 | AF86: 0 | AG86: Not Applicable | AI86: =IF(F86<25,"18-24",IF(F86<35,"25-34",IF(F86<45,"35-44",IF(F86<55,"45-54",IF(F86<65,"55-64","65+"))))) -> 25-34 | AJ86: =YEAR(tbl_LoanData[[#This Row],[Application Date]]) -> 2023 | AK86: =TEXT(tbl_LoanData[[#This Row],[Application Date]],"MMMM") -> January | AL86: =DATE(YEAR(tbl_LoanData[[#This Row],[Application Date]]),MONTH(tbl_LoanData[[#This Row],[Application Date]]),1) -> 44927 | AM86: =IF(AND(tbl_LoanData[[#This Row],[Application Date]]>=EOMONTH(TODAY(),-1)+1,tbl_LoanData[[#This Row],[Application Date]]<=TODAY()),tbl_LoanData[[#This Row],[Loan Amount]],0) -> 0 | AN86: =tbl_LoanData[[#This Row],[Amount Paid]]-(Q86-X86) -> -1317600 | AO86: =IF(tbl_LoanData[[#This Row],[Application Status]]="Approved",1,0) -> 0 | AP86: =IF(AND(J86>=DATE(YEAR(TODAY()),MONTH(TODAY()),1),J86<=TODAY()),"Current MTD",IF(AND(J86>=EOMONTH(TODAY(),-2)+1,J86<=EOMONTH(TODAY(),-1)),"Previous MTD","")) | AQ86: =IF(AND(J86>=DATE(YEAR(TODAY()),MONTH(TODAY()),1),J86<=TODAY()),TEXT(DATE(YEAR(TODAY()),MONTH(TODAY()),1),"mmm d")&"–"&DAY(TODAY()),IF(AND(J86>=EOMONTH(TODAY(),-2)+1,J86<=EOMONTH(TODAY(),-1)),""&TEXT(EOMONTH(TODAY(),-2)+1,"mmm d")&"–"&DAY(TODAY()),""))
A87: LN-104344 | B87: CUS-204344 | C87: Gloria | D87: Cruz | E87: Rosales | F87: 64 | G87: Female | H87: Cebu City | I87: Region VII (Central Visayas) | J87: 44940 | K87: 44959 | L87: MPV/Van | M87: Toyota | N87: Innova | O87: 2190000 | P87: 654700 | Q87: 1535300 | R87: 36 | S87: 6.44 | T87: 50886.67 | U87: Approved | V87: Defaulted | W87: 1628373.4 | X87: 203546.52 | Y87: 1831920 | Z87: 116 | AA87: Over 90 Days | AB87: Cavite | AC87: F. Lacson | AD87: Monthly | AE87: 70.11 | AF87: 4 | AG87: High Risk | AH87: 19 | AI87: =IF(F87<25,"18-24",IF(F87<35,"25-34",IF(F87<45,"35-44",IF(F87<55,"45-54",IF(F87<65,"55-64","65+"))))) -> 55-64 | AJ87: =YEAR(tbl_LoanData[[#This Row],[Application Date]]) -> 2023 | AK87: =TEXT(tbl_LoanData[[#This Row],[Application Date]],"MMMM") -> January | AL87: =DATE(YEAR(tbl_LoanData[[#This Row],[Application Date]]),MONTH(tbl_LoanData[[#This Row],[Application Date]]),1) -> 44927 | AM87: =IF(AND(tbl_LoanData[[#This Row],[Application Date]]>=EOMONTH(TODAY(),-1)+1,tbl_LoanData[[#This Row],[Application Date]]<=TODAY()),tbl_LoanData[[#This Row],[Loan Amount]],0) -> 0 | AN87: =tbl_LoanData[[#This Row],[Amount Paid]]-(Q87-X87) -> 296619.96 | AO87: =IF(tbl_LoanData[[#This Row],[Application Status]]="Approved",1,0) -> 1 | AP87: =IF(AND(J87>=DATE(YEAR(TODAY()),MONTH(TODAY()),1),J87<=TODAY()),"Current MTD",IF(AND(J87>=EOMONTH(TODAY(),-2)+1,J87<=EOMONTH(TODAY(),-1)),"Previous MTD","")) | AQ87: =IF(AND(J87>=DATE(YEAR(TODAY()),MONTH(TODAY()),1),J87<=TODAY()),TEXT(DATE(YEAR(TODAY()),MONTH(TODAY()),1),"mmm d")&"–"&DAY(TODAY()),IF(AND(J87>=EOMONTH(TODAY(),-2)+1,J87<=EOMONTH(TODAY(),-1)),""&TEXT(EOMONTH(TODAY(),-2)+1,"mmm d")&"–"&DAY(TODAY()),""))
A88: LN-104350 | B88: CUS-204350 | C88: Kevin | D88: Cruz | E88: Lazaro | F88: 37 | G88: Male | H88: Legazpi | I88: Region V (Bicol Region) | J88: 44953 | L88: Sedan | M88: Mitsubishi | N88: Mirage G4 | O88: 1001000 | P88: 141500 | Q88: 859500 | R88: 36 | S88: 14.93 | T88: 34568.61 | U88: Pending | V88: Not Applicable | W88: 0 | X88: 0 | Y88: 1244470.1 | Z88: 0 | AA88: Not Applicable | AB88: Iloilo | AC88: C. Villareal | AD88: Monthly | AE88: 85.86 | AF88: 0 | AG88: Not Applicable | AI88: =IF(F88<25,"18-24",IF(F88<35,"25-34",IF(F88<45,"35-44",IF(F88<55,"45-54",IF(F88<65,"55-64","65+"))))) -> 35-44 | AJ88: =YEAR(tbl_LoanData[[#This Row],[Application Date]]) -> 2023 | AK88: =TEXT(tbl_LoanData[[#This Row],[Application Date]],"MMMM") -> January | AL88: =DATE(YEAR(tbl_LoanData[[#This Row],[Application Date]]),MONTH(tbl_LoanData[[#This Row],[Application Date]]),1) -> 44927 | AM88: =IF(AND(tbl_LoanData[[#This Row],[Application Date]]>=EOMONTH(TODAY(),-1)+1,tbl_LoanData[[#This Row],[Application Date]]<=TODAY()),tbl_LoanData[[#This Row],[Loan Amount]],0) -> 0 | AN88: =tbl_LoanData[[#This Row],[Amount Paid]]-(Q88-X88) -> -859500 | AO88: =IF(tbl_LoanData[[#This Row],[Application Status]]="Approved",1,0) -> 0 | AP88: =IF(AND(J88>=DATE(YEAR(TODAY()),MONTH(TODAY()),1),J88<=TODAY()),"Current MTD",IF(AND(J88>=EOMONTH(TODAY(),-2)+1,J88<=EOMONTH(TODAY(),-1)),"Previous MTD","")) | AQ88: =IF(AND(J88>=DATE(YEAR(TODAY()),MONTH(TODAY()),1),J88<=TODAY()),TEXT(DATE(YEAR(TODAY()),MONTH(TODAY()),1),"mmm d")&"–"&DAY(TODAY()),IF(AND(J88>=EOMONTH(TODAY(),-2)+1,J88<=EOMONTH(TODAY(),-1)),""&TEXT(EOMONTH(TODAY(),-2)+1,"mmm d")&"–"&DAY(TODAY()),""))
A89: LN-104357 | B89: CUS-204357 | C89: Michael | D89: Bautista | E89: Tolentino | F89: 41 | G89: Male | H89: Paranaque | I89: NCR | J89: 44954 | K89: 44969 | L89: MPV/Van | M89: Nissan | N89: Urvan | O89: 1159000 | P89: 340500 | Q89: 818500 | R89: 36 | S89: 10.21 | T89: 29700.18 | U89: Approved | V89: Closed - Fully Paid | W89: 1069206.6 | X89: 0 | Y89: 1069206.6 | Z89: 0 | AA89: Current | AB89: Pampanga | AC89: F. Lacson | AD89: Monthly | AE89: 70.62 | AF89: 0 | AG89: Low Risk | AH89: 15 | AI89: =IF(F89<25,"18-24",IF(F89<35,"25-34",IF(F89<45,"35-44",IF(F89<55,"45-54",IF(F89<65,"55-64","65+"))))) -> 35-44 | AJ89: =YEAR(tbl_LoanData[[#This Row],[Application Date]]) -> 2023 | AK89: =TEXT(tbl_LoanData[[#This Row],[Application Date]],"MMMM") -> January | AL89: =DATE(YEAR(tbl_LoanData[[#This Row],[Application Date]]),MONTH(tbl_LoanData[[#This Row],[Application Date]]),1) -> 44927 | AM89: =IF(AND(tbl_LoanData[[#This Row],[Application Date]]>=EOMONTH(TODAY(),-1)+1,tbl_LoanData[[#This Row],[Application Date]]<=TODAY()),tbl_LoanData[[#This Row],[Loan Amount]],0) -> 0 | AN89: =tbl_LoanData[[#This Row],[Amount Paid]]-(Q89-X89) -> 250706.55 | AO89: =IF(tbl_LoanData[[#This Row],[Application Status]]="Approved",1,0) -> 1 | AP89: =IF(AND(J89>=DATE(YEAR(TODAY()),MONTH(TODAY()),1),J89<=TODAY()),"Current MTD",IF(AND(J89>=EOMONTH(TODAY(),-2)+1,J89<=EOMONTH(TODAY(),-1)),"Previous MTD","")) | AQ89: =IF(AND(J89>=DATE(YEAR(TODAY()),MONTH(TODAY()),1),J89<=TODAY()),TEXT(DATE(YEAR(TODAY()),MONTH(TODAY()),1),"mmm d")&"–"&DAY(TODAY()),IF(AND(J89>=EOMONTH(TODAY(),-2)+1,J89<=EOMONTH(TODAY(),-1)),""&TEXT(EOMONTH(TODAY(),-2)+1,"mmm d")&"–"&DAY(TODAY()),""))
A90: LN-104381 | B90: CUS-204381 | C90: Mark | D90: Villanueva | E90: Cortez | F90: 57 | G90: Male | H90: Iloilo City | I90: Region VI (Western Visayas) | J90: 44950 | K90: 44961 | L90: Truck | M90: Isuzu | N90: ELF | O90: 3147000 | P90: 361900 | Q90: 2785100 | R90: 36 | S90: 10.14 | T90: 100897.98 | U90: Approved | V90: Defaulted | W90: 3531429.3 | X90: 100898.12 | Y90: 3632327.4 | Z90: 28 | AA90: 1-30 Days | AB90: Cebu | AC90: F. Lacson | AD90: Monthly | AE90: 88.5 | AF90: 1 | AG90: Low Risk | AH90: 11 | AI90: =IF(F90<25,"18-24",IF(F90<35,"25-34",IF(F90<45,"35-44",IF(F90<55,"45-54",IF(F90<65,"55-64","65+"))))) -> 55-64 | AJ90: =YEAR(tbl_LoanData[[#This Row],[Application Date]]) -> 2023 | AK90: =TEXT(tbl_LoanData[[#This Row],[Application Date]],"MMMM") -> January | AL90: =DATE(YEAR(tbl_LoanData[[#This Row],[Application Date]]),MONTH(tbl_LoanData[[#This Row],[Application Date]]),1) -> 44927 | AM90: =IF(AND(tbl_LoanData[[#This Row],[Application Date]]>=EOMONTH(TODAY(),-1)+1,tbl_LoanData[[#This Row],[Application Date]]<=TODAY()),tbl_LoanData[[#This Row],[Loan Amount]],0) -> 0 | AN90: =tbl_LoanData[[#This Row],[Amount Paid]]-(Q90-X90) -> 847227.42 | AO90: =IF(tbl_LoanData[[#This Row],[Application Status]]="Approved",1,0) -> 1 | AP90: =IF(AND(J90>=DATE(YEAR(TODAY()),MONTH(TODAY()),1),J90<=TODAY()),"Current MTD",IF(AND(J90>=EOMONTH(TODAY(),-2)+1,J90<=EOMONTH(TODAY(),-1)),"Previous MTD","")) | AQ90: =IF(AND(J90>=DATE(YEAR(TODAY()),MONTH(TODAY()),1),J90<=TODAY()),TEXT(DATE(YEAR(TODAY()),MONTH(TODAY()),1),"mmm d")&"–"&DAY(TODAY()),IF(AND(J90>=EOMONTH(TODAY(),-2)+1,J90<=EOMONTH(TODAY(),-1)),""&TEXT(EOMONTH(TODAY(),-2)+1,"mmm d")&"–"&DAY(TODAY()),""))
A91: LN-104408 | B91: CUS-204408 | C91: Gloria | D91: Torres | E91: Fernandez | F91: 62 | G91: Female | H91: Lapu-Lapu | I91: Region VII (Central Visayas) | J91: 44953 | K91: 44964 | L91: SUV | M91: Kia | N91: Sportage | O91: 2431000 | P91: 921600 | Q91: 1509400 | R91: 60 | S91: 10.99 | T91: 38980.25 | U91: Approved | V91: Active | W91: 1637170.5 | X91: 701644.8 | Y91: 2338815.3 | Z91: 0 | AA91: Current | AB91: Cavite | AC91: G. Bunag | AD91: Monthly | AE91: 62.09 | AF91: 0 | AG91: Low Risk | AH91: 11 | AI91: =IF(F91<25,"18-24",IF(F91<35,"25-34",IF(F91<45,"35-44",IF(F91<55,"45-54",IF(F91<65,"55-64","65+"))))) -> 55-64 | AJ91: =YEAR(tbl_LoanData[[#This Row],[Application Date]]) -> 2023 | AK91: =TEXT(tbl_LoanData[[#This Row],[Application Date]],"MMMM") -> January | AL91: =DATE(YEAR(tbl_LoanData[[#This Row],[Application Date]]),MONTH(tbl_LoanData[[#This Row],[Application Date]]),1) -> 44927 | AM91: =IF(AND(tbl_LoanData[[#This Row],[Application Date]]>=EOMONTH(TODAY(),-1)+1,tbl_LoanData[[#This Row],[Application Date]]<=TODAY()),tbl_LoanData[[#This Row],[Loan Amount]],0) -> 0 | AN91: =tbl_LoanData[[#This Row],[Amount Paid]]-(Q91-X91) -> 829415.3 | AO91: =IF(tbl_LoanData[[#This Row],[Application Status]]="Approved",1,0) -> 1 | AP91: =IF(AND(J91>=DATE(YEAR(TODAY()),MONTH(TODAY()),1),J91<=TODAY()),"Current MTD",IF(AND(J91>=EOMONTH(TODAY(),-2)+1,J91<=EOMONTH(TODAY(),-1)),"Previous MTD","")) | AQ91: =IF(AND(J91>=DATE(YEAR(TODAY()),MONTH(TODAY()),1),J91<=TODAY()),TEXT(DATE(YEAR(TODAY()),MONTH(TODAY()),1),"mmm d")&"–"&DAY(TODAY()),IF(AND(J91>=EOMONTH(TODAY(),-2)+1,J91<=EOMONTH(TODAY(),-1)),""&TEXT(EOMONTH(TODAY(),-2)+1,"mmm d")&"–"&DAY(TODAY()),""))
A92: LN-104417 | B92: CUS-204417 | C92: Leon | D92: Del Rosario | E92: Tolentino | F92: 36 | G92: Male | H92: Tarlac City | I92: Region III (Central Luzon) | J92: 44952 | K92: 44963 | L92: Sedan | M92: Honda | N92: Civic | O92: 1055000 | P92: 357300 | Q92: 697700 | R92: 24 | S92: 10.29 | T92: 35053.61 | U92: Approved | V92: Closed - Fully Paid | W92: 841286.66 | X92: 0 | Y92: 841286.66 | Z92: 0 | AA92: Current | AB92: Davao | AC92: A. Ramirez | AD92: Monthly | AE92: 66.13 | AF92: 0 | AG92: Low Risk | AH92: 11 | AI92: =IF(F92<25,"18-24",IF(F92<35,"25-34",IF(F92<45,"35-44",IF(F92<55,"45-54",IF(F92<65,"55-64","65+"))))) -> 35-44 | AJ92: =YEAR(tbl_LoanData[[#This Row],[Application Date]]) -> 2023 | AK92: =TEXT(tbl_LoanData[[#This Row],[Application Date]],"MMMM") -> January | AL92: =DATE(YEAR(tbl_LoanData[[#This Row],[Application Date]]),MONTH(tbl_LoanData[[#This Row],[Application Date]]),1) -> 44927 | AM92: =IF(AND(tbl_LoanData[[#This Row],[Application Date]]>=EOMONTH(TODAY(),-1)+1,tbl_LoanData[[#This Row],[Application Date]]<=TODAY()),tbl_LoanData[[#This Row],[Loan Amount]],0) -> 0 | AN92: =tbl_LoanData[[#This Row],[Amount Paid]]-(Q92-X92) -> 143586.66 | AO92: =IF(tbl_LoanData[[#This Row],[Application Status]]="Approved",1,0) -> 1 | AP92: =IF(AND(J92>=DATE(YEAR(TODAY()),MONTH(TODAY()),1),J92<=TODAY()),"Current MTD",IF(AND(J92>=EOMONTH(TODAY(),-2)+1,J92<=EOMONTH(TODAY(),-1)),"Previous MTD","")) | AQ92: =IF(AND(J92>=DATE(YEAR(TODAY()),MONTH(TODAY()),1),J92<=TODAY()),TEXT(DATE(YEAR(TODAY()),MONTH(TODAY()),1),"mmm d")&"–"&DAY(TODAY()),IF(AND(J92>=EOMONTH(TODAY(),-2)+1,J92<=EOMONTH(TODAY(),-1)),""&TEXT(EOMONTH(TODAY(),-2)+1,"mmm d")&"–"&DAY(TODAY()),""))
A93: LN-104419 | B93: CUS-204419 | C93: Bienvenido | D93: Castillo | E93: Macaraeg | F93: 60 | G93: Male | H93: Pasig | I93: NCR | J93: 44950 | K93: 44966 | L93: MPV/Van | M93: Honda | N93: Mobilio | O93: 927000 | P93: 111000 | Q93: 816000 | R93: 48 | S93: 10.18 | T93: 23922.4 | U93: Approved | V93: Active | W93: 1004740.8 | X93: 143534.4 | Y93: 1148275.2 | Z93: 0 | AA93: Current | AB93: Cebu | AC93: G. Bunag | AD93: Monthly | AE93: 88.03 | AF93: 0 | AG93: Low Risk | AH93: 16 | AI93: =IF(F93<25,"18-24",IF(F93<35,"25-34",IF(F93<45,"35-44",IF(F93<55,"45-54",IF(F93<65,"55-64","65+"))))) -> 55-64 | AJ93: =YEAR(tbl_LoanData[[#This Row],[Application Date]]) -> 2023 | AK93: =TEXT(tbl_LoanData[[#This Row],[Application Date]],"MMMM") -> January | AL93: =DATE(YEAR(tbl_LoanData[[#This Row],[Application Date]]),MONTH(tbl_LoanData[[#This Row],[Application Date]]),1) -> 44927 | AM93: =IF(AND(tbl_LoanData[[#This Row],[Application Date]]>=EOMONTH(TODAY(),-1)+1,tbl_LoanData[[#This Row],[Application Date]]<=TODAY()),tbl_LoanData[[#This Row],[Loan Amount]],0) -> 0 | AN93: =tbl_LoanData[[#This Row],[Amount Paid]]-(Q93-X93) -> 332275.2 | AO93: =IF(tbl_LoanData[[#This Row],[Application Status]]="Approved",1,0) -> 1 | AP93: =IF(AND(J93>=DATE(YEAR(TODAY()),MONTH(TODAY()),1),J93<=TODAY()),"Current MTD",IF(AND(J93>=EOMONTH(TODAY(),-2)+1,J93<=EOMONTH(TODAY(),-1)),"Previous MTD","")) | AQ93: =IF(AND(J93>=DATE(YEAR(TODAY()),MONTH(TODAY()),1),J93<=TODAY()),TEXT(DATE(YEAR(TODAY()),MONTH(TODAY()),1),"mmm d")&"–"&DAY(TODAY()),IF(AND(J93>=EOMONTH(TODAY(),-2)+1,J93<=EOMONTH(TODAY(),-1)),""&TEXT(EOMONTH(TODAY(),-2)+1,"mmm d")&"–"&DAY(TODAY()),""))
A94: LN-104553 | B94: CUS-204553 | C94: Josefa | D94: Pascual | E94: Wenceslao | F94: 54 | G94: Female | H94: Mandaluyong | I94: NCR | J94: 44937 | K94: 44942 | L94: SUV | M94: Mitsubishi | N94: Montero Sport | O94: 1133000 | P94: 246200 | Q94: 886800 | R94: 24 | S94: 12.9 | T94: 46483.1 | U94: Approved | V94: Closed - Fully Paid | W94: 1115594.4 | X94: 0 | Y94: 1115594.4 | Z94: 0 | AA94: Current | AB94: Makati | AC94: B. Santiago | AD94: Monthly | AE94: 78.27 | AF94: 0 | AG94: Low Risk | AH94: 5 | AI94: =IF(F94<25,"18-24",IF(F94<35,"25-34",IF(F94<45,"35-44",IF(F94<55,"45-54",IF(F94<65,"55-64","65+"))))) -> 45-54 | AJ94: =YEAR(tbl_LoanData[[#This Row],[Application Date]]) -> 2023 | AK94: =TEXT(tbl_LoanData[[#This Row],[Application Date]],"MMMM") -> January | AL94: =DATE(YEAR(tbl_LoanData[[#This Row],[Application Date]]),MONTH(tbl_LoanData[[#This Row],[Application Date]]),1) -> 44927 | AM94: =IF(AND(tbl_LoanData[[#This Row],[Application Date]]>=EOMONTH(TODAY(),-1)+1,tbl_LoanData[[#This Row],[Application Date]]<=TODAY()),tbl_LoanData[[#This Row],[Loan Amount]],0) -> 0 | AN94: =tbl_LoanData[[#This Row],[Amount Paid]]-(Q94-X94) -> 228794.4 | AO94: =IF(tbl_LoanData[[#This Row],[Application Status]]="Approved",1,0) -> 1 | AP94: =IF(AND(J94>=DATE(YEAR(TODAY()),MONTH(TODAY()),1),J94<=TODAY()),"Current MTD",IF(AND(J94>=EOMONTH(TODAY(),-2)+1,J94<=EOMONTH(TODAY(),-1)),"Previous MTD","")) | AQ94: =IF(AND(J94>=DATE(YEAR(TODAY()),MONTH(TODAY()),1),J94<=TODAY()),TEXT(DATE(YEAR(TODAY()),MONTH(TODAY()),1),"mmm d")&"–"&DAY(TODAY()),IF(AND(J94>=EOMONTH(TODAY(),-2)+1,J94<=EOMONTH(TODAY(),-1)),""&TEXT(EOMONTH(TODAY(),-2)+1,"mmm d")&"–"&DAY(TODAY()),""))
A95: LN-104568 | B95: CUS-204568 | C95: Josefa | D95: Cruz | E95: Dela Cruz | F95: 61 | G95: Female | H95: San Pablo | I95: Region IV-A (CALABARZON) | J95: 44934 | L95: SUV | M95: Toyota | N95: RAV4 | O95: 2297000 | P95: 856900 | Q95: 1440100 | R95: 24 | S95: 6.92 | T95: 68308.74 | U95: Pending | V95: Not Applicable | W95: 0 | X95: 0 | Y95: 1639409.8 | Z95: 0 | AA95: Not Applicable | AB95: Pampanga | AC95: G. Bunag | AD95: Monthly | AE95: 62.69 | AF95: 0 | AG95: Not Applicable | AI95: =IF(F95<25,"18-24",IF(F95<35,"25-34",IF(F95<45,"35-44",IF(F95<55,"45-54",IF(F95<65,"55-64","65+"))))) -> 55-64 | AJ95: =YEAR(tbl_LoanData[[#This Row],[Application Date]]) -> 2023 | AK95: =TEXT(tbl_LoanData[[#This Row],[Application Date]],"MMMM") -> January | AL95: =DATE(YEAR(tbl_LoanData[[#This Row],[Application Date]]),MONTH(tbl_LoanData[[#This Row],[Application Date]]),1) -> 44927 | AM95: =IF(AND(tbl_LoanData[[#This Row],[Application Date]]>=EOMONTH(TODAY(),-1)+1,tbl_LoanData[[#This Row],[Application Date]]<=TODAY()),tbl_LoanData[[#This Row],[Loan Amount]],0) -> 0 | AN95: =tbl_LoanData[[#This Row],[Amount Paid]]-(Q95-X95) -> -1440100 | AO95: =IF(tbl_LoanData[[#This Row],[Application Status]]="Approved",1,0) -> 0 | AP95: =IF(AND(J95>=DATE(YEAR(TODAY()),MONTH(TODAY()),1),J95<=TODAY()),"Current MTD",IF(AND(J95>=EOMONTH(TODAY(),-2)+1,J95<=EOMONTH(TODAY(),-1)),"Previous MTD","")) | AQ95: =IF(AND(J95>=DATE(YEAR(TODAY()),MONTH(TODAY()),1),J95<=TODAY()),TEXT(DATE(YEAR(TODAY()),MONTH(TODAY()),1),"mmm d")&"–"&DAY(TODAY()),IF(AND(J95>=EOMONTH(TODAY(),-2)+1,J95<=EOMONTH(TODAY(),-1)),""&TEXT(EOMONTH(TODAY(),-2)+1,"mmm d")&"–"&DAY(TODAY()),""))
A96: LN-104615 | B96: CUS-204615 | C96: Antonio | D96: Aguilar | E96: Ybanez | F96: 33 | G96: Male | H96: Las Pinas | I96: NCR | J96: 44931 | K96: 44940 | L96: Sedan | M96: Nissan | N96: Sylphy | O96: 1276000 | P96: 459900 | Q96: 816100 | R96: 48 | S96: 5.93 | T96: 21034.98 | U96: Approved | V96: Active | W96: 778294.26 | X96: 231384.66 | Y96: 1009678.9 | Z96: 174 | AA96: Over 90 Days | AB96: Cavite | AC96: E. Ferrer | AD96: Monthly | AE96: 63.96 | AF96: 6 | AG96: High Risk | AH96: 9 | AI96: =IF(F96<25,"18-24",IF(F96<35,"25-34",IF(F96<45,"35-44",IF(F96<55,"45-54",IF(F96<65,"55-64","65+"))))) -> 25-34 | AJ96: =YEAR(tbl_LoanData[[#This Row],[Application Date]]) -> 2023 | AK96: =TEXT(tbl_LoanData[[#This Row],[Application Date]],"MMMM") -> January | AL96: =DATE(YEAR(tbl_LoanData[[#This Row],[Application Date]]),MONTH(tbl_LoanData[[#This Row],[Application Date]]),1) -> 44927 | AM96: =IF(AND(tbl_LoanData[[#This Row],[Application Date]]>=EOMONTH(TODAY(),-1)+1,tbl_LoanData[[#This Row],[Application Date]]<=TODAY()),tbl_LoanData[[#This Row],[Loan Amount]],0) -> 0 | AN96: =tbl_LoanData[[#This Row],[Amount Paid]]-(Q96-X96) -> 193578.92 | AO96: =IF(tbl_LoanData[[#This Row],[Application Status]]="Approved",1,0) -> 1 | AP96: =IF(AND(J96>=DATE(YEAR(TODAY()),MONTH(TODAY()),1),J96<=TODAY()),"Current MTD",IF(AND(J96>=EOMONTH(TODAY(),-2)+1,J96<=EOMONTH(TODAY(),-1)),"Previous MTD","")) | AQ96: =IF(AND(J96>=DATE(YEAR(TODAY()),MONTH(TODAY()),1),J96<=TODAY()),TEXT(DATE(YEAR(TODAY()),MONTH(TODAY()),1),"mmm d")&"–"&DAY(TODAY()),IF(AND(J96>=EOMONTH(TODAY(),-2)+1,J96<=EOMONTH(TODAY(),-1)),""&TEXT(EOMONTH(TODAY(),-2)+1,"mmm d")&"–"&DAY(TODAY()),""))
A97: LN-104698 | B97: CUS-204698 | C97: Juan | D97: Del Rosario | E97: Tolentino | F97: 61 | G97: Male | H97: Santa Rosa | I97: Region IV-A (CALABARZON) | J97: 44937 | K97: 44953 | L97: Motorcycle | M97: Suzuki | N97: Raider R150 | O97: 76000 | P97: 12700 | Q97: 63300 | R97: 24 | S97: 12.52 | T97: 3297.93 | U97: Approved | V97: Closed - Fully Paid | W97: 79150.32 | X97: 0 | Y97: 79150.32 | Z97: 0 | AA97: Current | AB97: Baguio | AC97: E. Ferrer | AD97: Monthly | AE97: 83.29 | AF97: 0 | AG97: Low Risk | AH97: 16 | AI97: =IF(F97<25,"18-24",IF(F97<35,"25-34",IF(F97<45,"35-44",IF(F97<55,"45-54",IF(F97<65,"55-64","65+"))))) -> 55-64 | AJ97: =YEAR(tbl_LoanData[[#This Row],[Application Date]]) -> 2023 | AK97: =TEXT(tbl_LoanData[[#This Row],[Application Date]],"MMMM") -> January | AL97: =DATE(YEAR(tbl_LoanData[[#This Row],[Application Date]]),MONTH(tbl_LoanData[[#This Row],[Application Date]]),1) -> 44927 | AM97: =IF(AND(tbl_LoanData[[#This Row],[Application Date]]>=EOMONTH(TODAY(),-1)+1,tbl_LoanData[[#This Row],[Application Date]]<=TODAY()),tbl_LoanData[[#This Row],[Loan Amount]],0) -> 0 | AN97: =tbl_LoanData[[#This Row],[Amount Paid]]-(Q97-X97) -> 15850.32 | AO97: =IF(tbl_LoanData[[#This Row],[Application Status]]="Approved",1,0) -> 1 | AP97: =IF(AND(J97>=DATE(YEAR(TODAY()),MONTH(TODAY()),1),J97<=TODAY()),"Current MTD",IF(AND(J97>=EOMONTH(TODAY(),-2)+1,J97<=EOMONTH(TODAY(),-1)),"Previous MTD","")) | AQ97: =IF(AND(J97>=DATE(YEAR(TODAY()),MONTH(TODAY()),1),J97<=TODAY()),TEXT(DATE(YEAR(TODAY()),MONTH(TODAY()),1),"mmm d")&"–"&DAY(TODAY()),IF(AND(J97>=EOMONTH(TODAY(),-2)+1,J97<=EOMONTH(TODAY(),-1)),""&TEXT(EOMONTH(TODAY(),-2)+1,"mmm d")&"–"&DAY(TODAY()),""))
A98: LN-104797 | B98: CUS-204797 | C98: Federico | D98: Reyes | E98: Rosario | F98: 48 | G98: Male | H98: Olongapo | I98: Region III (Central Luzon) | J98: 44930 | K98: 44934 | L98: SUV | M98: Hyundai | N98: Creta | O98: 2271000 | P98: 459000 | Q98: 1812000 | R98: 24 | S98: 7.37 | T98: 86628.7 | U98: Approved | V98: Defaulted | W98: 1992460.1 | X98: 86628.7 | Y98: 2079088.8 | Z98: 30 | AA98: 1-30 Days | AB98: Cebu | AC98: E. Ferrer | AD98: Monthly | AE98: 79.79 | AF98: 1 | AG98: Low Risk | AH98: 4 | AI98: =IF(F98<25,"18-24",IF(F98<35,"25-34",IF(F98<45,"35-44",IF(F98<55,"45-54",IF(F98<65,"55-64","65+"))))) -> 45-54 | AJ98: =YEAR(tbl_LoanData[[#This Row],[Application Date]]) -> 2023 | AK98: =TEXT(tbl_LoanData[[#This Row],[Application Date]],"MMMM") -> January | AL98: =DATE(YEAR(tbl_LoanData[[#This Row],[Application Date]]),MONTH(tbl_LoanData[[#This Row],[Application Date]]),1) -> 44927 | AM98: =IF(AND(tbl_LoanData[[#This Row],[Application Date]]>=EOMONTH(TODAY(),-1)+1,tbl_LoanData[[#This Row],[Application Date]]<=TODAY()),tbl_LoanData[[#This Row],[Loan Amount]],0) -> 0 | AN98: =tbl_LoanData[[#This Row],[Amount Paid]]-(Q98-X98) -> 267088.8 | AO98: =IF(tbl_LoanData[[#This Row],[Application Status]]="Approved",1,0) -> 1 | AP98: =IF(AND(J98>=DATE(YEAR(TODAY()),MONTH(TODAY()),1),J98<=TODAY()),"Current MTD",IF(AND(J98>=EOMONTH(TODAY(),-2)+1,J98<=EOMONTH(TODAY(),-1)),"Previous MTD","")) | AQ98: =IF(AND(J98>=DATE(YEAR(TODAY()),MONTH(TODAY()),1),J98<=TODAY()),TEXT(DATE(YEAR(TODAY()),MONTH(TODAY()),1),"mmm d")&"–"&DAY(TODAY()),IF(AND(J98>=EOMONTH(TODAY(),-2)+1,J98<=EOMONTH(TODAY(),-1)),""&TEXT(EOMONTH(TODAY(),-2)+1,"mmm d")&"–"&DAY(TODAY()),""))
A99: LN-104809 | B99: CUS-204809 | C99: Leonor | D99: Torres | E99: Gonzales | F99: 44 | G99: Female | H99: Paranaque | I99: NCR | J99: 44945 | K99: 44954 | L99: Motorcycle | M99: Suzuki | N99: Skydrive | O99: 79000 | P99: 22700 | Q99: 56300 | R99: 24 | S99: 8.08 | T99: 2724.92 | U99: Approved | V99: Closed - Fully Paid | W99: 65398.08 | X99: 0 | Y99: 65398.08 | Z99: 0 | AA99: Current | AB99: Cavite | AC99: E. Ferrer | AD99: Monthly | AE99: 71.27 | AF99: 0 | AG99: Low Risk | AH99: 9 | AI99: =IF(F99<25,"18-24",IF(F99<35,"25-34",IF(F99<45,"35-44",IF(F99<55,"45-54",IF(F99<65,"55-64","65+"))))) -> 35-44 | AJ99: =YEAR(tbl_LoanData[[#This Row],[Application Date]]) -> 2023 | AK99: =TEXT(tbl_LoanData[[#This Row],[Application Date]],"MMMM") -> January | AL99: =DATE(YEAR(tbl_LoanData[[#This Row],[Application Date]]),MONTH(tbl_LoanData[[#This Row],[Application Date]]),1) -> 44927 | AM99: =IF(AND(tbl_LoanData[[#This Row],[Application Date]]>=EOMONTH(TODAY(),-1)+1,tbl_LoanData[[#This Row],[Application Date]]<=TODAY()),tbl_LoanData[[#This Row],[Loan Amount]],0) -> 0 | AN99: =tbl_LoanData[[#This Row],[Amount Paid]]-(Q99-X99) -> 9098.08 | AO99: =IF(tbl_LoanData[[#This Row],[Application Status]]="Approved",1,0) -> 1 | AP99: =IF(AND(J99>=DATE(YEAR(TODAY()),MONTH(TODAY()),1),J99<=TODAY()),"Current MTD",IF(AND(J99>=EOMONTH(TODAY(),-2)+1,J99<=EOMONTH(TODAY(),-1)),"Previous MTD","")) | AQ99: =IF(AND(J99>=DATE(YEAR(TODAY()),MONTH(TODAY()),1),J99<=TODAY()),TEXT(DATE(YEAR(TODAY()),MONTH(TODAY()),1),"mmm d")&"–"&DAY(TODAY()),IF(AND(J99>=EOMONTH(TODAY(),-2)+1,J99<=EOMONTH(TODAY(),-1)),""&TEXT(EOMONTH(TODAY(),-2)+1,"mmm d")&"–"&DAY(TODAY()),""))
A100: LN-104846 | B100: CUS-204846 | C100: Gil | D100: Bautista | E100: Macaraeg | F100: 52 | G100: Male | H100: General Santos | I100: Region XII (SOCCSKSARGEN) | J100: 44943 | K100: 44959 | L100: Sedan | M100: Hyundai | N100: Elantra | O100: 849000 | P100: 255600 | Q100: 593400 | R100: 36 | S100: 6.9 | T100: 19895.38 | U100: Approved | V100: Closed - Fully Paid | W100: 716233.8 | X100: 0 | Y100: 716233.8 | Z100: 0 | AA100: Current | AB100: Cebu | AC100: I. Cabrera | AD100: Monthly | AE100: 69.89 | AF100: 0 | AG100: Low Risk | AH100: 16 | AI100: =IF(F100<25,"18-24",IF(F100<35,"25-34",IF(F100<45,"35-44",IF(F100<55,"45-54",IF(F100<65,"55-64","65+"))))) -> 45-54 | AJ100: =YEAR(tbl_LoanData[[#This Row],[Application Date]]) -> 2023 | AK100: =TEXT(tbl_LoanData[[#This Row],[Application Date]],"MMMM") -> January | AL100: =DATE(YEAR(tbl_LoanData[[#This Row],[Application Date]]),MONTH(tbl_LoanData[[#This Row],[Application Date]]),1) -> 44927 | AM100: =IF(AND(tbl_LoanData[[#This Row],[Application Date]]>=EOMONTH(TODAY(),-1)+1,tbl_LoanData[[#This Row],[Application Date]]<=TODAY()),tbl_LoanData[[#This Row],[Loan Amount]],0) -> 0 | AN100: =tbl_LoanData[[#This Row],[Amount Paid]]-(Q100-X100) -> 122833.8 | AO100: =IF(tbl_LoanData[[#This Row],[Application Status]]="Approved",1,0) -> 1 | AP100: =IF(AND(J100>=DATE(YEAR(TODAY()),MONTH(TODAY()),1),J100<=TODAY()),"Current MTD",IF(AND(J100>=EOMONTH(TODAY(),-2)+1,J100<=EOMONTH(TODAY(),-1)),"Previous MTD","")) | AQ100: =IF(AND(J100>=DATE(YEAR(TODAY()),MONTH(TODAY()),1),J100<=TODAY()),TEXT(DATE(YEAR(TODAY()),MONTH(TODAY()),1),"mmm d")&"–"&DAY(TODAY()),IF(AND(J100>=EOMONTH(TODAY(),-2)+1,J100<=EOMONTH(TODAY(),-1)),""&TEXT(EOMONTH(TODAY(),-2)+1,"mmm d")&"–"&DAY(TODAY()),""))
A101: LN-104870 | B101: CUS-204870 | C101: Ramon | D101: Aguilar | E101: Wenceslao | F101: 35 | G101: Male | H101: Laoag | I101: Region I (Ilocos Region) | J101: 44931 | K101: 44949 | L101: Sedan | M101: Hyundai | N101: Accent | O101: 1514000 | P101: 340600 | Q101: 1173400 | R101: 36 | S101: 12.16 | T101: 44484.9 | U101: Approved | V101: Defaulted | W101: 1556971.5 | X101: 44484.82 | Y101: 1601456.3 | Z101: 31 | AA101: 31-60 Days | AB101: Makati | AC101: J. Espino | AD101: Monthly | AE101: 77.5 | AF101: 1 | AG101: Medium RIsk | AH101: 18 | AI101: =IF(F101<25,"18-24",IF(F101<35,"25-34",IF(F101<45,"35-44",IF(F101<55,"45-54",IF(F101<65,"55-64","65+"))))) -> 35-44 | AJ101: =YEAR(tbl_LoanData[[#This Row],[Application Date]]) -> 2023 | AK101: =TEXT(tbl_LoanData[[#This Row],[Application Date]],"MMMM") -> January | AL101: =DATE(YEAR(tbl_LoanData[[#This Row],[Application Date]]),MONTH(tbl_LoanData[[#This Row],[Application Date]]),1) -> 44927 | AM101: =IF(AND(tbl_LoanData[[#This Row],[Application Date]]>=EOMONTH(TODAY(),-1)+1,tbl_LoanData[[#This Row],[Application Date]]<=TODAY()),tbl_LoanData[[#This Row],[Loan Amount]],0) -> 0 | AN101: =tbl_LoanData[[#This Row],[Amount Paid]]-(Q101-X101) -> 428056.32 | AO101: =IF(tbl_LoanData[[#This Row],[Application Status]]="Approved",1,0) -> 1 | AP101: =IF(AND(J101>=DATE(YEAR(TODAY()),MONTH(TODAY()),1),J101<=TODAY()),"Current MTD",IF(AND(J101>=EOMONTH(TODAY(),-2)+1,J101<=EOMONTH(TODAY(),-1)),"Previous MTD","")) | AQ101: =IF(AND(J101>=DATE(YEAR(TODAY()),MONTH(TODAY()),1),J101<=TODAY()),TEXT(DATE(YEAR(TODAY()),MONTH(TODAY()),1),"mmm d")&"–"&DAY(TODAY()),IF(AND(J101>=EOMONTH(TODAY(),-2)+1,J101<=EOMONTH(TODAY(),-1)),""&TEXT(EOMONTH(TODAY(),-2)+1,"mmm d")&"–"&DAY(TODAY()),""))
A102: LN-104871 | B102: CUS-204871 | C102: Rafael | D102: Bautista | E102: Sarmiento | F102: 35 | G102: Male | H102: Olongapo | I102: Region III (Central Luzon) | J102: 44937 | K102: 44941 | L102: Truck | M102: Isuzu | N102: ELF | O102: 3317000 | P102: 1250200 | Q102: 2066800 | R102: 12 | S102: 12.57 | T102: 193883.06 | U102: Approved | V102: Closed - Fully Paid | W102: 2326596.8 | X102: 0 | Y102: 2326596.8 | Z102: 0 | AA102: Current | AB102: Quezon City | AC102: C. Villareal | AD102: Monthly | AE102: 62.31 | AF102: 0 | AG102: Low Risk | AH102: 4 | AI102: =IF(F102<25,"18-24",IF(F102<35,"25-34",IF(F102<45,"35-44",IF(F102<55,"45-54",IF(F102<65,"55-64","65+"))))) -> 35-44 | AJ102: =YEAR(tbl_LoanData[[#This Row],[Application Date]]) -> 2023 | AK102: =TEXT(tbl_LoanData[[#This Row],[Application Date]],"MMMM") -> January | AL102: =DATE(YEAR(tbl_LoanData[[#This Row],[Application Date]]),MONTH(tbl_LoanData[[#This Row],[Application Date]]),1) -> 44927 | AM102: =IF(AND(tbl_LoanData[[#This Row],[Application Date]]>=EOMONTH(TODAY(),-1)+1,tbl_LoanData[[#This Row],[Application Date]]<=TODAY()),tbl_LoanData[[#This Row],[Loan Amount]],0) -> 0 | AN102: =tbl_LoanData[[#This Row],[Amount Paid]]-(Q102-X102) -> 259796.76 | AO102: =IF(tbl_LoanData[[#This Row],[Application Status]]="Approved",1,0) -> 1 | AP102: =IF(AND(J102>=DATE(YEAR(TODAY()),MONTH(TODAY()),1),J102<=TODAY()),"Current MTD",IF(AND(J102>=EOMONTH(TODAY(),-2)+1,J102<=EOMONTH(TODAY(),-1)),"Previous MTD","")) | AQ102: =IF(AND(J102>=DATE(YEAR(TODAY()),MONTH(TODAY()),1),J102<=TODAY()),TEXT(DATE(YEAR(TODAY()),MONTH(TODAY()),1),"mmm d")&"–"&DAY(TODAY()),IF(AND(J102>=EOMONTH(TODAY(),-2)+1,J102<=EOMONTH(TODAY(),-1)),""&TEXT(EOMONTH(TODAY(),-2)+1,"mmm d")&"–"&DAY(TODAY()),""))
...
